Workbook
Name a: #REF!
Name A: 'DPK Import'!$C:$C
Name AA: #REF!
Name AA: #REF!
Name AA: #REF!
Name AA: #REF!
Name AA: #REF!
Name AA: #REF!
Name AA: #REF!
Name AA: #REF!
Name AA: #REF!
Name AA: #REF!
Name AA: #REF!
Name AA: #REF!
Name AA: #REF!
Name AA: #REF!
Name AA: #REF!
Name AA: #REF!
Name AA: #REF!
Name AA: #REF!
Name AGO: #REF!
Name AGO: #REF!
Name AGO: #REF!
Name AGO: #REF!
Name AGO: #REF!
Name AGO: #REF!
Name AGO: #REF!
Name AGO: #REF!
Name AGO: #REF!
Name AGO: #REF!
Name AGO: #REF!
Name AGO: #REF!
Name AGO: #REF!
Name AGO: #REF!
Name AGO: #REF!
Name AGO: #REF!
Name AGO: #REF!
Name AGO: #REF!
Name AP_END: '[1]Client Data'!$D$6
Name b: #REF!
Name b: #REF!
Name b: #REF!
Name b: #REF!
Name b: #REF!
Name b: #REF!
Name b: #REF!
Name b: #REF!
Name b: #REF!
Name b: #REF!
Name b: #REF!
Name b: #REF!
Name b: #REF!
Name b: #REF!
Name bsnotes: #REF!
Name D: #REF!
Name Data: [2]Sheet1!$C$5:$V$185
Name DDD: #REF!
Name DDD: #REF!
Name DDD: #REF!
Name DDD: #REF!

Sheet Exchange Rates Feb 23
C3: 15 March - 14 April 2023
C4: Importer | D4: Vessel Name | E4: Last dates of discharge | F4: Deemed Exchange Rate Date | G4: Bank 1 | H4: Bank 2 | I4: Bank 3 | J4: Average Rate for Commercial Banks | K4: CBK | L4: Average | M4: Product | N4: Terminal | O4: NoR | P4: 43733 | R4: 43762 | T4: 43795
A5: 1 | C5: TEXAS ENERGY | D5: MT Sealegend | E5: 44971 | F5: 44971 | G5: 134.4288 | H5: 131.43 | I5: 133.5 | J5: =AVERAGE(G5:I5) -> 133.1196 | L5: =AVERAGE(J5:K5) -> 133.1196 | M5: AGO K02/2023 | N5: KOSF/KPRL
A6: 2 | C6: ORYXENERGIES | D6: MT STI LOTUS | E6: 44988 | F6: 44988 | G6: 137.0016 | H6: 136.99 | I6: 137.75 | J6: =AVERAGE(G6:I6) -> 137.2472 | L6: =AVERAGE(J6:K6) -> 137.2472 | M6: AGO K03/2023 | N6: KOSF/KPRL
A7: 3 | C7: E3 ENERGY | D7: MT Serengeti | E7: 44983 | F7: 44984 | G7: 136.0368 | H7: 133.95 | I7: 136.9 | J7: =AVERAGE(G7:I7) -> 135.62893 | L7: =AVERAGE(J7:K7) -> 135.62893 | M7: AGO V02/2023 | N7: KOSF | O7: 43808.662 | P7: AGO | Q7: V08/2019
A8: 4 | C8: E3 ENERGY | D8: MT Serengeti | E8: 44983 | F8: 44984 | G8: 136.0368 | H8: 133.95 | I8: 136.9 | J8: =AVERAGE(G8:I8) -> 135.62893 | L8: =AVERAGE(J8:K8) -> 135.62893 | M8: AGO V02/2023 | N8: VTTI
A9: 5 | C9: E3 ENERGY | D9: MT Nakhal Silver | E9: 44975 | F9: 44977 | G9: 134.7504 | H9: 132.05 | I9: 134.9 | J9: =AVERAGE(G9:I9) -> 133.90013 | L9: =AVERAGE(J9:K9) -> 133.90013 | M9: JETA-1 K03/2023 | N9: KOSF/KPRL
A10: 6 | C10: ORYXENERGIES | D10: MT Hafnia Lupus | E10: 44994 | F10: 44994 | G10: 139.2328 | H10: 138.02 | I10: 138.95 | J10: =AVERAGE(G10:I10) -> 138.73427 | L10: =AVERAGE(J10:K10) -> 138.73427 | M10: JETA-1K04/2023 | N10: KOSF
A11: 7 | C11: GULF ENERGY | D11: Mt Front Vega | E11: 44978 | F11: 44978 | G11: 135.1792 | H11: 132.56 | I11: 134.9 | J11: =AVERAGE(G11:I11) -> 134.21307 | L11: =AVERAGE(J11:K11) -> 134.21307 | M11: PMS K03/2023 | N11: KOSF/KPRL
A12: 8 | C12: GULF ENERGY | D12: MT Clearocean Mesquite - TOP UP | E12: 44980 | F12: 44980 | G12: 135.608 | H12: 133.23 | I12: 135.4 | J12: =AVERAGE(G12:I12) -> 134.746 | L12: =AVERAGE(J12:K12) -> 134.746 | M12: PMS K03/2023 | N12: KOSF
A13: 9 | C13: E3 ENERGY | D13: MT Sanmar Sangeet | E13: 44993 | F13: 44993 | G13: 137.8592 | H13: 137.57 | I13: 138.95 | J13: =AVERAGE(G13:I13) -> 138.1264 | L13: =AVERAGE(J13:K13) -> 138.1264 | M13: MSP K04/2023 | N13: KOSF/KPRL
A14: 10 | C14: E3 ENERGY | D14: MT PIS Polaris | E14: 44972 | F14: 44972 | G14: 134.536 | H14: 131.53 | I14: 133.5 | J14: =AVERAGE(G14:I14) -> 133.18867 | L14: =AVERAGE(J14:K14) -> 133.18867 | M14: S02/2023 AGO | N14: SOT
A15: 11 | C15: E3 ENERGY | D15: MT PIS Polaris | E15: 44968 | F15: 44970 | G15: 134.3216 | H15: 131.33 | I15: 133 | J15: =AVERAGE(G15:I15) -> 132.88387 | L15: =AVERAGE(J15:K15) -> 132.88387 | M15: S02/2023 PMS | N15: KOSF
A16: 12 | C16: E3 ENERGY | D16: MT Philoxenia | E16: 44989 | F16: 44988 | G16: 137.0016 | H16: 136.99 | I16: 137.75 | J16: =AVERAGE(G16:I16) -> 137.2472 | L16: =AVERAGE(J16:K16) -> 137.2472 | M16: AGO S03/2023 | N16: SOT
A17: 13 | C17: E3 ENERGY | D17: MT Philoxenia | E17: 44988 | F17: 44988 | G17: 137.0016 | H17: 136.99 | I17: 137.75 | J17: =AVERAGE(G17:I17) -> 137.2472 | L17: =AVERAGE(J17:K17) -> 137.2472 | M17: MSP S03/2023 | N17: KOSF
A18: 14 | C18: E3 ENERGY | D18: MT Philoxenia | E18: 44988 | F18: 44988 | G18: 137.0016 | H18: 136.99 | I18: 137.75 | J18: =AVERAGE(G18:I18) -> 137.2472 | L18: =AVERAGE(J18:K18) -> 137.2472 | M18: MSP S03/2023 | N18: SOT
C19: Average for the Month of February 2023 | G19: 133.98296 | H19: 133.87 | I19: 134.1 | J19: =AVERAGE(G19:I19) -> 133.98432 | L19: =AVERAGE(J19:K19) -> 133.98432

Sheet PMS Import
C3: PMS
C5: ='AGO Import'!C5 -> 44986
B7: Cargo No. | C7: Importer | D7: BL. Date | E7: Vessel | F7: ETA | G7: Qty Mt | H7: Vol. M3 | I7: CIF | J7: RDL & IDF | L7: Cost | Q7: Unit Cost | R7: RDL | S7: IDF
J8: RDL | K8: IDF | L8: USD a/c | O8: KES a/c | P8: Total KES | T8: Cost in USD | U8: Unit cost USD/Mt
I9: (USD/Mt) | J9: (USD/Mt) | K9: (USD/Mt) | L9: USD | M9: Exc Rate | N9: Amount Kes | Q9: (KES/Lts ) | R9: (KES/Lts ) | S9: (KES/Lts )
B10: 1 | C10: E3 ENERGY | D10: 22.02.2023 | E10: MT SANMAR SANGEET | F10: 02-04.03.2023 | G10: 37120.918 | H10: 51139.127 | I10: 838.06739 | J10: =(0.02*I10) -> 16.761348 | K10: =(0.035*I10) -> 29.332359 | L10: 31603214 | M10: ='[13]Exchange Rates '!L13 -> 138.1264 | N10: =L10*M10 -> 4.3652382e+09 | O10: 77167610 | P10: =N10+O10 -> 4.4424058e+09 | Q10: =P10/(H10*1000) -> 86.869019 | R10: =J10*G10*M10/(H10*1000) -> 1.6805484 | S10: =K10*G10*M10/(H10*1000) -> 2.9409597 | T10: =P10/M10 -> 32161888 | U10: =T10/G10 -> 866.40875 | V10: =((R10*H10)+(R11*H11)+(R12*H12)+(H13*R13)+(R14*H14)+(H15*R15))/H16 -> 1.7335008
B11: 2 | C11: E3 ENERGY | D11: 30.01.2023 | E11: MT PIS POLARIS | F11: 10-12.02.2023 | G11: 12444.22 | H11: 16692.116 | I11: 926.62403 | J11: =(0.02*I11) -> 18.532481 | K11: =(0.035*I11) -> 32.431841 | L11: 11706417 | M11: ='[13]Exchange Rates '!L15 -> 132.88387 | N11: =L11*M11 -> 1.555594e+09 | O11: 27601168 | P11: =N11+O11 -> 1.5831952e+09 | Q11: =P11/(H11*1000) -> 94.846883 | R11: =J11*G11*M11/(H11*1000) -> 1.8359553 | S11: =K11*G11*M11/(H11*1000) -> 3.2129217 | T11: =P11/M11 -> 11914126 | U11: =T11/G11 -> 957.40242 | V11: =((S11*H11)+(S10*H10)+(S12*H12)+(H13*S13)+(S14*H14)+(H15*S15))/H16 -> 3.0336263
B12: 3 | C12: E3 ENERGY | D12: 13.02.2023 | E12: MT PHILOXENIA-SOT | F12: 21-23.02.2023 | G12: 12156.891 | H12: 16418.796 | I12: 879.28148 | J12: =(0.02*I12) -> 17.58563 | K12: =(0.035*I12) -> 30.774852 | L12: 10789477 | M12: ='[13]Exchange Rates '!L17 -> 137.2472 | N12: =L12*M12 -> 1.4808255e+09 | O12: 25761157 | P12: =N12+O12 -> 1.5065867e+09 | Q12: =P12/(H12*1000) -> 91.759874 | R12: =J12*G12*M12/(H12*1000) -> 1.7870744 | S12: =K12*G12*M12/(H12*1000) -> 3.1273802 | T12: =P12/M12 -> 10977176 | U12: =T12/G12 -> 902.95914
B13: 4 | C13: E3 ENERGY | D13: 13.02.2023 | E13: MT PHILOXENIA-KOSF | F13: 21-23.02.2023 | G13: 3944.873 | H13: 5309.353 | I13: 879.28148 | J13: =(0.02*I13) -> 17.58563 | K13: =(0.035*I13) -> 30.774852 | L13: 3522375 | M13: ='[13]Exchange Rates '!L18 -> 137.2472 | N13: =L13*M13 -> 4.834361e+08 | O13: 8380381.7 | P13: =N13+O13 -> 4.9181649e+08 | Q13: =P13/(H13*1000) -> 92.632094 | R13: =J13*G13*M13/(H13*1000) -> 1.7932995 | S13: =K13*G13*M13/(H13*1000) -> 3.1382742 | T13: =P13/M13 -> 3583435.5 | U13: =T13/G13 -> 908.37791
B14: 5 | C14: GULF ENERGY | D14: 08.02.2023 | E14: MT FRONT VEGA | F14: 18-20.02.2023 | G14: 36402.328 | H14: 49941.457 | I14: 877.54717 | J14: =(0.02*I14) -> 17.550943 | K14: =(0.035*I14) -> 30.714151 | L14: 32440865 | M14: ='[13]Exchange Rates '!L11 -> 134.21307 | N14: =L14*M14 -> 4.353988e+09 | O14: 76792112 | P14: =N14+O14 -> 4.4307802e+09 | Q14: =P14/(H14*1000) -> 88.719481 | R14: =J14*G14*M14/(H14*1000) -> 1.716972 | S14: =K14*G14*M14/(H14*1000) -> 3.004701 | T14: =P14/M14 -> 33013031 | U14: =T14/G14 -> 906.8934
B15: 6 | C15: GULF ENERGY | D15: 09.02.2023 | E15: MT CLEAROCEAN MESQUITE | F15: 18-20.02.2023 | G15: 15332.924 | H15: 20556.675 | I15: 877.54717 | J15: =(0.02*I15) -> 17.550943 | K15: =(0.035*I15) -> 30.714151 | L15: 13663069 | M15: ='[13]Exchange Rates '!L12 -> 134.746 | N15: =L15*M15 -> 1.841044e+09 | O15: 32364552 | P15: =N15+O15 -> 1.8734085e+09 | Q15: =P15/(H15*1000) -> 91.133829 | R15: =J15*G15*M15/(H15*1000) -> 1.7639589 | S15: =K15*G15*M15/(H15*1000) -> 3.0869281 | T15: =P15/M15 -> 13903259 | U15: =T15/G15 -> 906.75848
G16: =SUM(G10:G15) -> 117402.15 | H16: =SUM(H10:H15) -> 160057.52 | R16: =V10 -> 1.7335008 | S16: =V11 -> 3.0336263 | T16: =SUM(T10:T15) -> 1.0555292e+08 | U16: =T16/G16 -> 899.07137
T17: =T16/H16 -> 659.46863

Sheet AGO Import
C3: AGO
C5: 44986
B7: Cargo No. | C7: Importer | D7: BL. Date | E7: Vessel | F7: ETA | G7: Qty Mt | H7: Vol. M3 | I7: CIF | J7: RDL & IDF | L7: Cost | Q7: Unit Cost | R7: RDL | S7: IDF | T7: COST
J8: RDL | K8: IDF | L8: USD a/c | O8: KES a/c | P8: Total KES
I9: (USD/Mt) | J9: (USD/Mt) | K9: (USD/Mt) | L9: USD | M9: Exc Rate | N9: Amount Kes | Q9: (KES/Lts ) | R9: (KES/Lts ) | S9: (KES/Lts ) | T9: USD | U9: Unit cost USD/Mt
B10: 1 | C10: TEXAS | D10: 02.02.2023 | E10: MT SEALEGEND | F10: 11-13.02.2023 | G10: 50542.573 | H10: 61592.22 | I10: 926.61961 | J10: =0.02*I10 -> 18.532392 | K10: =(0.035*I10) -> 32.431686 | L10: 47514086 | M10: ='[13]Exchange Rates '!L5 -> 133.1196 | N10: =(L10*M10) -> 6.3250561e+09 | O10: 1.10019e+08 | P10: =N10+O10 -> 6.4350751e+09 | Q10: =P10/(H10*1000) -> 104.4787 | R10: =(J10*G10*M10)/(H10*1000) -> 2.0244403 | S10: =(K10*G10*M10)/(H10*1000) -> 3.5427705 | T10: =P10/M10 -> 48340554 | U10: =T10/G10 -> 956.43238 | V10: =((R10*H10)+(H11*R11)+(R12*H12)+(H13*R13)+(R14*H14)+(H15*R15))/H16 -> 1.9943291
B11: 2 | C11: ORYX ENERGIES | D11: 13.02.2023 | E11: MT STI LOTUS | F11: 23-25.02.2023 | G11: 51275.358 | H11: 61204.292 | I11: 856.01748 | J11: =0.02*I11 -> 17.12035 | K11: =(0.035*I11) -> 29.960612 | L11: 44544464 | M11: ='[13]Exchange Rates '!L6 -> 137.2472 | N11: =(L11*M11) -> 6.113603e+09 | O11: 1.0627843e+08 | P11: =N11+O11 -> 6.2198814e+09 | Q11: =P11/(H11*1000) -> 101.62492 | R11: =(J11*G11*M11)/(H11*1000) -> 1.9685341 | S11: =(K11*G11*M11)/(H11*1000) -> 3.4449347 | T11: =P11/M11 -> 45318822 | U11: =T11/G11 -> 883.83239 | V11: =((S10*H10)+(H11*S11)+(S12*H12)+(H13*S13)+(S14*H14)+(H15*S15))/H16 -> 3.490076
A12: VTTI | B12: 3 | C12: E3 ENERGY | D12: 08.02.2023 | E12: MT SERENGETI-VTTI | F12: 20-22.02.2023 | G12: 24198.865 | H12: 28949.991 | I12: 858.51517 | J12: =0.02*I12 -> 17.170303 | K12: =(0.035*I12) -> 30.048031 | L12: 20973536 | M12: ='[13]Exchange Rates '!L7 -> 135.62893 | N12: =(L12*M12) -> 2.8446183e+09 | O12: 50376060 | P12: =N12+O12 -> 2.8949943e+09 | Q12: =P12/(H12*1000) -> 99.999835 | R12: =(J12*G12*M12)/(H12*1000) -> 1.9466007 | S12: =(K12*G12*M12)/(H12*1000) -> 3.4065513 | T12: =P12/M12 -> 21344961 | U12: =T12/G12 -> 882.06456
A13: KOSF | B13: 4 | C13: E3 ENERGY | D13: 08.02.2023 | E13: MT SERENGETI-KOSF | F13: 20-22.02.2023 | G13: 16110.36 | H13: 19278.644 | I13: 858.51517 | J13: =0.02*I13 -> 17.170303 | K13: =(0.035*I13) -> 30.048031 | L13: 14036454 | M13: ='[13]Exchange Rates '!L8 -> 135.62893 | N13: =(L13*M13) -> 1.9037493e+09 | O13: 33551645 | P13: =N13+O13 -> 1.9373009e+09 | Q13: =P13/(H13*1000) -> 100.48948 | R13: =(J13*G13*M13)/(H13*1000) -> 1.9460728 | S13: =(K13*G13*M13)/(H13*1000) -> 3.4056274 | T13: =P13/M13 -> 14283832 | U13: =T13/G13 -> 886.62403
B14: 5 | C14: E3 ENERGY | D14: 02.02.2023 | E14: MT PIS POLARIS | F14: 10-12.02.2023 | G14: 14586.144 | H14: 17817.317 | I14: 953.99504 | J14: =0.02*I14 -> 19.079901 | K14: =(0.035*I14) -> 33.389826 | L14: 14045754 | M14: ='[13]Exchange Rates '!L14 -> 133.18867 | N14: =(L14*M14) -> 1.8707352e+09 | O14: 33067503 | P14: =N14+O14 -> 1.9038027e+09 | Q14: =P14/(H14*1000) -> 106.85126 | R14: =(J14*G14*M14)/(H14*1000) -> 2.0803747 | S14: =(K14*G14*M14)/(H14*1000) -> 3.6406558 | T14: =P14/M14 -> 14294030 | U14: =T14/G14 -> 979.97316
B15: 6 | C15: E3 ENERGY | D15: 11.02.2023 | E15: MT PHILOXENIA | F15: 21-23.02.2023 | G15: 16097.494 | H15: 19669.68 | I15: 899.1598 | J15: =0.02*I15 -> 17.983196 | K15: =(0.035*I15) -> 31.470593 | L15: 14610329 | M15: ='[13]Exchange Rates '!L16 -> 137.2472 | N15: =(L15*M15) -> 2.0052268e+09 | O15: 34656263 | P15: =N15+O15 -> 2.0398831e+09 | Q15: =P15/(H15*1000) -> 103.70698 | R15: =(J15*G15*M15)/(H15*1000) -> 2.0199069 | S15: =(K15*G15*M15)/(H15*1000) -> 3.534837 | T15: =P15/M15 -> 14862839 | U15: =T15/G15 -> 923.30143
G16: =SUM(G10:G15) -> 172810.79 | H16: =SUM(H10:H15) -> 208512.14 | R16: =V10 -> 1.9943291 | S16: =V11 -> 3.490076 | T16: =SUM(T10:T15) -> 1.5844504e+08 | U16: =T16/G16 -> 916.87003
T17: =T16/H16 -> 759.88398

Sheet DPK Import
C3: DPK
D5: ='AGO Import'!C5 -> 44986
B7: Cargo No. | C7: Importer | D7: BL. Date | E7: Vessel | F7: ETA | G7: Qty Mt | H7: Vol. M3 | I7: CIF | J7: RDL & IDF | L7: Cost | Q7: Unit Cost | R7: RDL | S7: IDF
J8: RDL | K8: IDF | L8: USD a/c | O8: KES a/c | P8: Total KES
J9: (USD/Mt) | K9: (USD/Mt) | L9: USD | M9: Exc Rate | N9: Amount Kes | Q9: (KES/Lts ) | R9: (KES/Lts ) | S9: (KES/Lts ) | T9: Cost in USD | U9: Unit cost USD/Mt
B10: 1 | C10: E3 ENERGY | D10: 03.02.2023 | E10: MT NAKHAL SILVER | F10: 12-14.02.2023 | G10: 28973.434 | H10: 36938.085 | I10: 982.38433 | J10: =(0.02*I10) -> 19.647687 | K10: =(0.035*I10) -> 34.383451 | L10: 28875611 | M10: ='[13]Exchange Rates '!L9 -> 133.90013 | N10: =(L10*M10) -> 3.8664482e+09 | O10: 67154307 | P10: =N10+O10 -> 3.9336025e+09 | Q10: =P10/(H10*1000) -> 106.49178 | R10: =(J10*G10*M10)/(H10*1000) -> 2.0635644 | S10: =(K10*G10*M10)/(H10*1000) -> 3.6112377 | T10: =P10/M10 -> 29377137 | U10: =T10/G10 -> 1013.9335 | V10: =((R10*H10)+(R11*H11))/H12 -> 2.0134756
B11: 2 | C11: ORYX ENERGIES | D11: 23.02.2023 | E11: MT HAFNIA LUPUS | F11: 03-05.03.2023 | G11: 27628.641 | H11: 35193.855 | I11: 900.22273 | J11: =(0.02*I11) -> 18.004455 | K11: =(0.035*I11) -> 31.507795 | L11: 25244161 | M11: ='[13]Exchange Rates '!J10 -> 138.73427 | N11: =(L11*M11) -> 3.5022302e+09 | O11: 60452268 | P11: =N11+O11 -> 3.5626825e+09 | Q11: =P11/(H11*1000) -> 101.23024 | R11: =(J11*G11*M11)/(H11*1000) -> 1.9609043 | S11: =(K11*G11*M11)/(H11*1000) -> 3.4315825 | T11: =P11/M11 -> 25679903 | U11: =T11/G11 -> 929.46674
G12: =SUM(G10:G11) -> 56602.075 | H12: =SUM(H10:H11) -> 72131.94 | R12: =V10 -> 2.0134756 | S12: =V12 -> 3.5235822 | T12: =SUM(T10:T11) -> 55057039 | U12: =T12/G12 -> 972.70355 | V12: =((S10*H10)+(S11*H11))/H12 -> 3.5235822
T13: =T12/H12 -> 763.28239

Sheet WEIGHTED AVERAGE COST
B2: WEIGHTED AVERAGE COST ( Cu) FOR THE MONTH OF FEBRUARY 2023(KES/L)
B4: Super Petrol (PMS)
B5: COLUMN | D5: A | E5: B | F5: C | G5: D | H5: E | I5: F | J5: G | K5: H | L5: I
B6: IMPORTS | C6: CARGO NAME | I6: RDL | J6: IDF | K6: (B+C+D+E+F+G) | L6: A*F
C7: PMS | D7: M3 | E7: Kes/lit | F7: Kes/lit | G7: Kes/lit | H7: Kes/lit | I7: Kes/lit | J7: Kes/lit | K7: Kes/lit | L7: KES '000'
B8: ='AGO Import'!C5 -> 44986
B9: ='PMS Import'!C10 -> E3 ENERGY | C9: ='PMS Import'!E10 -> MT SANMAR SANGEET | D9: ='PMS Import'!H10 -> 51139.127 | E9: ='PMS Import'!Q10 -> 86.869019 | F9: =32.415+6+0.13+1.025+5+1.03343 -> 45.60343 | G9: 0 | H9: 0 | I9: ='PMS Import'!R10 -> 1.6805484 | J9: ='PMS Import'!S10 -> 2.9409597 | K9: =SUM(E9:J9) -> 137.09396 | L9: =(K9*D9) -> 7010865.3 | M9: ='PMS Import'!M10 -> 138.1264
B10: ='PMS Import'!C11 -> E3 ENERGY | C10: ='PMS Import'!E11 -> MT PIS POLARIS | D10: ='PMS Import'!H11 -> 16692.116 | E10: ='PMS Import'!Q11 -> 94.846883 | F10: =32.415+6+0.13+1.025+5+1.03343 -> 45.60343 | G10: 0 | H10: 0 | I10: ='PMS Import'!R11 -> 1.8359553 | J10: ='PMS Import'!S11 -> 3.2129217 | K10: =SUM(E10:J10) -> 145.49919 | L10: =(K10*D10) -> 2428689.4 | M10: ='PMS Import'!M11 -> 132.88387
B11: ='PMS Import'!C12 -> E3 ENERGY | C11: ='PMS Import'!E12 -> MT PHILOXENIA-SOT | D11: ='PMS Import'!H12 -> 16418.796 | E11: ='PMS Import'!Q12 -> 91.759874 | F11: =32.415+6+0.13+1.025+5+1.03343 -> 45.60343 | G11: 0 | H11: 0 | I11: ='PMS Import'!R12 -> 1.7870744 | J11: ='PMS Import'!S12 -> 3.1273802 | K11: =SUM(E11:J11) -> 142.27776 | L11: =(K11*D11) -> 2336029.5 | M11: ='PMS Import'!M12 -> 137.2472
B12: ='PMS Import'!C13 -> E3 ENERGY | C12: ='PMS Import'!E13 -> MT PHILOXENIA-KOSF | D12: ='PMS Import'!H13 -> 5309.353 | E12: ='PMS Import'!Q13 -> 92.632094 | F12: =32.415+6+0.13+1.025+5+1.03343 -> 45.60343 | G12: 0 | H12: 0 | I12: ='PMS Import'!R13 -> 1.7932995 | J12: ='PMS Import'!S13 -> 3.1382742 | K12: =SUM(E12:J12) -> 143.1671 | L12: =(K12*D12) -> 760124.66 | M12: ='PMS Import'!M13 -> 137.2472
B13: ='PMS Import'!C14 -> GULF ENERGY | C13: ='PMS Import'!E14 -> MT FRONT VEGA | D13: ='PMS Import'!H14 -> 49941.457 | E13: ='PMS Import'!Q14 -> 88.719481 | F13: =32.415+6+0.13+1.025+5+1.03343 -> 45.60343 | G13: 0 | H13: 0 | I13: ='PMS Import'!R14 -> 1.716972 | J13: ='PMS Import'!S14 -> 3.004701 | K13: =SUM(E13:J13) -> 139.04458 | L13: =(K13*D13) -> 6944089.1 | M13: ='PMS Import'!M14 -> 134.21307
B14: ='PMS Import'!C15 -> GULF ENERGY | C14: ='PMS Import'!E15 -> MT CLEAROCEAN MESQUITE | D14: ='PMS Import'!H15 -> 20556.675 | E14: ='PMS Import'!Q15 -> 91.133829 | F14: =32.415+6+0.13+1.025+5+1.03343 -> 45.60343 | G14: 0 | H14: 0 | I14: ='PMS Import'!R15 -> 1.7639589 | J14: ='PMS Import'!S15 -> 3.0869281 | K14: =SUM(E14:J14) -> 141.58815 | L14: =(K14*D14) -> 2910581.5 | M14: ='PMS Import'!M15 -> 134.746
B15: Demurrage | C15: MT PIS POLARIS | L15: =N15*M10/1000 -> 4037.0366 | N15: 30380.186
B16: Demurrage | C16: MT FRONT VEGA | L16: =N16*M13/1000 -> 5586.4953 | N16: 41624.079
B17: Demurrage | C17: MT CLEAROCEAN MESQUITE | L17: =N17*M14/1000 -> 4093.5356 | N17: 30379.645
B18: Demurrage | C18: MT PHILOXENIA | L18: =N18*M12/1000 -> 12823.565 | N18: 93434.077
B19: Demurrage | C19: MT SANMAR SANGEET | L19: =N19*M9/1000 -> 8640.0581 | N19: 62551.823
B20: Additional Demurrage - PMS S01/2023 | C20: MT JAG PADMA | L20: =N20*M20/1000 -> 6392.6371 | M20: 130.4411 | N20: 49007.844
B21: Additional Demurrage - PMS K01/2023 | C21: MT PERSEUS STAR | L21: =N21*M21/1000 -> 6627.5169 | M21: 131.62343 | N21: 50352.105
B22: Additional Demurrage - PMS K20/2022 | C22: MT SLOANE SQUARE | L22: =N22*M22/1000 -> 33125.228 | M22: 124.97612 | N22: 265052.47
B23: Additional Demurrage - PMS K23/2022 | C23: MT TORM HILDE | L23: =N23*M23/1000 -> 7416.0811 | M23: 130.11507 | N23: 56996.328
B24: Additional Demurrage - PMS K03/2023 | C24: MT FRONT VEGA | L24: =N24*M24/1000 -> 4158.8354 | M24: =M13 -> 134.21307 | N24: 30986.814
B25: Additional Demurrage - PMS K03/2023 | C25: MT CLEAROCEAN MESQUITE | L25: =N25*M25/1000 -> 3929.7942 | M25: =M14 -> 134.746 | N25: 29164.459
B26: Additional Demurrage - PMS K02/2023 | C26: MT TORM HILDE | L26: =N26*M26/1000 -> 3376.1575 | M26: 131.83307 | N26: 25609.338
B27: OTS FINANCING INTEREST-PMS K20/2022 | C27: MT SLOANE SQUARE | L27: =N27*M27/1000 -> 39154.882 | M27: 124.97612 | N27: 313298.92
B28: OTS FINANCING INTEREST-PMS K22/2022 | C28: MT HAFNIA DESPINA | L28: =N28*M28/1000 -> 20770.953 | M28: 128.0003 | N28: 162272.69
D29: =SUM(D9:D14) -> 160057.52 | E29: =((D9*E9)+(D10*E10)+(D11*E11)+(D12*E12)+(D13*E13)+(D14*E14))/D29 -> 89.519021 | L29: =SUM(L9:L28) -> 22550512
M31: =SUM(L15:L28)/D29 -> 1.0004702 | N31: =SUM(L20:L28)/D29 -> 0.78066987
D33: A | E33: B | L33: I
B34: KPRL | C34: CARGO NAME | L34: A*H
B38: TOTAL COST (KES) | L38: =L37+L29 -> 22550512
B39: TOTAL VOLUME (Litres) | D39: =D29+D37 -> 160057.52 | E39: =((D29*E29)+(D37*E37))/D39 -> 89.519021 | L39: =D29+D37 -> 160057.52
L40: =L38/L39 -> 140.89005
B43: =B2 -> WEIGHTED AVERAGE COST ( Cu) FOR THE MONTH OF FEBRUARY 2023(KES/L)
B45: Automotive Diesel (AGO)
B46: COLUMN | D46: A | E46: B | F46: C | G46: D | H46: E | I46: F | J46: G | K46: H | L46: I
B47: IMPORTS | C47: CARGO NAME | I47: RDL | J47: IDF | K47: (B+C+D+E+F+G) | L47: A*F
D48: M3 | E48: Kes/lit | F48: Kes/lit | G48: Kes/lit | H48: Kes/lit | I48: Kes/lit | J48: Kes/lit | K48: Kes/lit | L48: KES '000'
B49: =B8 -> 44986
B50: ='AGO Import'!C10 -> TEXAS | C50: ='AGO Import'!E10 -> MT SEALEGEND | D50: ='AGO Import'!H10 -> 61592.22 | E50: ='AGO Import'!Q10 -> 104.4787 | F50: =22.825+6+0.13+0.531+5+0.53528 -> 35.02128 | G50: 0 | H50: 0 | I50: ='AGO Import'!R10 -> 2.0244403 | J50: ='AGO Import'!S10 -> 3.5427705 | K50: =SUM(E50:J50) -> 145.06719 | L50: =K50*D50 -> 8935010.4 | M50: ='AGO Import'!M10 -> 133.1196 | N50: AMOUNT (USD) | O50: TIME TAKEN | P50: TIME ALLOWED | Q50: JETTY
B51: ='AGO Import'!C11 -> ORYX ENERGIES | C51: ='AGO Import'!E11 -> MT STI LOTUS | D51: ='AGO Import'!H11 -> 61204.292 | E51: ='AGO Import'!Q11 -> 101.62492 | F51: =22.825+6+0.13+0.531+5+0.53528 -> 35.02128 | G51: 0 | H51: 0 | I51: ='AGO Import'!R11 -> 1.9685341 | J51: ='AGO Import'!S11 -> 3.4449347 | K51: =SUM(E51:J51) -> 142.05967 | L51: =K51*D51 -> 8694661.6 | M51: ='AGO Import'!M11 -> 137.2472
B52: ='AGO Import'!C12 -> E3 ENERGY | C52: ='AGO Import'!E12 -> MT SERENGETI-VTTI | D52: ='AGO Import'!H12 -> 28949.991 | E52: ='AGO Import'!Q12 -> 99.999835 | F52: =22.825+6+0.13+0.531+5+0.53528 -> 35.02128 | G52: 0 | H52: 0 | I52: ='AGO Import'!R12 -> 1.9466007 | J52: ='AGO Import'!S12 -> 3.4065513 | K52: =SUM(E52:J52) -> 140.37427 | L52: =K52*D52 -> 4063833.8 | M52: ='AGO Import'!M12 -> 135.62893
B53: ='AGO Import'!C13 -> E3 ENERGY | C53: ='AGO Import'!E13 -> MT SERENGETI-KOSF | D53: ='AGO Import'!H13 -> 19278.644 | E53: ='AGO Import'!Q13 -> 100.48948 | F53: =22.825+6+0.13+0.531+5+0.53528 -> 35.02128 | G53: 0 | H53: 0 | I53: ='AGO Import'!R13 -> 1.9460728 | J53: ='AGO Import'!S13 -> 3.4056274 | K53: =SUM(E53:J53) -> 140.86246 | L53: =K53*D53 -> 2715637.2 | M53: ='AGO Import'!M13 -> 135.62893
B54: ='AGO Import'!C14 -> E3 ENERGY | C54: ='AGO Import'!E14 -> MT PIS POLARIS | D54: ='AGO Import'!H14 -> 17817.317 | E54: ='AGO Import'!Q14 -> 106.85126 | F54: =22.825+6+0.13+0.531+5+0.53528 -> 35.02128 | G54: 0 | H54: 0 | I54: ='AGO Import'!R14 -> 2.0803747 | J54: ='AGO Import'!S14 -> 3.6406558 | K54: =SUM(E54:J54) -> 147.59357 | L54: =K54*D54 -> 2629721.4 | M54: ='AGO Import'!M14 -> 133.18867
B55: ='AGO Import'!C15 -> E3 ENERGY | C55: ='AGO Import'!E15 -> MT PHILOXENIA | D55: ='AGO Import'!H15 -> 19669.68 | E55: ='AGO Import'!Q15 -> 103.70698 | F55: =22.825+6+0.13+0.531+5+0.53528 -> 35.02128 | G55: 0 | H55: 0 | I55: ='AGO Import'!R15 -> 2.0199069 | J55: ='AGO Import'!S15 -> 3.534837 | K55: =SUM(E55:J55) -> 144.283 | L55: =K55*D55 -> 2838000.5 | M55: ='AGO Import'!M15 -> 137.2472
B56: Demurrage | C56: MT PIS POLARIS | L56: =N56*M54/1000 -> 4732.921 | N56: 35535.464
B57: Demurrage | C57: MT SEALEGEND | L57: =N57*M50/1000 -> 3332.6826 | N57: 25035.251
B58: Demurrage | C58: MT SERENGETI | L58: =N58*M52/1000 -> 11538.082 | N58: 85070.949
B59: Demurrage | C59: MT PHILOXENIA | L59: =N59*M55/1000 -> 12847.333 | N59: 93607.248
B60: Demurrage | C60: MT STI LOTUS | L60: =N60*M51/1000 -> 14379.759 | N60: 104772.69
B61: Additional Demurrage-AGO V01/2023 | C61: MT KARIMATA | L61: =N61*M61/1000 -> 1851.4893 | M61: 131.62343 | N61: 14066.563
B62: Additional Demurrage-AGO K01/2023 | C62: MT SANMAR SANGEET | L62: =N62*M62/1000 -> 10172.848 | M62: 131.37947 | N62: 77431.037
B63: Additional Demurrage-AGO K23/2022 | C63: MT TAVISTOCK SQUARE | L63: =N63*M63/1000 -> 7485.2615 | M63: 131.10713 | N63: 57092.71
B64: Additional Demurrage-AGO S01/2023 | C64: MT JAG PADMA | L64: =N64*M64/1000 -> 7967.2496 | M64: 130.8647 | N64: 60881.579
D65: =SUM(D50:D55) -> 208512.14 | E65: =((D50*E50)+(D51*E51)+(D52*E52)+(D53*E53)+(D54*E54)+(D55*E55))/D65 -> 102.78029 | L65: =SUM(L50:L64) -> 29951173
M66: =SUM(L56:L64)/D65 -> 0.35637073
N67: =SUM(L61:L63)/D65 -> 0.093565769
D69: A | E69: B | F69: C | G69: D | H69: E | I69: F | J69: G | K69: H | L69: I
B70: KPRL | C70: CARGO NAME | I70: RDL | J70: IDF | K70: (B+C+D+E+F+G) | L70: A*H
B74: TOTAL COST (KES) | L74: =L73+L65 -> 29951173
B75: TOTAL VOLUME (Litres) | D75: =D65+D73 -> 208512.14 | E75: =((D65*E65)+(D73*E73))/D75 -> 102.78029 | L75: =D65+D73 -> 208512.14
L76: =L74/L75 -> 143.64234
B79: =B43 -> WEIGHTED AVERAGE COST ( Cu) FOR THE MONTH OF FEBRUARY 2023(KES/L)
B81: Kerosene (DPK)
B82: COLUMN | C82: JETI | D82: A | E82: B | F82: C | G82: D | H82: E | I82: F | J82: G | K82: H | L82: I
B83: IMPORTS | C83: CARGO NAME | I83: RDL | J83: IDF | K83: (B+C+D+E+F+G) | L83: A*F | O83: TIME TAKEN
D84: M3 | E84: Kes/lit | F84: Kes/lit | G84: Kes/lit | H84: Kes/lit | I84: Kes/lit | K84: Kes/lit | L84: KES '000' | N84: AMOUNT (USD) | P84: TIME ALLOWED | Q84: JETTY
B85: =B49 -> 44986
B86: ='DPK Import'!C10 -> E3 ENERGY | C86: ='DPK Import'!E10 -> MT NAKHAL SILVER | D86: ='DPK Import'!H10 -> 36938.085 | E86: ='DPK Import'!Q10 -> 106.49178 | F86: =0.45+7.205+3.1+0.2+18+0.531+0.53528 -> 30.02128 | G86: 0 | H86: 0 | I86: ='DPK Import'!R10 -> 2.0635644 | J86: ='DPK Import'!S10 -> 3.6112377 | K86: =SUM(E86:J86) -> 142.18786 | L86: =K86*D86 -> 5252147.4 | M86: ='DPK Import'!M10 -> 133.90013
B87: ='DPK Import'!C11 -> ORYX ENERGIES | C87: ='DPK Import'!E11 -> MT HAFNIA LUPUS | D87: ='DPK Import'!H11 -> 35193.855 | E87: ='DPK Import'!Q11 -> 101.23024 | F87: =0.45+7.205+3.1+0.2+18+0.531+0.53528 -> 30.02128 | G87: 0 | H87: 0 | I87: ='DPK Import'!R11 -> 1.9609043 | J87: ='DPK Import'!S11 -> 3.4315825 | K87: =SUM(E87:J87) -> 136.64401 | L87: =K87*D87 -> 4809029.5 | M87: ='DPK Import'!M11 -> 138.73427
B88: Demurrage | C88: MT NAKHAL SILVER | L88: =N88*M86/1000 -> 5260.0682 | N88: 39283.517
B89: Additional Demurrage-JET A-1 K02/2023 | C89: MT CELSIUS ROME | L89: =N89*M89/1000 -> 4132.9259 | M89: 131.90333 | N89: 31332.99
B90: OTS FINANCING INTEREST-JET A1-K12/2022 | C90: MT JARNAIN | L90: =N90*M90/1000 -> 65174.1 | M90: 124.33238 | N90: 524192.48
B91: Additional Demurrage-JET A-1 K01/2023 | C91: MT ENERGY CENTAUR | L91: =N91*M91/1000 -> 38488.388 | M91: 130.4411 | N91: 295063.35
B92: Administration Costs | C92: Based on February-March 2023 Pricing | L92: =N92/1000 -> 2235.7181 | N92: 2235718.1
D93: =SUM(D86:D87) -> 72131.94 | E93: =((D86*E86)+(D87*E87))/D93 -> 103.92463 | L93: =SUM(L86:L92) -> 10176468
M96: =SUM(L88:L92)/D93 -> 1.5983377 | N96: =SUM(L89:L91)/D93 -> 1.49442
D97: A | E97: B | F97: C | G97: D | H97: E | I97: F | J97: G | K97: H | L97: I
B98: KPRL | C98: CARGO NAME | I98: RDL | J98: IDF | K98: (B+C+D+E+F+G) | L98: A*H
B102: TOTAL COST (KES) | L102: =L93+L101 -> 10176468
B103: TOTAL VOLUME (Litres) | D103: =D93+D101 -> 72131.94 | E103: =((D93*E93)+(D101*E101))/D103 -> 103.92463 | L103: =D93+D101 -> 72131.94
L104: =L102/L103 -> 141.0813
B107: =B79 -> WEIGHTED AVERAGE COST ( Cu) FOR THE MONTH OF FEBRUARY 2023(KES/L)
B109: Regular Petrol (RMS)
B110: COLUMN | D110: A | E110: B | F110: C | G110: D | H110: E | I110: F | K110: G | L110: H
B111: IMPORTS | C111: CARGO NAME | I111: RDL | K111: (B+C+D+E+F) | L111: A*F
D112: M3 | E112: Kes/lit | F112: Kes/lit | G112: Kes/lit | H112: Kes/lit | I112: Kes/lit | K112: Kes/lit | L112: KES '000'
B114: =B85 -> 44986
D115: 0 | E115: 0 | F115: 0 | G115: 0 | H115: 0 | I115: 0 | K115: =SUM(E115:G115) -> 0 | L115: =K115*D115 -> 0
D117: =SUM(D114:D116) -> 0 | L117: =SUM(L114:L116) -> 0
D118: A | E118: B | F118: C | G118: D | H118: E | I118: F | K118: G | L118: H
B119: KPRL | C119: CARGO NAME | I119: RDL | K119: (B+C+D+E+F) | L119: A*F
B121: =B100 -> 0 | C121: CARGO NAME | D121: 1138.567 | E121: 68.3063 | F121: 28.96 | G121: 0 | H121: -0.45 | I121: 0 | K121: =E121+F121+H121 -> 96.8163 | L121: =D121*K121 -> 110231.84
C122: CARGO NAME | D122: 1928.154 | E122: 59.00555 | F122: 28.96 | G122: 0 | H122: -0.45 | I122: 0 | K122: =E122+F122+G122+H122 -> 87.51555 | L122: =K122*D122 -> 168743.46
D123: =SUM(D121:D122) -> 3066.721 | L123: =SUM(L121:L122) -> 278975.3
B124: TOTAL COST (KES) | L124: =L123+L117 -> 278975.3
B125: TOTAL VOLUME (Litres) | L125: =D117+D123 -> 3066.721
L126: =L124/L125 -> 90.968595

Sheet RMS Cargos
E3: RMS
G4: ='PMS Import'!C5 -> 44986
B6: Cargo No. | C6: Importer | D6: BL. Date | E6: Vessel | F6: ETA | G6: Qty Mt | H6: Vol. M3 | I6: Cost | N6: Unit Cost
I7: USD a/c | L7: KES a/c | M7: Total KES | N7: KES/Lts
I8: USD | J8: Exc Rate | K8: Amount Kes
K9: =I9*J9 -> 0 | M9: =K9+L9 -> 0
K10: =I10*J10 -> 0 | M10: =K10+L10 -> 0
K11: =I11*J11 -> 0 | M11: =K11+L11 -> 0

Sheet PMS SUMMARY
B3: SUPER PETROL | D3: ='PMS Import'!E10 -> MT SANMAR SANGEET | E3: ='PMS Import'!E11 -> MT PIS POLARIS | F3: ='PMS Import'!E12 -> MT PHILOXENIA-SOT | G3: ='PMS Import'!E13 -> MT PHILOXENIA-KOSF | H3: ='PMS Import'!E14 -> MT FRONT VEGA | I3: ='PMS Import'!E15 -> MT CLEAROCEAN MESQUITE
D4: ='PMS Import'!C10 -> E3 ENERGY | E4: ='PMS Import'!C11 -> E3 ENERGY | F4: ='PMS Import'!C12 -> E3 ENERGY | G4: ='PMS Import'!C13 -> E3 ENERGY | H4: ='PMS Import'!C14 -> GULF ENERGY | I4: ='PMS Import'!C15 -> GULF ENERGY
B5: Costs paid in USD | D5: USD/MT | E5: USD/MT | F5: USD/MT | G5: USD/MT | H5: USD/MT | I5: USD/MT
B6: Free On Board (FOB) | C6: Platts based | D6: 830.8875 | E6: 837.119 | F6: 830.8875 | G6: 830.8875 | H6: 830.888 | I6: 830.888 | J6: =AVERAGE(D6:G6) -> 832.44538
B7: Freight & Premium (F&P) | C7: Varies as per Tender | D7: 4.86 | E7: 86.94 | F7: 45.96 | G7: 45.96 | H7: 44.23 | I7: 44.23 | J7: =AVERAGE(D7:G7) -> 45.93 | K7: 932.70175
B8: Letter of Credit Charges (LC) | C8: [1.20%*C&F] | D8: 10.02897 | E8: 11.088708 | F8: 10.52217 | G8: 10.52217 | H8: 10.501416 | I8: 10.501416 | J8: =AVERAGE(D8:G8) -> 10.540505 | K8: =J6+J7 -> 878.37537
B9: Certificate of Confomity (COC) | D9: 0.031654007 | E9: 0.16468638 | F9: 0.11263009 | G9: 0.11263009 | H9: 0.030290489 | I9: 0.077579334 | K9: =K7-K8 -> 54.326375
B10: Total USD based Cost | D10: =SUM(D6:D9) -> 845.80812 | E10: =SUM(E6:E9) -> 935.31239 | F10: =SUM(F6:F9) -> 887.4823 | G10: =SUM(G6:G9) -> 887.4823 | H10: =SUM(H6:H9) -> 885.64971 | I10: =SUM(I6:I9) -> 885.697
B11: Costs paid in KShs | D11: KSHS/MT | E11: KSHS/MT | F11: KSHS/MT | G11: KSHS/MT | H11: KSHS/MT | I11: KSHS/MT | K11: =K9*J22/(J23*1000) -> 5.4723563
B12: Insurance | C12: [1.003*C&F*0.0770%] | D12: 282.90053 | E12: 310.48382 | F12: 292.20943 | G12: 292.20943 | H12: 290.97674 | I12: 290.97674
B13: War Risk | C13: [1.003*C&F*0.0275%] | D13: 31.212415 | E13: 34.25568 | F13: 32.239466 | G13: 32.239466 | H13: 32.103463 | I13: 32.103463
B14: KPA Wharfage | C14: [USD 2.20/MT + 16% VAT] | D14: 345.5408 | E14: 342.9888 | F14: 340.1816 | G14: 340.1816 | H14: 339.416 | I14: 339.416
B15: Stevedoring Charges | C15: [USD 1.65/MT] | D15: 223.41 | E15: 221.76 | F15: 219.945 | G15: 219.945 | H15: 219.45 | I15: 219.45
B16: Ocean Losses | C16: [0.50%*CIFLW] | D16: 577.00599 | E16: 632.9667 | F16: 595.85476 | G16: 595.85476 | H16: 593.34664 | I16: 593.34664
B17: Adminstration Fees | C17: [0.5% of CIF] | D17: 567.37162 | E17: 622.69135 | F17: 586.0411 | G17: 586.0411 | H17: 583.56887 | I17: 583.56887
B18: Inspection Charges | D18: 10.048048 | E18: 10.419296 | F18: 10.434292 | G18: 11.252 | H18: 10.052396 | I18: 10.314623
B19: Merchant Shipping Fee | C19: [USD 0.3/MT] | D19: 40.62 | E19: 40.32 | F19: 39.99 | G19: 39.99 | H19: 39.9 | I19: 39.9
B20: Analysis +Recertification Charges | C20: ='[14]DPK CRYSTAL'!B37 -> [0.50%*CIF] | D20: 0.70799901 | E20: 2.1057487 | F20: 2.1622078 | G20: 6.6593139 | H20: 0.72437042 | I20: 1.7116545
B21: Total Kshs based costs (KShs/MT) | D21: =SUM(D12:D20) -> 2078.8174 | E21: =SUM(E12:E20) -> 2217.9914 | F21: =SUM(F12:F20) -> 2119.0579 | G21: =SUM(G12:G20) -> 2124.3727 | H21: =SUM(H12:H20) -> 2109.5385 | I21: =SUM(I12:I20) -> 2110.788
B22: Exchange rate (USD/KShs) | D22: ='PMS Import'!M10 -> 138.1264 | E22: ='PMS Import'!M11 -> 132.88387 | F22: ='PMS Import'!M12 -> 137.2472 | G22: ='PMS Import'!M13 -> 137.2472 | H22: ='PMS Import'!M14 -> 134.21307 | I22: ='PMS Import'!M15 -> 134.746 | J22: =AVERAGE(D22:G22) -> 136.37617
B23: Conversion factor (M3/MT) | D23: ='PMS Import'!H10/'PMS Import'!G10 -> 1.3776364 | E23: ='PMS Import'!H11/'PMS Import'!G11 -> 1.3413549 | F23: ='PMS Import'!H12/'PMS Import'!G12 -> 1.3505752 | G23: ='PMS Import'!H13/'PMS Import'!G13 -> 1.3458869 | H23: ='PMS Import'!H14/'PMS Import'!G14 -> 1.3719303 | I23: ='PMS Import'!H15/'PMS Import'!G15 -> 1.3406885 | J23: =AVERAGE(D23:G23) -> 1.3538634 | K23: =J8*J22/(J23*1000) -> 1.0617568
B24: USD based Cost coverted to KShs/Litre | D24: =(D10*D22)/(D23*1000) -> 84.803532 | E24: =(E10*E22)/(E23*1000) -> 92.658493 | F24: =(F10*F22)/(F23*1000) -> 90.187097 | G24: =(G10*G22)/(G23*1000) -> 90.501259 | H24: =(H10*H22)/(H23*1000) -> 86.641255 | I24: =(I10*I22)/(I23*1000) -> 89.017044
B25: Kshs based cost converted KShs/Litre | D25: =D21/(D23*1000) -> 1.5089739 | E25: =E21/(E23*1000) -> 1.6535455 | F25: =F21/(F23*1000) -> 1.5690039 | G25: =G21/(G23*1000) -> 1.5784184 | H25: =H21/(H23*1000) -> 1.5376426 | I25: =I21/(I23*1000) -> 1.574406
B26: Kipevu shore handling charges | C26: [0.19USD*16%VAT] | D26: =(0.19*1.16*D22)/1000 -> 0.030443059 | E26: =(0.19*1.16*E22)/1000 -> 0.029287604 | F26: =(0*1.16*F22)/1000 -> 0 | G26: =(0.19*1.16*G22)/1000 -> 0.030249283 | H26: =(0.19*1.16*H22)/1000 -> 0.02958056 | I26: =(0.19*1.16*I22)/1000 -> 0.029698018
B27: KPRL hospitality Charges/Storage | C27: [3.28USD*16%VAT] | D27: =(3.28*1.16*D22)/1000 -> 0.52554333 | E27: =(3.28*1.16*E22)/1000 -> 0.50559654 | F27: =(0*1.16*F22)/1000 -> 0 | G27: =(3.28*1.16*G22)/1000 -> 0.52219815 | H27: =(3.28*1.16*H22)/1000 -> 0.51065388 | I27: =(3.28*1.16*I22)/1000 -> 0.51268158
B28: Direct Order charges | C28: ; | D28: =(195*D22)/D34 -> 0.00052669354 | E28: =(0*E22)/E34 -> 0 | F28: =(455*F22)/F34 -> 0.0038034138 | G28: =(0*G22)/G34 -> 0 | H28: =(130*H22)/H34 -> 0.00034936303 | I28: =(0*I22)/I34 -> 0
B29: Escalation | C29: KShs. 0.2570/ Litre | D29: 0 | E29: 0
B30: RML | C30: KShs. 0.2699/ Litre | D30: 0 | E30: 0
B31: DI Collection charges | C31: KShs. 0.2105/ Litre | D31: 0 | E31: 0 | F31: 0 | G31: 0 | H31: 0 | I31: 0
B32: Import Declaration (IDF) Fees | D32: ='PMS Import'!$S10 -> 2.9409597 | E32: ='PMS Import'!$S11 -> 3.2129217 | F32: ='PMS Import'!$S12 -> 3.1273802 | G32: ='PMS Import'!$S13 -> 3.1382742 | H32: ='PMS Import'!$S14 -> 3.004701 | I32: ='PMS Import'!$S15 -> 3.0869281
B33: Unit Cargo cost in KShs/Litre | D33: =SUM(D24:D32) -> 89.809979 | E33: =SUM(E24:E32) -> 98.059844 | F33: =SUM(F24:F32) -> 94.887285 | G33: =SUM(G24:G32) -> 95.770399 | H33: =SUM(H24:H32) -> 91.724182 | I33: =SUM(I24:I32) -> 94.220757
B34: Product Volume in Litres | D34: =D36*1000 -> 51139127 | E34: =E36*1000 -> 16692116 | F34: =F36*1000 -> 16418796 | G34: =G36*1000 -> 5309353 | H34: =H36*1000 -> 49941457 | I34: =I36*1000 -> 20556675 | J34: =SUM(D34:I34) -> 160057524
B35: Weighted Average cost for all cargoes in KShs/Litre | J35: =((D33*D34)+(E33*E34)+(F33*F34)+(G33*G34)+(H33*H34)+(I33*I34))/J34 -> 92.552655
D36: ='PMS Import'!H10 -> 51139.127 | E36: ='PMS Import'!H11 -> 16692.116 | F36: ='PMS Import'!H12 -> 16418.796 | G36: ='PMS Import'!H13 -> 5309.353 | H36: ='PMS Import'!$H14 -> 49941.457 | I36: ='PMS Import'!$H15 -> 20556.675 | J36: ='WEIGHTED AVERAGE COST'!M31 -> 1.0004702
B37: Landed Cost KShs/Litre | J37: =SUM(J35:J36) -> 93.553125
C39: VAT factor | D39: 1.16 | E39: 1.16 | F39: 1.16 | G39: 1.16 | H39: 1.16 | I39: 1.16
C40: Applicable exchange rate | D40: =D$22 -> 138.1264 | E40: =E$22 -> 132.88387 | F40: =F$22 -> 137.2472 | G40: =G$22 -> 137.2472 | H40: =H$22 -> 134.21307 | I40: =I$22 -> 134.746
C41: Conversion factor | D41: =D$23 -> 1.3776364 | E41: =E$23 -> 1.3413549 | F41: =F$23 -> 1.3505752 | G41: =G$23 -> 1.3458869 | H41: =H$23 -> 1.3719303 | I41: =I$23 -> 1.3406885
C42: Product Volume | D42: =D$34 -> 51139127 | E42: =E$34 -> 16692116 | F42: =F$34 -> 16418796 | G42: =G$34 -> 5309353 | H42: =H$34 -> 49941457 | I42: =I$34 -> 20556675
B44: Weighted VAT charged costs | D44: =((D$42*D$50)+(E42*E50)+(F42*F50)+(G42*G50)+(H42*H50)+(I42*I50))/J34 -> 0.6458438
B45: Weighted Non-VAT charged costs | D45: =J36+((D$42*D$60)+(E42*E60)+(F42*F60)+(G42*G60)+(H42*H60)+(I42*I60))/J34 -> 89.740845
B46: Merchant Shipping Fee | D46: =((D$42*D$74)+(E42*E74)+(F42*F74)+(G74*G42)+(H42*H74)+(I42*I74))/J34 -> 0.029475332
B47: Import Declaration Fees (IDF) | D47: =((D42*D75)+(E42*E75)+(F42*F75)+(G75*G42)+(H42*H75)+(I42*I75))/J34 -> 3.0336263
B50: VAT charged costs (KShs/litre) | D50: =D55+D56 -> 0.70225472 | E50: =E55+E56 -> 0.6895905 | F50: =F55+F56 -> 0.22517742 | G50: =G55+G56 -> 0.70561385 | H50: =H55+H56 -> 0.68576719 | I50: =I55+I56 -> 0.69354764
B51: KPA Wharfage | D51: =D$14/$D$39 -> 297.88 | E51: =E$14/$D$39 -> 295.68 | F51: =F$14/$D$39 -> 293.26 | G51: =G$14/$D$39 -> 293.26 | H51: =H$14/$D$39 -> 292.6 | I51: =I$14/$D$39 -> 292.6
B52: Inspection Charges | D52: =D$18/$D$39 -> 8.66211 | E52: =E$18/$D$39 -> 8.9821516 | F52: =F$18/$D$39 -> 8.995079 | G52: =G$18/$D$39 -> 9.7 | H52: =H$18/$D$39 -> 8.6658585 | I52: =I$18/$D$39 -> 8.8919161
B53: Analysis +Recertification Charges | D53: =D$20/$D$39 -> 0.61034398 | E53: =E$20/$D$39 -> 1.8153006 | F53: =F$20/$D$39 -> 1.8639723 | G53: =G$20/$D$39 -> 5.7407878 | H53: =H$20/$D$39 -> 0.62445726 | I53: =I$20/$D$39 -> 1.4755642
B54: Sub-total (KShs/MT) | D54: =SUM(D$51:D$53) -> 307.15245 | E54: =SUM(E$51:E$53) -> 306.47745 | F54: =SUM(F$51:F$53) -> 304.11905 | G54: =SUM(G$51:G$53) -> 308.70079 | H54: =SUM(H$51:H$53) -> 301.89032 | I54: =SUM(I$51:I$53) -> 302.96748
B55: Sub-total (KShs/Litre) | D55: =D$54/(D$41*1000) -> 0.22295611 | E55: =E$54/(E$41*1000) -> 0.22848349 | F55: =F$54/(F$41*1000) -> 0.22517742 | G55: =G$54/(G$41*1000) -> 0.22936606 | H55: =H$54/(H$41*1000) -> 0.22004785 | I55: =I$54/(I$41*1000) -> 0.22597902
B56: Storage and vessel handling (KShs/litre) | D56: =D$57+D$58 -> 0.47929861 | E56: =E$57+E$58 -> 0.46110702 | F56: =F$57+F$58 -> 0 | G56: =G$57+G$58 -> 0.47624778 | H56: =H$57+H$58 -> 0.46571934 | I56: =I$57+I$58 -> 0.46756862
B57: Kipevu/SOT shore handling charges | D57: =D$26/$D$39 -> 0.026244016 | E57: =E$26/$D$39 -> 0.025247935 | F57: =F$26/$D$39 -> 0 | G57: =G$26/$D$39 -> 0.026076968 | H57: =H$26/$D$39 -> 0.025500483 | I57: =I$26/$D$39 -> 0.02560174
B58: KPRL hospitality Charges | D58: =D$27/$D$39 -> 0.45305459 | E58: =E$27/$D$39 -> 0.43585908 | F58: =F$27/$D$39 -> 0 | G58: =G$27/$D$39 -> 0.45017082 | H58: =H$27/$D$39 -> 0.44021886 | I58: =I$27/$D$39 -> 0.44196688
B60: Non-VAT charged costs (KShs/litre) | D60: =SUM(D$61,D$62,D$68) -> 86.024919 | E60: =SUM(E$61,E$62,E$68) -> 94.016938 | F60: =SUM(F$61,F$62,F$68) -> 91.469089 | G60: =SUM(G$61,G$62,G$68) -> 91.7839 | H60: =SUM(H$61,H$62,H$68) -> 87.894908 | I60: =SUM(I$61,I$62,I$68) -> 90.299553
B61: USD based costs | D61: =D$24 -> 84.803532 | E61: =E$24 -> 92.658493 | F61: =F$24 -> 90.187097 | G61: =G$24 -> 90.501259 | H61: =H$24 -> 86.641255 | I61: =I$24 -> 89.017044
B62: KShs based Costs I | D62: =SUM(D$63:D$67)/(D$41*1000) -> 1.2208596 | E62: =SUM(E$63:E$67)/(E$41*1000) -> 1.3584455 | F62: =SUM(F$63:F$67)/(F$41*1000) -> 1.2781885 | G62: =SUM(G$63:G$67)/(G$41*1000) -> 1.282641 | H62: =SUM(H$63:H$67)/(H$41*1000) -> 1.253304 | I62: =SUM(I$63:I$67)/(I$41*1000) -> 1.2825095
B63: Insurance | D63: =D$12 -> 282.90053 | E63: =E$12 -> 310.48382 | F63: =F$12 -> 292.20943 | G63: =G$12 -> 292.20943 | H63: =H$12 -> 290.97674 | I63: =I$12 -> 290.97674
B64: War Risk | D64: =D$13 -> 31.212415 | E64: =E$13 -> 34.25568 | F64: =F$13 -> 32.239466 | G64: =G$13 -> 32.239466 | H64: =H$13 -> 32.103463 | I64: =I$13 -> 32.103463
B65: Stevedoring Charges | D65: =D$15 -> 223.41 | E65: =E$15 -> 221.76 | F65: =F$15 -> 219.945 | G65: =G$15 -> 219.945 | H65: =H$15 -> 219.45 | I65: =I$15 -> 219.45
B66: Ocean Losses | D66: =D$16 -> 577.00599 | E66: =E$16 -> 632.9667 | F66: =F$16 -> 595.85476 | G66: =G$16 -> 595.85476 | H66: =H$16 -> 593.34664 | I66: =I$16 -> 593.34664
B67: Adminstration Fees | D67: =D$17 -> 567.37162 | E67: =E$17 -> 622.69135 | F67: =F$17 -> 586.0411 | G67: =G$17 -> 586.0411 | H67: =H$17 -> 583.56887 | I67: =I$17 -> 583.56887
B68: KShs based Costs II | D68: =SUM(D$69:D$72) -> 0.00052669354 | E68: =SUM(E$69:E$72) -> 0 | F68: =SUM(F$69:F$72) -> 0.0038034138 | G68: =SUM(G$69:G$72) -> 0 | H68: =SUM(H$69:H$72) -> 0.00034936303 | I68: =SUM(I$69:I$72) -> 0
B69: Escalation | D69: =D$29 -> 0 | E69: =E$29 -> 0 | F69: =F$29 -> 0 | G69: =G$29 -> 0 | H69: =H$29 -> 0 | I69: =I$29 -> 0
B70: RML | D70: =D$30 -> 0 | E70: =E$30 -> 0 | F70: =F$30 -> 0 | G70: =G$30 -> 0 | H70: =H$30 -> 0 | I70: =I$30 -> 0
B71: KOSF Charges Recovery | D71: =D$31 -> 0 | E71: =E$31 -> 0 | F71: =F$31 -> 0 | G71: =G$31 -> 0 | H71: =H$31 -> 0 | I71: =I$31 -> 0
B72: Direct order charges | D72: =D$28 -> 0.00052669354 | E72: =E$28 -> 0 | F72: =F$28 -> 0.0038034138 | G72: =G$28 -> 0 | H72: =H$28 -> 0.00034936303 | I72: =I$28 -> 0
B74: Merchant Shipping Fee | D74: =D$19/(D$41*1000) -> 0.029485284 | E74: =E19/(E$41*1000) -> 0.030059158 | F74: =F19/(F$41*1000) -> 0.029609605 | G74: =G19/(G$41*1000) -> 0.029712749 | H74: =H19/(H$41*1000) -> 0.02908311 | I74: =I19/(I$41*1000) -> 0.029760828
B75: Import Declaration Fees (IDF) | D75: =D$32 -> 2.9409597 | E75: =E$32 -> 3.2129217 | F75: =F$32 -> 3.1273802 | G75: =G$32 -> 3.1382742 | H75: =H$32 -> 3.004701 | I75: =I$32 -> 3.0869281

Sheet AGO SUMMARY
C3: DIESEL | E3: ='AGO Import'!E10 -> MT SEALEGEND | F3: ='AGO Import'!E11 -> MT STI LOTUS | G3: ='AGO Import'!E12 -> MT SERENGETI-VTTI | H3: ='AGO Import'!$E13 -> MT SERENGETI-KOSF | I3: ='AGO Import'!$E14 -> MT PIS POLARIS | J3: ='AGO Import'!$E15 -> MT PHILOXENIA
E4: ='AGO Import'!C10 -> TEXAS | F4: ='AGO Import'!C11 -> ORYX ENERGIES | G4: ='AGO Import'!C12 -> E3 ENERGY | H4: ='AGO Import'!$C13 -> E3 ENERGY | I4: ='AGO Import'!$C14 -> E3 ENERGY | J4: ='AGO Import'!$C15 -> E3 ENERGY
C5: Costs paid in USD | E5: USD/MT | F5: USD/MT | G5: USD/MT | H5: USD/MT | I5: USD/MT | J5: USD/MT
C6: Free On Board (FOB) | D6: Platts based | E6: 847.33459 | F6: 774.9379 | G6: 777.15868 | H6: 777.15868 | I6: 849.05424 | J6: 791.7308 | K6: =AVERAGE(E6:H6) -> 794.14746
C7: Freight & Premium (F&P) | D7: Varies as per Tender | E7: 76.72 | F7: 78.71 | G7: 78.98 | H7: 78.98 | I7: 102.3 | J7: 104.94 | K7: =AVERAGE(E7:H7) -> 78.3475
C8: Letter of Credit Charges | D8: [1.20%*C&F] | E8: 11.088655 | F8: 10.243775 | G8: 10.273664 | H8: 10.273664 | I8: 11.416251 | J8: 10.76005 | K8: =AVERAGE(E8:H8) -> 10.46994
C9: Certificate of Conformity (CoC) | E9: 0.030257275 | F9: 0.030087967 | G9: 0.03993257 | H9: 0.03993257 | I9: 0.1630838 | J9: 0.16786829
C10: Total USD based Cost | E10: =SUM(E6:E9) -> 935.17351 | F10: =SUM(F6:F9) -> 863.92176 | G10: =SUM(G6:G9) -> 866.45228 | H10: =SUM(H6:H9) -> 866.45228 | I10: =SUM(I6:I9) -> 962.93358 | J10: =SUM(J6:J9) -> 907.59871
C11: Costs paid in KShs | E11: KSHS/MT | F11: KSHS/MT | G11: KSHS/MT | H11: KSHS/MT | I11: KSHS/MT | J11: KSHS/MT
C12: Insurance | D12: [1.003*C&F*0.0770%] | E12: 304.93802 | F12: 283.83793 | G12: 285.2012 | H12: 285.2012 | I12: 319.89286 | J12: 298.81554
C13: War Risk | D13: [1.003*C&F*0.0275%] | E13: 33.643811 | F13: 31.315838 | G13: 31.466248 | H13: 31.466248 | I13: 35.29378 | J13: 32.968319
C14: KPA Wharfage | D14: [USD 2.20/MT + 16% VAT] | E14: 336.864 | F14: 339.416 | G14: 340.054 | H14: 340.054 | I14: 343.244 | J14: 340.1816
C15: Stevedoring Charges | D15: [USD 1.65/MT] | E15: 217.8 | F15: 219.45 | G15: 219.8625 | H15: 219.8625 | I15: 221.925 | J15: 219.945
C16: Ocean Losses | D16: [0.50%*CIFLW] | E16: 621.66077 | F16: 578.85806 | G16: 581.63014 | H16: 581.63014 | I16: 652.06494 | J16: 609.26221
C17: Adminstration Fees | D17: 0.5% of CIF | E17: 611.56894 | F17: 569.25162 | G17: 571.98573 | H17: 571.98573 | I17: 641.56166 | J17: 599.29
C18: Inspection Charges | E18: 9.9978595 | F18: 9.9957329 | G18: 10.147617 | H18: 10.291545 | I18: 10.338156 | J18: 10.292727
C19: Analysis +Recertification Charges | E19: 0.68585087 | F19: 0.67527093 | G19: 1.4308936 | H19: 2.1469341 | I19: 2.3788282 | J19: 2.1528181
C20: Merchant Shipping Fee | D20: USD 0.3/MT | E20: 39.6 | F20: 39.9 | G20: 39.975 | H20: 39.975 | I20: 40.35 | J20: 39.99
C21: Total Kshs based costs | E21: =SUM(E12:E20) -> 2176.7593 | F21: =SUM(F12:F20) -> 2072.7005 | G21: =SUM(G12:G20) -> 2081.7533 | H21: =SUM(H12:H20) -> 2082.6133 | I21: =SUM(I12:I20) -> 2267.0492 | J21: =SUM(J12:J20) -> 2152.8982
C22: Exchange rate (USD/KShs) | E22: ='AGO Import'!$M10 -> 133.1196 | F22: ='AGO Import'!$M11 -> 137.2472 | G22: ='AGO Import'!$M12 -> 135.62893 | H22: ='AGO Import'!$M13 -> 135.62893 | I22: ='AGO Import'!$M14 -> 133.18867 | J22: ='AGO Import'!$M15 -> 137.2472 | K22: =AVERAGE(E22:H22) -> 135.40617
C23: Conversion factor (M3/MT) | E23: ='AGO Import'!H10/'AGO Import'!G10 -> 1.2186206 | F23: ='AGO Import'!H11/'AGO Import'!G11 -> 1.1936395 | G23: ='AGO Import'!H12/'AGO Import'!G12 -> 1.1963367 | H23: ='AGO Import'!$H13/'AGO Import'!$G13 -> 1.1966613 | I23: ='AGO Import'!$H14/'AGO Import'!$G14 -> 1.2215235 | J23: ='AGO Import'!$H15/'AGO Import'!$G15 -> 1.2219094 | K23: =AVERAGE(E23:H23) -> 1.2013145 | L23: =K8*K22/(K23*1000) -> 1.1801192
C24: USD based Cost coverted to KShs/Litre | E24: =(E10*E22)/(E23*1000) -> 102.15643 | F24: =(F10*F22)/(F23*1000) -> 99.335557 | G24: =(G10*G22)/(G23*1000) -> 98.229867 | H24: =(H10*H22)/(H23*1000) -> 98.203226 | I24: =(I10*I22)/(I23*1000) -> 104.99335 | J24: =(J10*J22)/(J23*1000) -> 101.94322
C25: Kshs based cost converted KShs/Litre | E25: =E21/(E23*1000) -> 1.7862485 | F25: =F21/(F23*1000) -> 1.7364543 | G25: =G21/(G23*1000) -> 1.7401065 | H25: =H21/(H23*1000) -> 1.7403532 | I25: =I21/(I23*1000) -> 1.8559195 | J25: =J21/(J23*1000) -> 1.7619131
C26: Kipevu shore handling charges | D26: [0.19USD*16%VAT] | E26: =(0.19*1.16*E22)/1000 -> 0.02933956 | F26: =(0.19*1.16*F22)/1000 -> 0.030249283 | G26: =(0.19*1.16*G22)/1000 -> 0.029892617 | H26: =(0.19*1.16*H22)/1000 -> 0.029892617 | I26: =(0*1.16*I22)/1000 -> 0 | J26: =(0*1.16*J22)/1000 -> 0
C27: KPRL hospitality Charges | D27: [3.28USD*16%VAT] | E27: =(3.28*1.16*E22)/1000 -> 0.50649345 | F27: =(3.28*1.16*F22)/1000 -> 0.52219815 | G27: =(0*1.16*G22)/1000 -> 0 | H27: =(3.28*1.16*H22)/1000 -> 0.51604097 | I27: =(0*1.16*I22)/1000 -> 0 | J27: =(0*1.16*J22)/1000 -> 0
C28: Direct Order charges | E28: =(65*E22)/E35 -> 0.00014048485 | F28: =(195*F22)/F35 -> 0.00043727659 | G28: =(0*G22)/G35 -> 0 | H28: =(0*H22)/H35 -> 0 | I28: =(260*I22)/I35 -> 0.0019435616 | J28: =(260*J22)/J35 -> 0.0018141765
C29: Excise | D29: KShs. 0.0121/ Litre | E29: 0 | F29: 0
C30: RML | D30: KShs. 0.3621/ Litre | E30: 0 | F30: 0
C31: KOSF Charges Recovery | D31: KShs. 0.1643/ Litre | E31: 0 | F31: 0
C32: Excise Duty Recovery Charges | E32: 0 | F32: 0 | G32: 0 | H32: 0 | I32: 0 | J32: 0
C33: Import Declaration (IDF) Fees | E33: ='AGO Import'!$S10 -> 3.5427705 | F33: ='AGO Import'!$S11 -> 3.4449347 | G33: ='AGO Import'!$S12 -> 3.4065513 | H33: ='AGO Import'!$S13 -> 3.4056274 | I33: ='AGO Import'!$S14 -> 3.6406558 | J33: ='AGO Import'!$S15 -> 3.534837
C34: Unit Cargo cost in KShs/Litre | E34: =SUM(E24:E33) -> 108.02142 | F34: =SUM(F24:F33) -> 105.06983 | G34: =SUM(G24:G33) -> 103.40642 | H34: =SUM(H24:H33) -> 103.89514 | I34: =SUM(I24:I33) -> 110.49187 | J34: =SUM(J24:J33) -> 107.24178
C35: Product Volume in Litres | E35: =E37*1000 -> 61592220 | F35: =F37*1000 -> 61204292 | G35: =G37*1000 -> 28949991 | H35: =H37*1000 -> 19278644 | I35: =I37*1000 -> 17817317 | J35: =J37*1000 -> 19669680 | K35: =SUM(E35:J35) -> 2.0851214e+08
C36: Weighted Average cost for all cargoes in KShs/Litre | K36: =((E34*E35)+(F34*F35)+(G34*G35)+(H34*H35)+(I34*I35)+(J34*J35))/K35 -> 106.27034
C37: Volume in M3 | E37: ='AGO Import'!H10 -> 61592.22 | F37: ='AGO Import'!H11 -> 61204.292 | G37: ='AGO Import'!H12 -> 28949.991 | H37: ='AGO Import'!$H13 -> 19278.644 | I37: ='AGO Import'!$H14 -> 17817.317 | J37: ='AGO Import'!$H15 -> 19669.68 | K37: ='WEIGHTED AVERAGE COST'!M66 -> 0.35637073
C38: Landed Cost KShs/Litre | K38: =SUM(K36:K37) -> 106.62671
D41: VAT factor | E41: 1.16 | F41: 1.16 | G41: 1.16 | H41: 1.16 | I41: 1.16 | J41: 1.16
D42: Applicable exchange rate | E42: =E$22 -> 133.1196 | F42: =F$22 -> 137.2472 | G42: =G$22 -> 135.62893 | H42: =H$22 -> 135.62893 | I42: =I$22 -> 133.18867 | J42: =J$22 -> 137.2472
D43: Conversion factor | E43: =E$23 -> 1.2186206 | F43: =F$23 -> 1.1936395 | G43: =G$23 -> 1.1963367 | H43: =H$23 -> 1.1966613 | I43: =I$23 -> 1.2215235 | J43: =J$23 -> 1.2219094
D44: Product Volume | E44: =E$35 -> 61592220 | F44: =F$35 -> 61204292 | G44: =G$35 -> 28949991 | H44: =H$35 -> 19278644 | I44: =I$35 -> 17817317 | J44: =J$35 -> 19669680
C46: Weighted VAT charged costs | E46: =((E$44*E$51)+(F44*F51)+(G44*G51)+(H44*H51)+(I44*I51)+(J44*J51))/K35 -> 0.5737644
C47: Weighted Non-VAT charged costs | E47: =K37+((E$44*E$61)+(F44*F61)+(G44*G61)+(H44*H61)+(I44*I61)+(J61*J44))/K35 -> 102.43802
C48: Merchant Shipping Fee | E48: =((E$44*E$75)+(F44*F75)+(G44*G75)+(H44*H75)+(I44*I75)+(J75*J44))/K35 -> 0.033048548
C49: Import Declaration Fees (IDF) | E49: =((E$44*E$76)+(F44*F76)+(G44*G76)+(H44*H76)+(I44*I76)+(J76*J44))/K35 -> 3.490076
C51: VAT charged costs (KShs/litre) | E51: =E56+E57 -> 0.70778504 | F51: =F56+F57 -> 0.72908723 | G51: =G56+G57 -> 0.27915257 | H51: =H56+H57 -> 0.72456627 | I51: =I56+I57 -> 0.25121328 | J51: =J56+J57 -> 0.24878187
C52: KPA Wharfage | E52: =E$14/$E$41 -> 290.4 | F52: =F$14/$E$41 -> 292.6 | G52: =G$14/$E$41 -> 293.15 | H52: =H$14/$E$41 -> 293.15 | I52: =I$14/$E$41 -> 295.9 | J52: =J$14/$E$41 -> 293.26
C53: Inspection Charges | E53: =E$18/$E$41 -> 8.6188444 | F53: =F$18/$E$41 -> 8.6170111 | G53: =G$18/$E$41 -> 8.7479455 | H53: =H$18/$E$41 -> 8.8720212 | I53: =I$18/$E$41 -> 8.9122038 | J53: =J$18/$E$41 -> 8.8730407
C54: Analysis +Recertification Charges | E54: =E$19/$E$41 -> 0.59125075 | F54: =F$19/$E$41 -> 0.58213011 | G54: =G$19/$E$41 -> 1.2335289 | H54: =H$19/$E$41 -> 1.8508053 | I54: =I$19/$E$41 -> 2.050714 | J54: =J$19/$E$41 -> 1.8558777
C55: Sub-total (KShs/MT) | E55: =SUM(E$52:E$54) -> 299.6101 | F55: =SUM(F$52:F$54) -> 301.79914 | G55: =SUM(G$52:G$54) -> 303.13147 | H55: =SUM(H$52:H$54) -> 303.87283 | I55: =SUM(I$52:I$54) -> 306.86292 | J55: =SUM(J$52:J$54) -> 303.98892
C56: Sub-total (KShs/Litre) | E56: =E$55/(E$43*1000) -> 0.24586003 | F56: =F$55/(F$43*1000) -> 0.25283944 | G56: =G$55/(G$43*1000) -> 0.25338307 | H56: =H$55/(H$43*1000) -> 0.25393387 | I56: =I$55/(I$43*1000) -> 0.25121328 | J56: =J$55/(J$43*1000) -> 0.24878187
C57: Storage and vessel handling (KShs/litre) | E57: =E$58+E$59 -> 0.46192501 | F57: =F$58+F$59 -> 0.47624778 | G57: =G$58+G$59 -> 0.025769497 | H57: =H$58+H$59 -> 0.4706324 | I57: =I$58+I$59 -> 0 | J57: =J$58+J$59 -> 0
C58: Kipevu/SOT shore handling charges | E58: =E$26/$E$41 -> 0.025292724 | F58: =F$26/$E$41 -> 0.026076968 | G58: =G$26/$E$41 -> 0.025769497 | H58: =H$26/$E$41 -> 0.025769497 | I58: =I$26/$E$41 -> 0 | J58: =J$26/$E$41 -> 0
C59: KPRL hospitality Charges | E59: =E$27/$E$41 -> 0.43663229 | F59: =F$27/$E$41 -> 0.45017082 | G59: =G$27/$E$41 -> 0 | H59: =H$27/$E$41 -> 0.4448629 | I59: =I$27/$E$41 -> 0 | J59: =J$27/$E$41 -> 0
C61: Non-VAT charged costs (KShs/litre) | E61: =SUM(E$62,E$63,E$69) -> 103.62512 | F61: =SUM(F$62,F$63,F$69) -> 100.74573 | G61: =SUM(G$62,G$63,G$69) -> 99.642635 | H61: =SUM(H$62,H$63,H$69) -> 99.61561 | I61: =SUM(I$62,I$63,I$69) -> 106.52677 | J61: =SUM(J$62,J$63,J$69) -> 103.38563
C62: USD based costs | E62: =E$24 -> 102.15643 | F62: =F$24 -> 99.335557 | G62: =G$24 -> 98.229867 | H62: =H$24 -> 98.203226 | I62: =I$24 -> 104.99335 | J62: =J$24 -> 101.94322
C63: KShs based Costs I | E63: =SUM(E$64:E$68)/(E$43*1000) -> 1.4685552 | F63: =SUM(F$64:F$68)/(F$43*1000) -> 1.4097334 | G63: =SUM(G$64:G$68)/(G$43*1000) -> 1.4127676 | H63: =SUM(H$64:H$68)/(H$43*1000) -> 1.4123845 | I63: =SUM(I$64:I$68)/(I$43*1000) -> 1.5314796 | J63: =SUM(J$64:J$68)/(J$43*1000) -> 1.4405986
C64: Insurance | E64: =E$12 -> 304.93802 | F64: =F$12 -> 283.83793 | G64: =G$12 -> 285.2012 | H64: =H$12 -> 285.2012 | I64: =I$12 -> 319.89286 | J64: =J$12 -> 298.81554
C65: War Risk | E65: =E$13 -> 33.643811 | F65: =F$13 -> 31.315838 | G65: =G$13 -> 31.466248 | H65: =H$13 -> 31.466248 | I65: =I$13 -> 35.29378 | J65: =J$13 -> 32.968319
C66: Stevedoring Charges | E66: =E$15 -> 217.8 | F66: =F$15 -> 219.45 | G66: =G$15 -> 219.8625 | H66: =H$15 -> 219.8625 | I66: =I$15 -> 221.925 | J66: =J$15 -> 219.945
C67: Ocean Losses | E67: =E$16 -> 621.66077 | F67: =F$16 -> 578.85806 | G67: =G$16 -> 581.63014 | H67: =H$16 -> 581.63014 | I67: =I$16 -> 652.06494 | J67: =J$16 -> 609.26221
C68: Adminstration Fees | E68: =E$17 -> 611.56894 | F68: =F$17 -> 569.25162 | G68: =G$17 -> 571.98573 | H68: =H$17 -> 571.98573 | I68: =I$17 -> 641.56166 | J68: =J$17 -> 599.29
C69: KShs based Costs II | E69: =SUM(E$70:E$73) -> 0.00014048485 | F69: =SUM(F$70:F$73) -> 0.00043727659 | G69: =SUM(G$70:G$73) -> 0 | H69: =SUM(H$70:H$73) -> 0 | I69: =SUM(I$70:I$73) -> 0.0019435616 | J69: =SUM(J$70:J$73) -> 0.0018141765
C70: Excise | E70: =E32 -> 0 | F70: =F32 -> 0 | G70: =G32 -> 0 | H70: =H32 -> 0 | I70: =I32 -> 0 | J70: =J32 -> 0
C71: RML | E71: =E$30 -> 0 | F71: =F$30 -> 0 | G71: =G$30 -> 0 | H71: =H$30 -> 0 | I71: =I$30 -> 0 | J71: =J$30 -> 0
C72: KOSF Charges Recovery | E72: =E$31 -> 0 | F72: =F$31 -> 0 | G72: =G$31 -> 0 | H72: =H$31 -> 0 | I72: =I$31 -> 0 | J72: =J$31 -> 0
C73: Direct order charges | E73: =E28 -> 0.00014048485 | F73: =F28 -> 0.00043727659 | G73: =G28 -> 0 | H73: =H28 -> 0 | I73: =I28 -> 0.0019435616 | J73: =J28 -> 0.0018141765
C75: Merchant Shipping Fees | E75: =E$20/(E$43*1000) -> 0.032495758 | F75: =F$20/(F$43*1000) -> 0.033427178 | G75: =G$20/(G$43*1000) -> 0.033414505 | H75: =H$20/(H$43*1000) -> 0.033405443 | I75: =I$20/(I$43*1000) -> 0.033032522 | J75: =J$20/(J$43*1000) -> 0.032727466
C76: Import Declaration Fees (IDF) | E76: =E$33 -> 3.5427705 | F76: =F$33 -> 3.4449347 | G76: =G$33 -> 3.4065513 | H76: =H$33 -> 3.4056274 | I76: =I$33 -> 3.6406558 | J76: =J$33 -> 3.534837

Sheet DPK SUMMARY
B3: KEROSENE | D3: KOSF | E3: KOSF
D4: ='DPK Import'!E10 -> MT NAKHAL SILVER | E4: ='DPK Import'!E11 -> MT HAFNIA LUPUS
D5: ='DPK Import'!C10 -> E3 ENERGY | E5: ='DPK Import'!C11 -> ORYX ENERGIES
B6: Costs paid in USD | D6: USD/MT | E6: USD/MT
B7: Free On Board (FOB) | C7: Platts based | D7: 882.04495 | E7: 821.18078 | F7: =AVERAGE(D7:E7) -> 851.61287
B8: Freight & Premium (F&P) | C8: Varies as per Tender | D8: 97.62 | E8: 76.55 | F8: =AVERAGE(D8:E8) -> 87.085
B9: Letter of Credit Charges | C9: [1.2%*C&F] | D9: 11.755979 | E9: 10.772769 | F9: =AVERAGE(D9:E9) -> 11.264374
B10: Certificate of Conformity Cost (CoC) | D10: 0.071118682 | E10: 0.064633753
B11: Total USD based Cost | D11: =SUM(D7:D10) -> 991.49204 | E11: =SUM(E7:E10) -> 908.56819
B12: Costs paid in KShs | D12: KSHS/MT | E12: KSHS/MT
B13: Insurance | C13: [1.003*C&F*0.0770%] | D13: 329.77971 | E13: 303.88187
B14: War Risk | C14: [1.003*C&F*0.0275%] | D14: 36.384596 | E14: 33.527287
B15: KPA Wharfage | C15: [USD 2.20/MT + 16% VAT] | D15: 343.6268 | E15: 345.5408
B16: Stevedoring Charges | C16: [USD 1.65/MT] | D16: 222.1725 | E16: 223.41
B17: Ocean Losses | C17: [0.1%*CIFLW] | D17: 672.13396 | E17: 619.58871
B18: Adminstration Fees | C18: [0.5% of CIF] | D18: 661.39025 | E18: 609.45079
B19: Inspection Charges | D19: 10.100381 | E19: 10.112441
B20: Analysis +Recertification Charges | D20: 40.395 | E20: 40.62
B21: Merchant Shipping Fee | C21: [USD 0.3/MT] | D21: 1.8060647 | E21: 1.8966746
B22: Total Kshs based costs (KShs/Litre) | D22: =SUM(D13:D21) -> 2317.7893 | E22: =SUM(E13:E21) -> 2188.0286
B23: Exchange rate (USD/KShs) | D23: ='DPK Import'!M10 -> 133.90013 | E23: ='DPK Import'!M11 -> 138.73427 | F23: =AVERAGE(D23:E23) -> 136.3172
B24: Conversion factor (M3/MT) | D24: ='DPK Import'!H10/'DPK Import'!G10 -> 1.274895 | E24: ='DPK Import'!H11/'DPK Import'!G11 -> 1.2738178 | F24: =AVERAGE(D24:E24) -> 1.2743564 | H24: =F9*F23/(F24*1000) -> 1.2049439
B25: USD based Cost coverted to KShs/Litre | D25: =(D11*D23)/(D24*1000) -> 104.13479 | E25: =(E11*E23)/(E24*1000) -> 98.954136
B26: Kshs based cost converted KShs/Litre | D26: =D22/(D24*1000) -> 1.8180237 | E26: =E22/(E24*1000) -> 1.7176935
B27: Kipevu shore handling charges | C27: [0.19USD*16%VAT] | D27: =(0.19*1.16*D$23)/1000 -> 0.029511589 | E27: =(0.19*1.16*E$23)/1000 -> 0.030577032
B28: KPRL hospitality Charges | C28: [3.28USD*16%VAT] | D28: =(3.28*1.16*D$23)/1000 -> 0.50946323 | E28: =(3.28*1.16*E$23)/1000 -> 0.52785614
B29: Direct Order charges | D29: =(0*D$23)/D$33 -> 0 | E29: =(0*E$23)/E$33 -> 0
B30: KOSF Charges Recovery | C30: [KShs 0.2974/ltr] | D30: 0 | E30: 0
B31: Import Declaration Fees | D31: ='DPK Import'!S10 -> 3.6112377 | E31: ='DPK Import'!S11 -> 3.4315825
B32: Unit Cargo cost in KShs/Litre | D32: =SUM(D25:D31) -> 110.10302 | E32: =SUM(E25:E31) -> 104.66185
B33: Product Volume in Litres | D33: =D35*1000 -> 36938085 | E33: =E35*1000 -> 35193855 | F33: =SUM(D33:E33) -> 72131940
B34: Weighted Average cost for all cargoes in KShs/Litre | F34: =((D32*D33)+(E32*E33))/F33 -> 107.44822
B35: Volume in M3 | D35: ='DPK Import'!H10 -> 36938.085 | E35: ='DPK Import'!H11 -> 35193.855 | F35: ='WEIGHTED AVERAGE COST'!M96 -> 1.5983377
B36: Landed Cost KShs/Litre | F36: =SUM(F34:F35) -> 109.04656
C38: VAT factor | D38: 1.16 | E38: 1.16
C39: Applicable exchange rate | D39: =D$23 -> 133.90013 | E39: =E$23 -> 138.73427
C40: Conversion factor | D40: =D$24 -> 1.274895 | E40: =E$24 -> 1.2738178
C41: Product Volume | D41: =D$33 -> 36938085 | E41: =E$33 -> 35193855
B43: Weighted VAT charged costs | D43: =((D41*D48)+(E41*E48))/F33 -> 0.74013888
B44: Weighted Non-VAT charged costs | D44: =F35+((D41*D58)+(E41*E58))/F33 -> 104.66296
B45: Merchant Shipping Fee | D45: =((D41*D70)+(E41*E70))/F33 -> 0.0014519287
B46: Import Declaration Fees (IDF) | D46: =((D41*D71)+(E41*E71))/F33 -> 3.5235822
B48: VAT charged costs (KShs/litre) | D48: =D53+D54 -> 0.73113424 | E48: =E53+E54 -> 0.74958979
B49: KPA Wharfage | D49: =D$15/D38 -> 296.23 | E49: =E$15/E38 -> 297.88
B50: Inspection Charges | D50: =D$19/D38 -> 8.7072252 | E50: =E$19/E38 -> 8.7176217
B51: Analysis +Recertification Charges | D51: =D$20/D38 -> 34.823276 | E51: =E$20/E38 -> 35.017241
B52: Sub-total (KShs/MT) | D52: =SUM(D$49:D$51) -> 339.7605 | E52: =SUM(E$49:E$51) -> 341.61486
B53: Sub-total (KShs/Litre) | D53: =D$52/(D$40*1000) -> 0.26650078 | E53: =E$52/(E$40*1000) -> 0.26818189
B54: Storage and vessel handling (KShs/litre) | D54: =D$55+D$56 -> 0.46463346 | E54: =E$55+E$56 -> 0.48140791
B55: Kipevu/SOT shore handling charges | D55: =D$27/D38 -> 0.025441025 | E55: =E$27/E38 -> 0.026359511
B56: KPRL hospitality Charges | D56: =D$28/D38 -> 0.43919244 | E56: =E$28/E38 -> 0.45504839
B58: Non-VAT charged costs (KShs/litre) | D58: =SUM(D$59,D$60,D$66) -> 105.64225 | E58: =SUM(E$59,E$60,E$66) -> 100.35925
B59: USD based costs | D59: =D$25 -> 104.13479 | E59: =E$25 -> 98.954136
B60: KShs based Costs I | D60: =SUM(D$61:D$65)/(D$40*1000) -> 1.5074662 | E60: =SUM(E$61:E$65)/(E$40*1000) -> 1.4051135
B61: Insurance | D61: =D$13 -> 329.77971 | E61: =E$13 -> 303.88187
B62: War Risk | D62: =D$14 -> 36.384596 | E62: =E$14 -> 33.527287
B63: Stevedoring Charges | D63: =D$16 -> 222.1725 | E63: =E$16 -> 223.41
B64: Ocean Losses | D64: =D$17 -> 672.13396 | E64: =E$17 -> 619.58871
B65: Adminstration Fees | D65: =D$18 -> 661.39025 | E65: =E$18 -> 609.45079
B66: KShs based Costs II | D66: =SUM(D$67:D$68) -> 0 | E66: =SUM(E$67:E$68) -> 0
B67: KOSF Charges Recovery | D67: =D$30 -> 0 | E67: =E$30 -> 0
B68: Direct order charges | D68: =D$29 -> 0 | E68: =E$29 -> 0
B70: Merchant Shipping Fees | D70: =D$21/(D$40*1000) -> 0.001416638 | E70: =E$21/(E$40*1000) -> 0.0014889685
B71: Import Declaration Fees (IDF) | D71: =D$31 -> 3.6112377 | E71: =E$31 -> 3.4315825

Sheet VAT Breakdown for PMS_AGO_DPK
B2: Breakdown of the costs of Super Petrol (PMS), Diesel (AGO) and Kerosene (DPK) in Nairobi: 15th March - 14th April 2023
B3: Cost Item | C3: Cost Description | D3: Super Petrol | E3: Diesel | F3: Kerosene
D4: KShs/Litre | E4: KShs/Litre | F4: KShs/Litre
B5: Landed Cost (a) | C5: Weighted Average cost for all imports | D5: ='Nairobi_Price VAT Inclusive'!C6 -> 90.386689 | E5: ='Nairobi_Price VAT Inclusive'!E6 -> 103.01178 | F5: ='Nairobi_Price VAT Inclusive'!G6 -> 105.4031
B7: Pipeline Transport (Msa-Nrb) | C7: Pipeline (100% PMS, AGO & IK) | D7: ='Nairobi_Price VAT Inclusive'!C24 -> 2.5266 | E7: ='Nairobi_Price VAT Inclusive'!E24 -> 2.5266 | F7: ='Nairobi_Price VAT Inclusive'!G24 -> 2.5266
B8: Road Transport (Msa-Nrb) - Bridging | C8: Road (0% PMS, AGO & IK) | D8: 0 | E8: 0 | F8: 0
B9: Pipeline Losses | C9: Pipeline (0.25%) | D9: ='Nairobi_Price VAT Inclusive'!C26 -> 0.065748689 | E9: ='Nairobi_Price VAT Inclusive'!E26 -> 0.067033093 | F9: ='Nairobi_Price VAT Inclusive'!G26 -> 0.065837941
B10: Depot Losses | C10: 0.5% PMS; 0.3% For DPK & AGO | D10: ='Nairobi_Price VAT Inclusive'!C27 -> 0.70445024 | E10: ='Nairobi_Price VAT Inclusive'!E27 -> 0.43092702 | F10: ='Nairobi_Price VAT Inclusive'!G27 -> 0.42324391
B11: Delivery within 40kms of Nrb | C11: Delivery to retail stations | D11: ='Nairobi_Price VAT Inclusive'!C41 -> 0.53759193 | E11: ='Nairobi_Price VAT Inclusive'!E41 -> 0.53759193 | F11: ='Nairobi_Price VAT Inclusive'!G41 -> 0.53759193
B12: Storage and distribution (b) | D12: =SUM(D7:D11) -> 3.8343909 | E12: =SUM(E7:E11) -> 3.562152 | F12: =SUM(F7:F11) -> 3.5532738
B14: Importers Margin | C14: Wholesale | D14: ='Nairobi_Price VAT Inclusive'!C28 -> 4.204 | E14: ='Nairobi_Price VAT Inclusive'!E28 -> 4.174 | F14: ='Nairobi_Price VAT Inclusive'!G28 -> 4.174
B15: Dealers Margin | C15: Retail Investment &Operating Margin | D15: ='Nairobi_Price VAT Inclusive'!C42 -> 8.19 | E15: ='Nairobi_Price VAT Inclusive'!E42 -> 8.19 | F15: ='Nairobi_Price VAT Inclusive'!G42 -> 8.19
B17: Oil marketing companies margins (c ) | D17: =SUM(D14:D16) -> 12.394 | E17: =SUM(E14:E16) -> 12.364 | F17: =SUM(F14:F16) -> 12.364
B20: Excise Duty | C20: Tax | D20: 21.95302 | E20: 11.37099 | F20: 11.37098
B21: Road Maintenance Levy | C21: Levy | D21: 18 | E21: 18 | F21: 0
B22: Petroleum Development Levy | C22: Levy | D22: 5.4 | E22: 5.4 | F22: 0.4
B23: Petroleum Regulatory Levy | C23: Levy | D23: 0.25 | E23: 0.25 | F23: 0.25
B24: Railway Development Levy | C24: Levy | D24: ='PMS Import'!V10 -> 1.7335008 | E24: ='AGO Import'!V10 -> 1.9943291 | F24: ='DPK Import'!R12 -> 2.0134756
B25: Anti-adulteration Levy | C25: Levy | D25: 0 | E25: 0 | F25: 18
B26: Merchant Shipping Levy | C26: Levy | D26: ='PMS SUMMARY'!D46 -> 0.029475332 | E26: ='AGO SUMMARY'!E48 -> 0.033048548 | F26: ='DPK SUMMARY'!D45 -> 0.0014519287
B27: Import Declaration Fee | C27: Levy | D27: ='PMS SUMMARY'!D47 -> 3.0336263 | E27: ='AGO SUMMARY'!E49 -> 3.490076 | F27: ='DPK SUMMARY'!D46 -> 3.5235822 | G27: Actual last month(February-March 2023) | H27: 165.78712 | I27: 172.61363 | J27: 165.3549
B28: Value Added Tax (VAT) | C28: Tax | D28: 12.56 | E28: 12.76 | F28: 12.55
B29: Taxes and levies (d) | D29: =SUM(D20:D28) -> 62.959622 | E29: =SUM(E20:E28) -> 53.298444 | F29: =SUM(F20:F28) -> 48.10949
B30: Retail Prices in Nairobi (a) + (b) + (c ) + (d) | D30: =SUM(D5,D12,D17,D29) -> 169.5747 | E30: =SUM(E5,E12,E17,E29) -> 172.23638 | F30: =SUM(F5,F12,F17,F29) -> 169.42987 | H30: ='Nairobi_Price VAT Inclusive'!C49 -> 169.5747 | I30: ='Nairobi_Price VAT Inclusive'!E49 -> 172.23638 | J30: ='Nairobi_Price VAT Inclusive'!G49 -> 169.42987
D31: ='Nairobi_Price VAT Inclusive'!C48 -> + 12.56 | E31: ='Nairobi_Price VAT Inclusive'!E48 -> + 12.76 | F31: ='Nairobi_Price VAT Inclusive'!G48 -> + 12.55 | G31: Change from actual prices | H31: =H30-H27 -> 3.7875866 | I31: =I30-I27 -> -0.37725138 | J31: =J30-J27 -> 4.074965
B32: Summary | D32: Super Petrol | E32: Diesel | F32: Kerosene | G32: Published Prices (February-March 2023) | H32: =177.3 -> 177.3 | I32: 162 | J32: 145.94
D33: KShs/Litre | E33: KShs/Litre | F33: KShs/Litre | G33: Proposed Published Prices (March-April 2023) | H33: =177.3+2 -> 179.3 | I33: 162 | J33: 145.94
B34: Products Costs (a) | D34: =D5 -> 90.386689 | E34: =E5 -> 103.01178 | F34: =F5 -> 105.4031 | G34: Change from published prices | H34: =H30-H33 -> -9.725298 | I34: =I30-I33 -> 10.236378 | J34: =J30-J33 -> 23.489867
B35: Distribution and storage Costs (b) | D35: =D12 -> 3.8343909 | E35: =E12 -> 3.562152 | F35: =F12 -> 3.5532738
B36: Margins (c ) | D36: =D17 -> 12.394 | E36: =E17 -> 12.364 | F36: =F17 -> 12.364 | G36: Stabilization Delta | H36: =H30-H33 -> -9.725298 | I36: =I30-I33 -> 10.236378 | J36: =J30-J33 -> 23.489867
B37: Taxes & Levies (d) | D37: =D29 -> 62.959622 | E37: =E29 -> 53.298444 | F37: =F29 -> 48.10949
B38: Retail Prices in Nairobi | D38: =SUM(D34:D37) -> 169.5747 | E38: =SUM(E34:E37) -> 172.23638 | F38: =SUM(F34:F37) -> 169.42987
H39: =H36/1.08 -> -9.0049055 | I39: =I30-12.36 -> 159.87638 | J39: =12.36-J36 -> -11.129867
D40: =D30/1.08*0.08 -> 12.561089 | E40: =E30/1.08*0.08 -> 12.75825 | F40: =F30/1.08*0.08 -> 12.55036
I41: =I33-I39 -> 2.1236224 | J41: =J39/1.08 -> -10.305432
I43: =I41/1.08 -> 1.9663171

Sheet VAT Breakdown for PUBLICATION
B2: Breakdown of the costs of Super Petrol (PMS), Diesel (AGO) and Kerosene (DPK) in Nairobi: 15th April - 14th May 2020
B3: Cost Item | C3: Cost Description | D3: Super Petrol | E3: Diesel | F3: Kerosene
D4: KShs/Litre | E4: KShs/Litre | F4: KShs/Litre
B5: Landed Cost (a) | C5: Weighted Average cost for all imports | D5: 32.22 | E5: 45.41 | F5: 27.56
B7: Pipeline Transport (Msa-Nrb) | C7: Pipeline (100% PMS, AGO & IK) | D7: 2.28 | E7: 2.28 | F7: 2.28
B8: Road Transport (Msa-Nrb) - Bridging | C8: Road (0% PMS, AGO & IK) | D8: 0 | E8: 0 | F8: 0
B9: Pipeline Losses | C9: Pipeline (0.25%) | D9: 0 | E9: 0 | F9: 0
B10: Depot Losses | C10: 0.5% PMS; 0.3% For DPK & AGO | D10: 0.37 | E10: 0.23 | F10: 0.18
B11: Delivery within 40kms of Nrb | C11: Delivery to petrol stations | D11: 0.54 | E11: 0.54 | F11: 0.54
B12: Storage and distribution (b) | D12: =SUM(D7:D11) -> 3.19 | E12: =SUM(E7:E11) -> 3.05 | F12: =SUM(F7:F11) -> 3
B14: Importers Margin | C14: Wholesale | D14: 4.2 | E14: 4.17 | F14: 4.17
B15: Dealers Margin | C15: Retail Investment Margin | D15: 4.05 | E15: 4.05 | F15: 4.05
C16: Retail Operating Margin | D16: 4.14 | E16: 4.14 | F16: 4.14
B17: Oil marketing companies margins (c ) | D17: =SUM(D14:D16) -> 12.39 | E17: =SUM(E14:E16) -> 12.36 | F17: =SUM(F14:F16) -> 12.36
B20: Excise Duty | C20: Tax | D20: 20.92 | E20: 10.84 | F20: 10.84 | L20: =ROUND(K20,2) -> 0
B21: Road Maintenance Levy | C21: Levy | D21: 18 | E21: 18 | F21: 0 | L21: =ROUND(K21,2) -> 0
B22: Petroleum Development Levy | C22: Levy | D22: 0.4 | E22: 0.4 | F22: 0.4 | L22: =ROUND(K22,2) -> 0
B23: Petroleum Regulatory Levy | C23: Levy | D23: 0.25 | E23: 0.25 | F23: 0.25 | L23: =ROUND(K23,2) -> 0
B24: Railway Development Levy | C24: Levy | D24: 0.62 | E24: 0.86 | F24: 0.52 | L24: =ROUND(K24,2) -> 0
B25: Anti-adulteration Levy | C25: Levy | D25: 0 | E25: 0 | F25: 18 | L25: =ROUND(K25,2) -> 0
B26: Merchant Shipping Levy | C26: Levy | D26: 0.02 | E26: 0.03 | F26: 0.02 | L26: 0.03
B27: Import Declaration Fee | C27: Levy | D27: 1.07 | E27: 1.51 | F27: 0.91
B28: Value Added Tax (VAT) | C28: Tax | D28: 3.79 | E28: 4.85 | F28: 3.42 | L28: =ROUND(K28,2) -> 0
B29: Taxes and levies (d) | D29: =SUM(D20:D28) -> 45.07 | E29: =SUM(E20:E28) -> 36.74 | F29: =SUM(F20:F28) -> 34.36 | L29: =SUM(L20:L28) -> 0.03
B30: Retail Prices in Nairobi (a) + (b) + (c ) + (d) | D30: =SUM(D5,D12,D17,D29) -> 92.87 | E30: =SUM(E5,E12,E17,E29) -> 97.56 | F30: =SUM(F5,F12,F17,F29) -> 77.28
B32: Summary | D32: Super Petrol | E32: Diesel | F32: Kerosene
D33: KShs/Litre | E33: KShs/Litre | F33: KShs/Litre
B34: Products Costs (a) | D34: =D5 -> 32.22 | E34: =E5 -> 45.41 | F34: =F5 -> 27.56
B35: Distribution and storage Costs (b) | D35: =D12 -> 3.19 | E35: =E12 -> 3.05 | F35: =F12 -> 3
B36: Margins (c ) | D36: =D17 -> 12.39 | E36: =E17 -> 12.36 | F36: =F17 -> 12.36
B37: Taxes & Levies (d) | D37: =D29 -> 45.07 | E37: =E29 -> 36.74 | F37: =F29 -> 34.36
B38: Retail Prices in Nairobi | D38: =SUM(D34:D37) -> 92.87 | E38: =SUM(E34:E37) -> 97.56 | F38: =SUM(F34:F37) -> 77.28
D41: =D34-D42 -> 31.22 | E41: =E34-E42 -> 45.05 | F41: =F34-F42 -> 25.96
D42: =ROUND('PMS SUMMARY'!J36,2) -> 1 | E42: =ROUND('AGO SUMMARY'!K37,2) -> 0.36 | F42: =ROUND('DPK SUMMARY'!F35,2) -> 1.6

Sheet Breakdown for PMS, AGO & DPK
B2: Breakdown of the costs of Super Petrol (PMS), Diesel (AGO) and Kerosene (DPK) in Nairobi: 15th Oct - 14th Nov 2020
B3: Cost Item | C3: Cost Description | D3: Super Petrol | E3: Diesel | F3: Kerosene
D4: KShs/Litre | E4: KShs/Litre | F4: KShs/Litre
B5: Landed Cost (a) | C5: Weighted Average cost for all imports | D5: ='PMS SUMMARY'!J37 -> 93.553125 | E5: ='AGO SUMMARY'!K38 -> 106.62671 | F5: ='DPK SUMMARY'!F36 -> 109.04656
B7: Pipeline Transport (Msa-Nrb) | C7: Pipeline (100% PMS, AGO & IK) | D7: =Nairobi!D9 -> 2.930856 | E7: =Nairobi!E9 -> 2.930856 | F7: =Nairobi!F9 -> 2.930856
B8: Road Transport (Msa-Nrb) - Bridging | C8: Road (0% PMS, AGO & IK) | D8: 0 | E8: 0 | F8: 0
B9: Pipeline Losses | C9: Pipeline (0.25%) | D9: =Nairobi!D13 -> 0.065748689 | E9: =Nairobi!E13 -> 0.067033093 | F9: =Nairobi!F13 -> 0.065837941
B10: Depot Losses | C10: 0.5% PMS; 0.3% For DPK & AGO | D10: =Nairobi!D15 -> 0.70445024 | E10: =Nairobi!E15 -> 0.43092702 | F10: =Nairobi!F15 -> 0.42324391
B11: Delivery within 40kms of Nrb | C11: Delivery to petrol stations | D11: =Nairobi!D23 -> 0.62360664 | E11: =Nairobi!E23 -> 0.62360664 | F11: =Nairobi!F23 -> 0.62360664
B12: Storage and distribution (b) | D12: =SUM(D7:D11) -> 4.3246616 | E12: =SUM(E7:E11) -> 4.0524228 | F12: =SUM(F7:F11) -> 4.0435445
B14: Importers Margin | C14: Wholesale | D14: =Nairobi!D17 -> 4.204 | E14: =Nairobi!E17 -> 4.174 | F14: =Nairobi!F17 -> 4.174
B15: Dealers Margin | C15: Retail | D15: =Nairobi!D21 -> 8.19 | E15: =Nairobi!E21 -> 8.19 | F15: =Nairobi!F21 -> 8.19
B16: Oil marketing companies margins (c ) | D16: =SUM(D14:D15) -> 12.394 | E16: =SUM(E14:E15) -> 12.364 | F16: =SUM(F14:F15) -> 12.364
B19: Excise Duty | C19: Tax | D19: 21.95302 | E19: 11.37099 | F19: 11.37098
B20: Road Maintenance Levy | C20: Levy | D20: 18 | E20: 18 | F20: 0
B21: Petroleum Development Levy | C21: Levy | D21: 5.4 | E21: 5.4 | F21: 0.4
B22: Petroleum Regulatory Levy | C22: Levy | D22: 0.25 | E22: 0.25 | F22: 0.25
B23: Railway Development Levy | C23: Levy | D23: ='PMS Import'!V10 -> 1.7335008 | E23: ='AGO Import'!V10 -> 1.9943291 | F23: ='DPK Import'!R12 -> 2.0134756
B24: Anti-adulteration Levy | C24: Levy | D24: 0 | E24: 0 | F24: 18 | H24: =H26-D26 -> 0.0004017929 | I24: =I26-E26 -> 0.00031339361
B25: Taxes and levies (d) | D25: =SUM(D19:D24) -> 47.336521 | E25: =SUM(E19:E24) -> 37.015319 | F25: =SUM(F19:F24) -> 32.034456
B26: Retail Prices in Nairobi (a) + (b) + (c ) + (d) | D26: =SUM(D5,D12,D16,D25) -> 157.60831 | E26: =SUM(E5,E12,E16,E25) -> 160.05845 | F26: =SUM(F5,F12,F16,F25) -> 157.48856 | H26: =Nairobi!D25 -> 157.60871 | I26: =Nairobi!E25 -> 160.05876 | J26: =Nairobi!F25 -> 157.48885
B28: Summary | D28: Super Petrol | E28: Diesel | F28: Kerosene
D29: KShs/Litre | E29: KShs/Litre | F29: KShs/Litre
B30: Products Costs (a) | D30: =D5 -> 93.553125 | E30: =E5 -> 106.62671 | F30: =F5 -> 109.04656
B31: Distribution and storage Costs (b) | D31: =D12 -> 4.3246616 | E31: =E12 -> 4.0524228 | F31: =F12 -> 4.0435445
B32: Margins (c ) | D32: =D16 -> 12.394 | E32: =E16 -> 12.364 | F32: =F16 -> 12.364
B33: Taxes & Levies (d) | D33: =D25 -> 47.336521 | E33: =E25 -> 37.015319 | F33: =F25 -> 32.034456
B34: Retail Prices in Nairobi | D34: =SUM(D30:D33) -> 157.60831 | E34: =SUM(E30:E33) -> 160.05845 | F34: =SUM(F30:F33) -> 157.48856

Sheet Mombasa
C2: MOMBASA CITY
C3: Petroleum Costing
C4: March 15 - April 14, 2023
D6: PMS | E6: AGO | F6: DPK
C7: Kshs/lt | D7: ='WEIGHTED AVERAGE COST'!L40 -> 140.89005 | E7: ='WEIGHTED AVERAGE COST'!L76 -> 143.64234 | F7: ='WEIGHTED AVERAGE COST'!L104 -> 141.0813 | H7: Weighted average cost (KPRL + KOSF)
G8: 1.16 | H8: 16% VAT Inclusive
C9: Kshs/lt | D9: =$G$10*$G$9*$G$8 -> 0 | E9: =$G$10*$G$9*$G$8 -> 0 | F9: =$G$10*$G$9*$G$8 -> 0 | G9: 0 | H9: % transported through pipeline - Zero for Mombasa
G10: 0 | H10: Pipeline Rate
C11: Kshs/lt | D11: =$G$11*G12*$G$8 -> 0 | E11: =$G$11*G12*$G$8 -> 0 | F11: =$G$11*G12*$G$8 -> 0 | G11: =8.14*G14/1000 -> 0 | H11: Bridging Rate Kshs 0.00912 per litre x distance
G12: =1-G9 -> 1 | H12: % transported through road
C13: Kshs/lt | D13: =$G$13*D7 -> 0 | E13: =$G$13*E7 -> 0 | F13: =$G$13*F7 -> 0 | G13: 0 | H13: Allowed pipeline losses
G14: 0 | H14: Distance from Source Depot
C15: Kshs/lt | D15: =G15*D7 -> 0.70445024 | E15: =G16*E7 -> 0.43092702 | F15: =G16*F7 -> 0.42324391 | G15: 0.005 | H15: Allowed depot losses. 0.5% for PMS,RMS and 0.3% for AGO,DPK
G16: 0.003
C18: Kshs/lt | D18: =3.05+0.49+0.664 -> 4.204 | E18: =3.05+0.46+0.664 -> 4.174 | F18: =3.05+0.46+0.664 -> 4.174 | H18: Allowed oil marketing company's gross wholesale margin
C20: Kshs/lt | D20: =SUM(D7:D19) -> 145.7985 | E20: =SUM(E7:E19) -> 148.24727 | F20: =SUM(F7:F19) -> 145.67855 | H20: Maximum Wholesale price
C22: Kshs/lt | D22: =4.14+4.05 -> 8.19 | E22: =4.14+4.05 -> 8.19 | F22: =4.14+4.05 -> 8.19 | H22: Allowed retail dealers gross margin
C24: Kshs/lt | D24: =$G$24*G8 -> 0.62360664 | E24: =$G$24*G8 -> 0.62360664 | F24: =$G$24*G8 -> 0.62360664 | G24: ='Delivery =<40km-Sept 2013'!E24 -> 0.53759193 | H24: 40km radius-Delivery rate within town
C26: Kshs/lt | D26: =D20+D22+D24 -> 154.6121 | E26: =E20+E22+E24 -> 157.06087 | F26: =F20+F22+F24 -> 154.49215 | H26: Maximum retail pump price
B28: February 15 - March 14 2023 | C28: =C26 -> Kshs/lt | D28: 151.11143 | E28: 157.40392 | F28: 150.71042
B29: Change | C29: =C28 -> Kshs/lt | D29: =D26-D28 -> 3.5006772 | E29: =E26-E28 -> -0.34304023 | F29: =F26-F28 -> 3.7817338
B31: Change | C31: % | D31: =D29/D28*100 -> 2.3166198 | E31: =E29/E28*100 -> -0.21793628 | F31: =F29/F28*100 -> 2.5092716

Sheet MOMBASA_PRICE VAT Inclusive
B3: OMC WHOLE-SALE FUEL PRICE BREAK-DOWN INCLUDING VAT
B4: =Mombasa!C4 -> March 15 - April 14, 2023 | C4: Super petrol | E4: Diesel | G4: Kerosene
B5: Item | C5: COST/ PRICE | D5: (INPUT)/ OUTPUT | E5: COST/ PRICE | F5: (INPUT)/ OUTPUT | G5: COST/ PRICE | H5: (INPUT)/ OUTPUT
B6: Landed cost, exclusive of VAT (KShs/Litre) [a+b+c] | C6: =C$7+C$8 -> 90.386689 | E6: =E$7+E$8 -> 103.01178 | G6: =G$7+G$8 -> 105.4031
B7: (a) None VAT-charged costs (KShs/litre) | C7: ='PMS SUMMARY'!D45 -> 89.740845 | E7: ='AGO SUMMARY'!E47 -> 102.43802 | G7: ='DPK SUMMARY'!D44 -> 104.66296
B8: (b) VAT-charged costs (KShs/litre) | C8: ='PMS SUMMARY'!D44 -> 0.6458438 | E8: ='AGO SUMMARY'!E46 -> 0.5737644 | G8: ='DPK SUMMARY'!D43 -> 0.74013888
A9: I. | B9: VATable amount (KShs/Litre) | C9: =C$6 -> 90.386689 | E9: =E$6 -> 103.01178 | G9: =G$6 -> 105.4031
B10: INPUT VAT 2 (on I.) | D10: =-(C9*0.08) -> -7.2309351 | F10: =-(E9*0.08) -> -8.2409425 | H10: =-(G9*0.08) -> -8.4322483
A11: II. | B11: Levies
B12: Excise duty | C12: ='Breakdown for PMS, AGO & DPK'!D19 -> 21.95302 | E12: ='Breakdown for PMS, AGO & DPK'!E19 -> 11.37099 | G12: ='Breakdown for PMS, AGO & DPK'!F19 -> 11.37098
B13: Merchant Shipping Fee | C13: ='PMS SUMMARY'!D46 -> 0.029475332 | E13: ='AGO SUMMARY'!E48 -> 0.033048548 | G13: ='DPK SUMMARY'!D45 -> 0.0014519287
B14: Import Declaration Fee | C14: ='PMS SUMMARY'!D47 -> 3.0336263 | E14: ='AGO SUMMARY'!E49 -> 3.490076 | G14: ='DPK SUMMARY'!D46 -> 3.5235822
B15: Road Maintenance Levy | C15: ='Breakdown for PMS, AGO & DPK'!D20 -> 18 | E15: ='Breakdown for PMS, AGO & DPK'!E20 -> 18 | G15: 0
B16: Anti-adulteration Levy | C16: 0 | E16: 0 | G16: ='Breakdown for PMS, AGO & DPK'!F24 -> 18
B17: Petroleum Development Levy | C17: ='Breakdown for PMS, AGO & DPK'!D21 -> 5.4 | E17: ='Breakdown for PMS, AGO & DPK'!E21 -> 5.4 | G17: ='Breakdown for PMS, AGO & DPK'!F21 -> 0.4
B18: Petroleum Regulatory Levy | C18: ='Breakdown for PMS, AGO & DPK'!D22 -> 0.25 | E18: ='Breakdown for PMS, AGO & DPK'!E22 -> 0.25 | G18: ='Breakdown for PMS, AGO & DPK'!F22 -> 0.25
B19: Railway Development Levy | C19: ='Breakdown for PMS, AGO & DPK'!D23 -> 1.7335008 | E19: ='Breakdown for PMS, AGO & DPK'!E23 -> 1.9943291 | G19: ='Breakdown for PMS, AGO & DPK'!F23 -> 2.0134756
B20: Sub-total | C20: =SUM(C12:C19) -> 50.399622 | E20: =SUM(E12:E19) -> 40.538444 | G20: =SUM(G12:G19) -> 35.55949
A21: III. | B21: Storage and Distribution Costs (Variable/Litre) | C21: =SUM(C$22:C$23) -> 0.70445024 | E21: =SUM(E$22:E$23) -> 0.43092702 | G21: =SUM(G$22:G$23) -> 0.42324391
B22: Storage and Distribution Costs (with VAT) | C22: =SUM(C$24:C$25) -> 0 | E22: =SUM(E$24:E$25) -> 0 | G22: =SUM(G$24:G$25) -> 0
B23: Storage and Distribution Costs (without VAT) | C23: =C$26+C$27 -> 0.70445024 | E23: =E$26+E$27 -> 0.43092702 | G23: =G$26+G$27 -> 0.42324391
B24: Pipeline Transport (Msa) | C24: =Mombasa!D9 -> 0 | E24: =Mombasa!E9 -> 0 | G24: =Mombasa!F9 -> 0
B25: Road Transport (Msa) - Bridging | C25: =Mombasa!D11 -> 0 | E25: =Mombasa!E11 -> 0 | G25: =Mombasa!F11 -> 0
B26: Pipeline Losses | C26: =Mombasa!D13 -> 0 | E26: =Mombasa!E13 -> 0 | G26: =Mombasa!F13 -> 0
B27: Depot Losses | C27: =Mombasa!D15 -> 0.70445024 | E27: =Mombasa!E15 -> 0.43092702 | G27: =Mombasa!F15 -> 0.42324391
A28: IV. | B28: Oil Marketers Margin | C28: =Mombasa!D18 -> 4.204 | E28: =Mombasa!E18 -> 4.174 | G28: =Mombasa!F18 -> 4.174
B29: VATable price [(I)+(III)+(IV)] | C29: =C$9+C$20+C$22+C$23+C$28 -> 145.69476 | E29: =E$9+E$20+E$22+E$23+E$28 -> 148.15515 | G29: =G$9+G$20+G$22+G$23+G$28 -> 145.55984
B30: Output VAT | D30: =CONCATENATE("+ ",ROUND((C$29*0.08),2)) -> + 11.66 | F30: =CONCATENATE("+ ",ROUND((E$29*0.08),2)) -> + 11.85 | H30: =CONCATENATE("+ ",ROUND((G$29*0.08),2)) -> + 11.64
B31: OMC Wholesale price exclusive of VAT | C31: =C$9+C$20+C$21+C$28 -> 145.69476 | E31: =E$9+E$20+E$21+E$28 -> 148.15515 | G31: =G$9+G$20+G$21+G$28 -> 145.55984
B32: ADD: VAT at wholesale | C32: =D30 -> + 11.66 | E32: =F30 -> + 11.85 | G32: =H30 -> + 11.64
B33: Wholesale Price inxclusive of VAT | C33: =C31+C32 -> 157.35476 | D33: =+D10+D30 -> 4.4290649 | E33: =E31+E32 -> 160.00515 | F33: =F10+F30 -> 3.6090575 | G33: =G31+G32 -> 157.19984 | H33: =H10+H30 -> 3.2077517
B35: RETAIL FUEL COST BREAK-DOWN INCLUDING VAT
C36: =C4 -> Super petrol | E36: =E4 -> Diesel | G36: =G4 -> Kerosene
A37: V. | B37: Wholesale price inclusive of VAT | C37: =C33 -> 157.35476 | E37: =E33 -> 160.00515 | G37: =G33 -> 157.19984
B38: Input VAT on Product at retail | D38: =-C32 -> -11.66 | F38: =-E32 -> -11.85 | H38: =-G32 -> -11.64
A39: VI. | B39: Distribution Cost
B40: Delivery Within 40kms | C40: =Mombasa!G24 -> 0.53759193 | E40: =C40 -> 0.53759193 | G40: =E40 -> 0.53759193
B41: Subtotal | C41: =SUM(C40) -> 0.53759193 | E41: =SUM(E40) -> 0.53759193 | G41: =SUM(G40) -> 0.53759193
A42: VII. | B42: Retailer's Margin | C42: =Mombasa!D22 -> 8.19 | E42: =Mombasa!E22 -> 8.19 | G42: =Mombasa!F22 -> 8.19
B43: Retail price | C43: =C$37+C$42+C$41 -> 166.08235 | E43: =E$37+E$42+E$41 -> 168.73274 | G43: =G$37+G$42+G$41 -> 165.92743
B44: LESS: Levies | C44: 0 | E44: 0 | G44: 0
B45: Non-VATable storage and distribution costs | C45: 0 | E45: 0 | G45: 0
B46: VATable value [(V)+(VI)-Input VAT] | C46: =C$43-C44-C45+D$38 -> 154.42235 | E46: =E$43-E44-E45+F$38 -> 156.88274 | G46: =G$43-G44-G45+H$38 -> 154.28743
B47: Output VAT on product at retail level | D47: =CONCATENATE("+ ",ROUND((C$46*0.08),2)) -> + 12.35 | F47: =CONCATENATE("+ ",ROUND((E$46*0.08),2)) -> + 12.55 | H47: =CONCATENATE("+ ",ROUND((G$46*0.08),2)) -> + 12.34
B48: ADD: VAT at retail | C48: =D47 -> + 12.35 | E48: =F47 -> + 12.55 | G48: =H47 -> + 12.34
B49: Retail Pump-Price under VAT regime | C49: =C$46+C$48+C$44+C$45 -> 166.77235 | D49: =D38+D47 -> 0.69 | E49: =E$46+E$48+E$44+E$45 -> 169.43274 | F49: =F38+F47 -> 0.7 | G49: =G$46+G$48+G$44+G$45 -> 166.62743 | H49: =H38+H47 -> 0.7
A51: EXPECTED IMPACT ON THE FINAL RETAIL PRICE COMPARED TO THE NON-VAT REGIME
B53: ERC PRICE UNDER NON-VAT REGIME | C53: =Mombasa!D26 -> 154.6121 | D53: =C9+C20+C21+C28+C42+0.16*C8+0.16*SUM(C24:C25) -> 153.9881 | E53: ='Breakdown for PMS, AGO & DPK'!E26 -> 160.05845 | G53: ='Breakdown for PMS, AGO & DPK'!F26 -> 157.48856
B54: PRICE DIFFERENCE | C54: =C49-C53 -> 12.160248 | D54: =C53-D53 -> 0.62400843 | E54: =E49-E53 -> 9.3742939 | G54: =G49-G53 -> 9.1388691
B55: PERCENTAGE INCREAMENT | C55: =C54/C53 -> 0.078650042 | D55: =7-5.55+3.89-3.112 -> 2.228 | E55: =E54/E53 -> 0.058567941 | G55: =G54/G53 -> 0.058028781
B56: GOVERNMENT NET VAT COLLECTION (KSHS PER LITRE) | C56: =D$33+D$49+-$D$10 -> 12.35 | E56: =F$33+F$49 -> 4.3090575 | G56: =H$33+H$49 -> 3.9077517
C59: PMS | D59: AGO | E59: IK
B60: =B4 -> March 15 - April 14, 2023 | C60: =C49 -> 166.77235 | D60: =E49 -> 169.43274 | E60: =G49 -> 166.62743
B62: =Mombasa!B28 -> February 15 - March 14 2023 | C62: 162.98639 | D62: 169.80984 | E62: 162.55422
B64: Absolute Change | C64: =C60-C62 -> 3.7859611 | D64: =D60-D62 -> -0.37709177 | E64: =E60-E62 -> 4.0732054
B66: Percentage Change (%) | C66: =C64/C62*100 -> 2.3228694 | D66: =D64/D62*100 -> -0.22206709 | E66: =E64/E62*100 -> 2.5057518

Sheet Kilifi
C2: KILIFI TOWN
C3: Petroleum Costing
C4: =Mombasa!C4 -> March 15 - April 14, 2023
D6: PMS | E6: AGO | F6: DPK
C7: Kshs/lt | D7: ='WEIGHTED AVERAGE COST'!L40 -> 140.89005 | E7: ='WEIGHTED AVERAGE COST'!L76 -> 143.64234 | F7: ='WEIGHTED AVERAGE COST'!L104 -> 141.0813 | H7: Weighted average cost (KPRL + KOSF)
G8: =Mombasa!G8 -> 1.16 | H8: 16% VAT Inclusive
C9: Kshs/lt | D9: =$G$10*$G$9*$G$8 -> 0 | E9: =$G$10*$G$9*$G$8 -> 0 | F9: =$G$10*$G$9*$G$8 -> 0 | G9: 0 | H9: % transported through pipeline - Zero for Mombasa
G10: 0 | H10: Pipeline Rate
C11: Kshs/lt | D11: =$G$11*G12*$G$8 -> 0 | E11: =$G$11*G12*$G$8 -> 0 | F11: =$G$11*G12*$G$8 -> 0 | G11: =8.14*G14/1000 -> 0 | H11: Bridging Rate Kshs 0.0814 per litre x distance
G12: 0 | H12: % transported through road
C13: Kshs/lt | D13: =$G$13*D7 -> 0 | E13: =$G$13*E7 -> 0 | F13: =$G$13*F7 -> 0 | G13: 0 | H13: Allowed pipeline losses
G14: 0 | H14: Distance from Source Depot
C15: Kshs/lt | D15: =G15*D7 -> 0.70445024 | E15: =G16*E7 -> 0.43092702 | F15: =G16*F7 -> 0.42324391 | G15: 0.005 | H15: Allowed depot losses. 0.5% for PMS,RMS and 0.3% for AGO,DPK
G16: 0.003
C17: Kshs/lt | D17: =Mombasa!D18 -> 4.204 | E17: =Mombasa!E18 -> 4.174 | F17: =Mombasa!F18 -> 4.174 | H17: Allowed oil marketing company's gross wholesale margin
C19: Kshs/lt | D19: =SUM(D7:D18) -> 145.7985 | E19: =SUM(E7:E18) -> 148.24727 | F19: =SUM(F7:F18) -> 145.67855 | H19: Maximum Wholesale price
C21: Kshs/lt | D21: =Mombasa!D22 -> 8.19 | E21: =Mombasa!E22 -> 8.19 | F21: =Mombasa!F22 -> 8.19 | H21: Allowed retail dealers gross margin
C23: Kshs/lt | D23: =$G$23*G8 -> 1.389116 | E23: =$G$23*G8 -> 1.389116 | F23: =$G$23*G8 -> 1.389116 | G23: ='Delivery >40km-Sept 2013'!E24*I23/1000 -> 1.1975138 | H23: Road distance from Mombasa Depot | I23: 100
C25: Kshs/lt | D25: =D19+D21+D23 -> 155.37761 | E25: =E19+E21+E23 -> 157.82638 | F25: =F19+F21+F23 -> 155.25766 | H25: Maximum retail pump price

Sheet KILIFI_PRICE VAT Inclusive
B3: OMC WHOLE-SALE FUEL PRICE BREAK-DOWN INCLUDING VAT
B4: =Mombasa!C4 -> March 15 - April 14, 2023 | C4: Super petrol | E4: Diesel | G4: Kerosene
B5: Item | C5: COST/ PRICE | D5: (INPUT)/ OUTPUT | E5: COST/ PRICE | F5: (INPUT)/ OUTPUT | G5: COST/ PRICE | H5: (INPUT)/ OUTPUT
B6: Landed cost, exclusive of VAT (KShs/Litre) [a+b+c] | C6: =C$7+C$8 -> 90.386689 | E6: =E$7+E$8 -> 103.01178 | G6: =G$7+G$8 -> 105.4031
B7: (a) None VAT-charged costs (KShs/litre) | C7: ='PMS SUMMARY'!D45 -> 89.740845 | E7: ='AGO SUMMARY'!E47 -> 102.43802 | G7: ='DPK SUMMARY'!D44 -> 104.66296
B8: (b) VAT-charged costs (KShs/litre) | C8: ='PMS SUMMARY'!D44 -> 0.6458438 | E8: ='AGO SUMMARY'!E46 -> 0.5737644 | G8: ='DPK SUMMARY'!D43 -> 0.74013888
A9: I. | B9: VATable amount (KShs/Litre) | C9: =C$6 -> 90.386689 | E9: =E$6 -> 103.01178 | G9: =G$6 -> 105.4031
B10: INPUT VAT 2 (on I.) | D10: =-(C9*0.08) -> -7.2309351 | F10: =-(E9*0.08) -> -8.2409425 | H10: =-(G9*0.08) -> -8.4322483
A11: II. | B11: Levies
B12: Excise duty | C12: ='Breakdown for PMS, AGO & DPK'!D19 -> 21.95302 | E12: ='Breakdown for PMS, AGO & DPK'!E19 -> 11.37099 | G12: ='Breakdown for PMS, AGO & DPK'!F19 -> 11.37098
B13: Merchant Shipping Fee | C13: ='PMS SUMMARY'!D46 -> 0.029475332 | E13: ='AGO SUMMARY'!E48 -> 0.033048548 | G13: ='DPK SUMMARY'!D45 -> 0.0014519287
B14: Import Declaration Fee | C14: ='PMS SUMMARY'!D47 -> 3.0336263 | E14: ='AGO SUMMARY'!E49 -> 3.490076 | G14: ='DPK SUMMARY'!D46 -> 3.5235822
B15: Road Maintenance Levy | C15: ='Breakdown for PMS, AGO & DPK'!D20 -> 18 | E15: ='Breakdown for PMS, AGO & DPK'!E20 -> 18 | G15: 0
B16: Anti-adulteration Levy | C16: 0 | E16: 0 | G16: ='Breakdown for PMS, AGO & DPK'!F24 -> 18
B17: Petroleum Development Levy | C17: ='Breakdown for PMS, AGO & DPK'!D21 -> 5.4 | E17: ='Breakdown for PMS, AGO & DPK'!E21 -> 5.4 | G17: ='Breakdown for PMS, AGO & DPK'!F21 -> 0.4
B18: Petroleum Regulatory Levy | C18: ='Breakdown for PMS, AGO & DPK'!D22 -> 0.25 | E18: ='Breakdown for PMS, AGO & DPK'!E22 -> 0.25 | G18: ='Breakdown for PMS, AGO & DPK'!F22 -> 0.25
B19: Railway Development Levy | C19: ='Breakdown for PMS, AGO & DPK'!D23 -> 1.7335008 | E19: ='Breakdown for PMS, AGO & DPK'!E23 -> 1.9943291 | G19: ='Breakdown for PMS, AGO & DPK'!F23 -> 2.0134756
B20: Sub-total | C20: =SUM(C12:C19) -> 50.399622 | E20: =SUM(E12:E19) -> 40.538444 | G20: =SUM(G12:G19) -> 35.55949
A21: III. | B21: Storage and Distribution Costs (Variable/Litre) | C21: =SUM(C$22:C$23) -> 0.70445024 | E21: =SUM(E$22:E$23) -> 0.43092702 | G21: =SUM(G$22:G$23) -> 0.42324391
B22: Storage and Distribution Costs (with VAT) | C22: =SUM(C$24:C$25) -> 0 | E22: =SUM(E$24:E$25) -> 0 | G22: =SUM(G$24:G$25) -> 0
B23: Storage and Distribution Costs (without VAT) | C23: =C$26+C$27 -> 0.70445024 | E23: =E$26+E$27 -> 0.43092702 | G23: =G$26+G$27 -> 0.42324391
B24: Pipeline Transport (Msa) | C24: =Mombasa!D9 -> 0 | E24: =Mombasa!E9 -> 0 | G24: =Mombasa!F9 -> 0
B25: Road Transport (Msa) - Bridging | C25: =Mombasa!D11 -> 0 | E25: =Mombasa!E11 -> 0 | G25: =Mombasa!F11 -> 0
B26: Pipeline Losses | C26: =Mombasa!D13 -> 0 | E26: =Mombasa!E13 -> 0 | G26: =Mombasa!F13 -> 0
B27: Depot Losses | C27: =Mombasa!D15 -> 0.70445024 | E27: =Mombasa!E15 -> 0.43092702 | G27: =Mombasa!F15 -> 0.42324391
A28: IV. | B28: Oil Marketers Margin | C28: =Mombasa!D18 -> 4.204 | E28: =Mombasa!E18 -> 4.174 | G28: =Mombasa!F18 -> 4.174
B29: VATable price [(I)+(III)+(IV)] | C29: =C$9+C$20+C$22+C$23+C$28 -> 145.69476 | E29: =E$9+E$20+E$22+E$23+E$28 -> 148.15515 | G29: =G$9+G$20+G$22+G$23+G$28 -> 145.55984
B30: Output VAT | D30: =CONCATENATE("+ ",ROUND((C$29*0.08),2)) -> + 11.66 | F30: =CONCATENATE("+ ",ROUND((E$29*0.08),2)) -> + 11.85 | H30: =CONCATENATE("+ ",ROUND((G$29*0.08),2)) -> + 11.64
B31: OMC Wholesale price exclusive of VAT | C31: =C$9+C$20+C$21+C$28 -> 145.69476 | E31: =E$9+E$20+E$21+E$28 -> 148.15515 | G31: =G$9+G$20+G$21+G$28 -> 145.55984
B32: ADD: VAT at wholesale | C32: =D30 -> + 11.66 | E32: =F30 -> + 11.85 | G32: =H30 -> + 11.64
B33: Wholesale Price inxclusive of VAT | C33: =C31+C32 -> 157.35476 | D33: =+D10+D30 -> 4.4290649 | E33: =E31+E32 -> 160.00515 | F33: =F10+F30 -> 3.6090575 | G33: =G31+G32 -> 157.19984 | H33: =H10+H30 -> 3.2077517
B35: RETAIL FUEL COST BREAK-DOWN INCLUDING VAT
C36: =C4 -> Super petrol | E36: =E4 -> Diesel | G36: =G4 -> Kerosene
A37: V. | B37: Wholesale price inclusive of VAT | C37: =C33 -> 157.35476 | E37: =E33 -> 160.00515 | G37: =G33 -> 157.19984
B38: Input VAT on Product at retail | D38: =-C32 -> -11.66 | F38: =-E32 -> -11.85 | H38: =-G32 -> -11.64
A39: VI. | B39: Distribution Cost
B40: Delivery Within 40kms | C40: =Kilifi!G23 -> 1.1975138 | E40: =C40 -> 1.1975138 | G40: =E40 -> 1.1975138
B41: Subtotal | C41: =SUM(C40) -> 1.1975138 | E41: =SUM(E40) -> 1.1975138 | G41: =SUM(G40) -> 1.1975138
A42: VII. | B42: Retailer's Margin | C42: =Mombasa!D22 -> 8.19 | E42: =Mombasa!E22 -> 8.19 | G42: =Mombasa!F22 -> 8.19
B43: Retail price | C43: =C$37+C$42+C$41 -> 166.74228 | E43: =E$37+E$42+E$41 -> 169.39267 | G43: =G$37+G$42+G$41 -> 166.58735
B44: LESS: Levies | C44: 0 | E44: 0 | G44: 0
B45: Non-VATable storage and distribution costs | C45: 0 | E45: 0 | G45: 0
B46: VATable value [(V)+(VI)-Input VAT] | C46: =C$43-C44-C45+D$38 -> 155.08228 | E46: =E$43-E44-E45+F$38 -> 157.54267 | G46: =G$43-G44-G45+H$38 -> 154.94735
B47: Output VAT on product at retail level | D47: =CONCATENATE("+ ",ROUND((C$46*0.08),2)) -> + 12.41 | F47: =CONCATENATE("+ ",ROUND((E$46*0.08),2)) -> + 12.6 | H47: =CONCATENATE("+ ",ROUND((G$46*0.08),2)) -> + 12.4
B48: ADD: VAT at retail | C48: =D47 -> + 12.41 | E48: =F47 -> + 12.6 | G48: =H47 -> + 12.4
B49: Retail Pump-Price under VAT regime | C49: =C$46+C$48+C$44+C$45 -> 167.49228 | D49: =D38+D47 -> 0.75 | E49: =E$46+E$48+E$44+E$45 -> 170.14267 | F49: =F38+F47 -> 0.75 | G49: =G$46+G$48+G$44+G$45 -> 167.34735 | H49: =H38+H47 -> 0.76
A51: EXPECTED IMPACT ON THE FINAL RETAIL PRICE COMPARED TO THE NON-VAT REGIME
B53: ERC PRICE UNDER NON-VAT REGIME | C53: =Mombasa!D26 -> 154.6121 | D53: =C9+C20+C21+C28+C42+0.16*C8+0.16*SUM(C24:C25) -> 153.9881 | E53: ='Breakdown for PMS, AGO & DPK'!E26 -> 160.05845 | G53: ='Breakdown for PMS, AGO & DPK'!F26 -> 157.48856
B54: PRICE DIFFERENCE | C54: =C49-C53 -> 12.88017 | D54: =C53-D53 -> 0.62400843 | E54: =E49-E53 -> 10.084216 | G54: =G49-G53 -> 9.858791
B55: PERCENTAGE INCREAMENT | C55: =C54/C53 -> 0.083306351 | D55: =7-5.55+3.89-3.112 -> 2.228 | E55: =E54/E53 -> 0.063003332 | G55: =G54/G53 -> 0.062600045
B56: GOVERNMENT NET VAT COLLECTION (KSHS PER LITRE) | C56: =D$33+D$49+-$D$10 -> 12.41 | E56: =F$33+F$49 -> 4.3590575 | G56: =H$33+H$49 -> 3.9677517

Sheet Likoni Mainland
C2: LIKONI MAINLAND
C3: Petroleum Costing
C4: =Kilifi!C4 -> March 15 - April 14, 2023
D6: PMS | E6: AGO | F6: DPK
C7: Kshs/lt | D7: ='WEIGHTED AVERAGE COST'!L40 -> 140.89005 | E7: ='WEIGHTED AVERAGE COST'!L76 -> 143.64234 | F7: ='WEIGHTED AVERAGE COST'!L104 -> 141.0813 | H7: Weighted average cost (KPRL + KOSF)
G8: =Mombasa!G8 -> 1.16 | H8: 16% VAT Inclusive
C9: Kshs/lt | D9: =$G$10*$G$9*$G$8 -> 0 | E9: =$G$10*$G$9*$G$8 -> 0 | F9: =$G$10*$G$9*$G$8 -> 0 | G9: 0 | H9: % transported through pipeline - Zero for Mombasa
G10: 0 | H10: Pipeline Rate
C11: Kshs/lt | D11: =$G$11*G12*$G$8 -> 0 | E11: =$G$11*G12*$G$8 -> 0 | F11: =$G$11*G12*$G$8 -> 0 | G11: =8.14*G14/1000 -> 0 | H11: Bridging Rate Kshs 0.0814 per litre x distance
G12: 0 | H12: % transported through road
C13: Kshs/lt | D13: =$G$13*D7 -> 0 | E13: =$G$13*E7 -> 0 | F13: =$G$13*F7 -> 0 | G13: 0 | H13: Allowed pipeline losses
G14: 0 | H14: Distance from Source Depot
C15: Kshs/lt | D15: =G15*D7 -> 0.70445024 | E15: =G16*E7 -> 0.43092702 | F15: =G16*F7 -> 0.42324391 | G15: 0.005 | H15: Allowed depot losses. 0.5% for PMS,RMS and 0.3% for AGO,DPK
G16: 0.003
C17: Kshs/lt | D17: =Mombasa!D18 -> 4.204 | E17: =Mombasa!E18 -> 4.174 | F17: =Mombasa!F18 -> 4.174 | H17: Allowed oil marketing company's gross wholesale margin
C19: Kshs/lt | D19: =SUM(D7:D18) -> 145.7985 | E19: =SUM(E7:E18) -> 148.24727 | F19: =SUM(F7:F18) -> 145.67855 | H19: Maximum Wholesale price
C21: Kshs/lt | D21: =Mombasa!D22 -> 8.19 | E21: =Mombasa!E22 -> 8.19 | F21: =Mombasa!F22 -> 8.19 | H21: Allowed retail dealers gross margin
C23: Kshs/lt | D23: =$G$23*$G$8 -> 0.62360664 | E23: =$G$23*$G$8 -> 0.62360664 | F23: =$G$23*$G$8 -> 0.62360664 | G23: =Mombasa!G24 -> 0.53759193 | H23: 40km radius-Delivery rate within town
C25: Kshs/lt | D25: 0.33 | E25: 0.33 | F25: 0.33 | H25: Ferry Charges
C27: Kshs/lt | D27: =D19+D21+D23+D25 -> 154.9421 | E27: =E19+E21+E23+E25 -> 157.39087 | F27: =F19+F21+F23+F25 -> 154.82215 | H27: Maximum retail pump price

Sheet LIKONI_PRICE VAT Inclusive
B3: OMC WHOLE-SALE FUEL PRICE BREAK-DOWN INCLUDING VAT
B4: =Mombasa!C4 -> March 15 - April 14, 2023 | C4: Super petrol | E4: Diesel | G4: Kerosene
B5: Item | C5: COST/ PRICE | D5: (INPUT)/ OUTPUT | E5: COST/ PRICE | F5: (INPUT)/ OUTPUT | G5: COST/ PRICE | H5: (INPUT)/ OUTPUT
B6: Landed cost, exclusive of VAT (KShs/Litre) [a+b+c] | C6: =C$7+C$8 -> 90.386689 | E6: =E$7+E$8 -> 103.01178 | G6: =G$7+G$8 -> 105.4031
B7: (a) None VAT-charged costs (KShs/litre) | C7: ='PMS SUMMARY'!D45 -> 89.740845 | E7: ='AGO SUMMARY'!E47 -> 102.43802 | G7: ='DPK SUMMARY'!D44 -> 104.66296
B8: (b) VAT-charged costs (KShs/litre) | C8: ='PMS SUMMARY'!D44 -> 0.6458438 | E8: ='AGO SUMMARY'!E46 -> 0.5737644 | G8: ='DPK SUMMARY'!D43 -> 0.74013888
A9: I. | B9: VATable amount (KShs/Litre) | C9: =C$6 -> 90.386689 | E9: =E$6 -> 103.01178 | G9: =G$6 -> 105.4031
B10: INPUT VAT 2 (on I.) | D10: =-(C9*0.08) -> -7.2309351 | F10: =-(E9*0.08) -> -8.2409425 | H10: =-(G9*0.08) -> -8.4322483
A11: II. | B11: Levies
B12: Excise duty | C12: ='Breakdown for PMS, AGO & DPK'!D19 -> 21.95302 | E12: ='Breakdown for PMS, AGO & DPK'!E19 -> 11.37099 | G12: ='Breakdown for PMS, AGO & DPK'!F19 -> 11.37098
B13: Merchant Shipping Fee | C13: ='PMS SUMMARY'!D46 -> 0.029475332 | E13: ='AGO SUMMARY'!E48 -> 0.033048548 | G13: ='DPK SUMMARY'!D45 -> 0.0014519287
B14: Import Declaration Fee | C14: ='PMS SUMMARY'!D47 -> 3.0336263 | E14: ='AGO SUMMARY'!E49 -> 3.490076 | G14: ='DPK SUMMARY'!D46 -> 3.5235822
B15: Road Maintenance Levy | C15: ='Breakdown for PMS, AGO & DPK'!D20 -> 18 | E15: ='Breakdown for PMS, AGO & DPK'!E20 -> 18 | G15: 0
B16: Anti-adulteration Levy | C16: 0 | E16: 0 | G16: ='Breakdown for PMS, AGO & DPK'!F24 -> 18
B17: Petroleum Development Levy | C17: ='Breakdown for PMS, AGO & DPK'!D21 -> 5.4 | E17: ='Breakdown for PMS, AGO & DPK'!E21 -> 5.4 | G17: ='Breakdown for PMS, AGO & DPK'!F21 -> 0.4
B18: Petroleum Regulatory Levy | C18: ='Breakdown for PMS, AGO & DPK'!D22 -> 0.25 | E18: ='Breakdown for PMS, AGO & DPK'!E22 -> 0.25 | G18: ='Breakdown for PMS, AGO & DPK'!F22 -> 0.25
B19: Railway Development Levy | C19: ='Breakdown for PMS, AGO & DPK'!D23 -> 1.7335008 | E19: ='Breakdown for PMS, AGO & DPK'!E23 -> 1.9943291 | G19: ='Breakdown for PMS, AGO & DPK'!F23 -> 2.0134756
B20: Sub-total | C20: =SUM(C12:C19) -> 50.399622 | E20: =SUM(E12:E19) -> 40.538444 | G20: =SUM(G12:G19) -> 35.55949
A21: III. | B21: Storage and Distribution Costs (Variable/Litre) | C21: =SUM(C$22:C$23) -> 0.70445024 | E21: =SUM(E$22:E$23) -> 0.43092702 | G21: =SUM(G$22:G$23) -> 0.42324391
B22: Storage and Distribution Costs (with VAT) | C22: =SUM(C$24:C$25) -> 0 | E22: =SUM(E$24:E$25) -> 0 | G22: =SUM(G$24:G$25) -> 0
B23: Storage and Distribution Costs (without VAT) | C23: =C$26+C$27 -> 0.70445024 | E23: =E$26+E$27 -> 0.43092702 | G23: =G$26+G$27 -> 0.42324391
B24: Pipeline Transport (Msa-Likoni) | C24: ='Likoni Mainland'!D9 -> 0 | E24: ='Likoni Mainland'!E9 -> 0 | G24: ='Likoni Mainland'!F9 -> 0
B25: Road Transport (Msa-Likoni) - Bridging | C25: ='Likoni Mainland'!D11 -> 0 | E25: ='Likoni Mainland'!E11 -> 0 | G25: ='Likoni Mainland'!F11 -> 0
B26: Pipeline Losses | C26: ='Likoni Mainland'!D13 -> 0 | E26: ='Likoni Mainland'!E13 -> 0 | G26: ='Likoni Mainland'!F13 -> 0
B27: Depot Losses | C27: ='Likoni Mainland'!D15 -> 0.70445024 | E27: ='Likoni Mainland'!E15 -> 0.43092702 | G27: ='Likoni Mainland'!F15 -> 0.42324391
A28: IV. | B28: Oil Marketers Margin | C28: ='MOMBASA_PRICE VAT Inclusive'!$C$28 -> 4.204 | E28: ='MOMBASA_PRICE VAT Inclusive'!$E$28 -> 4.174 | G28: ='MOMBASA_PRICE VAT Inclusive'!$G$28 -> 4.174
B29: VATable price [(I)+(III)+(IV)] | C29: =C$9+C$20+C$22+C$23+C$28 -> 145.69476 | E29: =E$9+E$20+E$22+E$23+E$28 -> 148.15515 | G29: =G$9+G$20+G$22+G$23+G$28 -> 145.55984
B30: Output VAT | D30: =CONCATENATE("+ ",ROUND((C$29*0.08),2)) -> + 11.66 | F30: =CONCATENATE("+ ",ROUND((E$29*0.08),2)) -> + 11.85 | H30: =CONCATENATE("+ ",ROUND((G$29*0.08),2)) -> + 11.64
B31: OMC Wholesale price exclusive of VAT | C31: =C$9+C$20+C$21+C$28 -> 145.69476 | E31: =E$9+E$20+E$21+E$28 -> 148.15515 | G31: =G$9+G$20+G$21+G$28 -> 145.55984
B32: ADD: VAT at wholesale | C32: =D30 -> + 11.66 | E32: =F30 -> + 11.85 | G32: =H30 -> + 11.64
B33: Wholesale Price inxclusive of VAT | C33: =C31+C32 -> 157.35476 | D33: =+D10+D30 -> 4.4290649 | E33: =E31+E32 -> 160.00515 | F33: =F10+F30 -> 3.6090575 | G33: =G31+G32 -> 157.19984 | H33: =H10+H30 -> 3.2077517
B35: RETAIL FUEL COST BREAK-DOWN INCLUDING VAT
C36: =C4 -> Super petrol | E36: =E4 -> Diesel | G36: =G4 -> Kerosene
A37: V. | B37: Wholesale price inclusive of VAT | C37: =C33 -> 157.35476 | E37: =E33 -> 160.00515 | G37: =G33 -> 157.19984
B38: Input VAT on Product at retail | D38: =-C32 -> -11.66 | F38: =-E32 -> -11.85 | H38: =-G32 -> -11.64
A39: VI. | B39: Distribution Costs
B40: Delivery within 40kms | C40: ='Likoni Mainland'!G23 -> 0.53759193 | E40: =C40 -> 0.53759193 | G40: =E40 -> 0.53759193
B41: Ferry transport | C41: ='Likoni Mainland'!D25 -> 0.33 | E41: =C41 -> 0.33 | G41: =E41 -> 0.33
B42: Subtotal | C42: =C40+C41 -> 0.86759193 | E42: =E40+E41 -> 0.86759193 | G42: =G40+G41 -> 0.86759193
A43: VII | B43: Retailer's Margin | C43: ='MOMBASA_PRICE VAT Inclusive'!C42 -> 8.19 | E43: ='MOMBASA_PRICE VAT Inclusive'!E42 -> 8.19 | G43: ='MOMBASA_PRICE VAT Inclusive'!G42 -> 8.19
B44: Retail price | C44: =C$37+C$43+C$42 -> 166.41235 | E44: =E$37+E$43+E$42 -> 169.06274 | G44: =G$37+G$43+G$42 -> 166.25743
B45: LESS: Levies | C45: 0 | E45: 0 | G45: 0
B46: Non-VATable storage and distribution costs | C46: 0 | E46: 0 | G46: 0
B47: VATable value [(V)+(VI)-Input VAT] | C47: =C$44-C45-C46+D$38 -> 154.75235 | E47: =E$44-E45-E46+F$38 -> 157.21274 | G47: =G$44-G45-G46+H$38 -> 154.61743
B48: Output VAT on product at retail level | D48: =CONCATENATE("+ ",ROUND((C$47*0.08),2)) -> + 12.38 | F48: =CONCATENATE("+ ",ROUND((E$47*0.08),2)) -> + 12.58 | H48: =CONCATENATE("+ ",ROUND((G$47*0.08),2)) -> + 12.37
B49: ADD: VAT at retail | C49: =D48 -> + 12.38 | E49: =F48 -> + 12.58 | G49: =H48 -> + 12.37
B50: Retail Pump-Price under VAT regime | C50: =C$47+C$49+C$45+C$46 -> 167.13235 | D50: =D38+D48 -> 0.72 | E50: =E$47+E$49+E$45+E$46 -> 169.79274 | F50: =F38+F48 -> 0.73 | G50: =G$47+G$49+G$45+G$46 -> 166.98743 | H50: =H38+H48 -> 0.73

Sheet Lungalunga
C2: LUNGALUNGA TOWN
C3: Petroleum Costing
C4: ='Likoni Mainland'!C4 -> March 15 - April 14, 2023
D6: PMS | E6: AGO | F6: DPK
C7: Kshs/lt | D7: ='WEIGHTED AVERAGE COST'!L40 -> 140.89005 | E7: ='WEIGHTED AVERAGE COST'!L76 -> 143.64234 | F7: ='WEIGHTED AVERAGE COST'!L104 -> 141.0813 | H7: Weighted average cost (KPRL + KOSF)
G8: =Mombasa!G8 -> 1.16 | H8: 16% VAT Inclusive
C9: Kshs/lt | D9: =$G$10*$G$9*$G$8 -> 0 | E9: =$G$10*$G$9*$G$8 -> 0 | F9: =$G$10*$G$9*$G$8 -> 0 | G9: 0 | H9: % transported through pipeline - Zero for Mombasa
G10: 0 | H10: Pipeline Rate
C11: Kshs/lt | D11: =$G$11*G12*$G$8 -> 0 | E11: =$G$11*G12*$G$8 -> 0 | F11: =$G$11*G12*$G$8 -> 0 | G11: =8.14*G14/1000 -> 0 | H11: Bridging Rate Kshs 0.0814 per litre x distance
G12: 0 | H12: % transported through road
C13: Kshs/lt | D13: =$G$13*D7 -> 0 | E13: =$G$13*E7 -> 0 | F13: =$G$13*F7 -> 0 | G13: 0 | H13: Allowed pipeline losses
G14: 0 | H14: Distance from Source Depot
C15: Kshs/lt | D15: =G15*D7 -> 0.70445024 | E15: =G16*E7 -> 0.43092702 | F15: =G16*F7 -> 0.42324391 | G15: 0.005 | H15: Allowed depot losses. 0.5% for PMS,RMS and 0.3% for AGO,DPK
G16: 0.003
C17: Kshs/lt | D17: =Mombasa!D18 -> 4.204 | E17: =Mombasa!E18 -> 4.174 | F17: =Mombasa!F18 -> 4.174 | H17: Allowed oil marketing company's gross wholesale margin
C19: Kshs/lt | D19: =SUM(D7:D18) -> 145.7985 | E19: =SUM(E7:E18) -> 148.24727 | F19: =SUM(F7:F18) -> 145.67855 | H19: Maximum Wholesale price
C21: Kshs/lt | D21: =Mombasa!D22 -> 8.19 | E21: =Mombasa!E22 -> 8.19 | F21: =Mombasa!F22 -> 8.19 | H21: Allowed retail dealers gross margin
C23: Kshs/lt | D23: =$G$23*$G$8 -> 1.389116 | E23: =$G$23*$G$8 -> 1.389116 | F23: =$G$23*$G$8 -> 1.389116 | G23: ='Delivery >40km-Sept 2013'!E24*I23/1000 -> 1.1975138 | H23: Road distance from Mombasa Depot | I23: 100
C25: Kshs/lt | D25: 0.33 | E25: 0.33 | F25: 0.33 | H25: Ferry Charges
C27: Kshs/lt | D27: =D19+D21+D23+D25 -> 155.70761 | E27: =E19+E21+E23+E25 -> 158.15638 | F27: =F19+F21+F23+F25 -> 155.58766 | H27: Maximum retail pump price

Sheet LUNGALUNGA_PRICE VAT Inclusive
B3: OMC WHOLE-SALE FUEL PRICE BREAK-DOWN INCLUDING VAT
B4: =Mombasa!C4 -> March 15 - April 14, 2023 | C4: Super petrol | E4: Diesel | G4: Kerosene
B5: Item | C5: COST/ PRICE | D5: (INPUT)/ OUTPUT | E5: COST/ PRICE | F5: (INPUT)/ OUTPUT | G5: COST/ PRICE | H5: (INPUT)/ OUTPUT
B6: Landed cost, exclusive of VAT (KShs/Litre) [a+b+c] | C6: =C$7+C$8 -> 90.386689 | E6: =E$7+E$8 -> 103.01178 | G6: =G$7+G$8 -> 105.4031
B7: (a) None VAT-charged costs (KShs/litre) | C7: ='PMS SUMMARY'!D45 -> 89.740845 | E7: ='AGO SUMMARY'!E47 -> 102.43802 | G7: ='DPK SUMMARY'!D44 -> 104.66296
B8: (b) VAT-charged costs (KShs/litre) | C8: ='PMS SUMMARY'!D44 -> 0.6458438 | E8: ='AGO SUMMARY'!E46 -> 0.5737644 | G8: ='DPK SUMMARY'!D43 -> 0.74013888
A9: I. | B9: VATable amount (KShs/Litre) | C9: =C$6 -> 90.386689 | E9: =E$6 -> 103.01178 | G9: =G$6 -> 105.4031
B10: INPUT VAT 2 (on I.) | D10: =-(C9*0.08) -> -7.2309351 | F10: =-(E9*0.08) -> -8.2409425 | H10: =-(G9*0.08) -> -8.4322483
A11: II. | B11: Levies
B12: Excise duty | C12: ='Breakdown for PMS, AGO & DPK'!D19 -> 21.95302 | E12: ='Breakdown for PMS, AGO & DPK'!E19 -> 11.37099 | G12: ='Breakdown for PMS, AGO & DPK'!F19 -> 11.37098
B13: Merchant Shipping Fee | C13: ='PMS SUMMARY'!D46 -> 0.029475332 | E13: ='AGO SUMMARY'!E48 -> 0.033048548 | G13: ='DPK SUMMARY'!D45 -> 0.0014519287
B14: Import Declaration Fee | C14: ='PMS SUMMARY'!D47 -> 3.0336263 | E14: ='AGO SUMMARY'!E49 -> 3.490076 | G14: ='DPK SUMMARY'!D46 -> 3.5235822
B15: Road Maintenance Levy | C15: ='Breakdown for PMS, AGO & DPK'!D20 -> 18 | E15: ='Breakdown for PMS, AGO & DPK'!E20 -> 18 | G15: 0
B16: Anti-adulteration Levy | C16: 0 | E16: 0 | G16: ='Breakdown for PMS, AGO & DPK'!F24 -> 18
B17: Petroleum Development Levy | C17: ='Breakdown for PMS, AGO & DPK'!D21 -> 5.4 | E17: ='Breakdown for PMS, AGO & DPK'!E21 -> 5.4 | G17: ='Breakdown for PMS, AGO & DPK'!F21 -> 0.4
B18: Petroleum Regulatory Levy | C18: ='Breakdown for PMS, AGO & DPK'!D22 -> 0.25 | E18: ='Breakdown for PMS, AGO & DPK'!E22 -> 0.25 | G18: ='Breakdown for PMS, AGO & DPK'!F22 -> 0.25
B19: Railway Development Levy | C19: ='Breakdown for PMS, AGO & DPK'!D23 -> 1.7335008 | E19: ='Breakdown for PMS, AGO & DPK'!E23 -> 1.9943291 | G19: ='Breakdown for PMS, AGO & DPK'!F23 -> 2.0134756
B20: Sub-total | C20: =SUM(C12:C19) -> 50.399622 | E20: =SUM(E12:E19) -> 40.538444 | G20: =SUM(G12:G19) -> 35.55949
A21: III. | B21: Storage and Distribution Costs (Variable/Litre) | C21: =SUM(C$22:C$23) -> 0.70445024 | E21: =SUM(E$22:E$23) -> 0.43092702 | G21: =SUM(G$22:G$23) -> 0.42324391
B22: Storage and Distribution Costs (with VAT) | C22: =SUM(C$24:C$25) -> 0 | E22: =SUM(E$24:E$25) -> 0 | G22: =SUM(G$24:G$25) -> 0
B23: Storage and Distribution Costs (without VAT) | C23: =C$26+C$27 -> 0.70445024 | E23: =E$26+E$27 -> 0.43092702 | G23: =G$26+G$27 -> 0.42324391
B24: Pipeline Transport (Msa-Likoni) | C24: ='Likoni Mainland'!D9 -> 0 | E24: ='Likoni Mainland'!E9 -> 0 | G24: ='Likoni Mainland'!F9 -> 0
B25: Road Transport (Msa-Likoni) - Bridging | C25: ='Likoni Mainland'!D11 -> 0 | E25: ='Likoni Mainland'!E11 -> 0 | G25: ='Likoni Mainland'!F11 -> 0
B26: Pipeline Losses | C26: ='Likoni Mainland'!D13 -> 0 | E26: ='Likoni Mainland'!E13 -> 0 | G26: ='Likoni Mainland'!F13 -> 0
B27: Depot Losses | C27: ='Likoni Mainland'!D15 -> 0.70445024 | E27: ='Likoni Mainland'!E15 -> 0.43092702 | G27: ='Likoni Mainland'!F15 -> 0.42324391
A28: IV. | B28: Oil Marketers Margin | C28: ='MOMBASA_PRICE VAT Inclusive'!$C$28 -> 4.204 | E28: ='MOMBASA_PRICE VAT Inclusive'!$E$28 -> 4.174 | G28: ='MOMBASA_PRICE VAT Inclusive'!$G$28 -> 4.174
B29: VATable price [(I)+(III)+(IV)] | C29: =C$9+C$20+C$22+C$23+C$28 -> 145.69476 | E29: =E$9+E$20+E$22+E$23+E$28 -> 148.15515 | G29: =G$9+G$20+G$22+G$23+G$28 -> 145.55984
B30: Output VAT | D30: =CONCATENATE("+ ",ROUND((C$29*0.08),2)) -> + 11.66 | F30: =CONCATENATE("+ ",ROUND((E$29*0.08),2)) -> + 11.85 | H30: =CONCATENATE("+ ",ROUND((G$29*0.08),2)) -> + 11.64
B31: OMC Wholesale price exclusive of VAT | C31: =C$9+C$20+C$21+C$28 -> 145.69476 | E31: =E$9+E$20+E$21+E$28 -> 148.15515 | G31: =G$9+G$20+G$21+G$28 -> 145.55984
B32: ADD: VAT at wholesale | C32: =D30 -> + 11.66 | E32: =F30 -> + 11.85 | G32: =H30 -> + 11.64
B33: Wholesale Price inxclusive of VAT | C33: =C31+C32 -> 157.35476 | D33: =+D10+D30 -> 4.4290649 | E33: =E31+E32 -> 160.00515 | F33: =F10+F30 -> 3.6090575 | G33: =G31+G32 -> 157.19984 | H33: =H10+H30 -> 3.2077517
B35: RETAIL FUEL COST BREAK-DOWN INCLUDING VAT
C36: =C4 -> Super petrol | E36: =E4 -> Diesel | G36: =G4 -> Kerosene
A37: V. | B37: Wholesale price inclusive of VAT | C37: =C33 -> 157.35476 | E37: =E33 -> 160.00515 | G37: =G33 -> 157.19984
B38: Input VAT on Product at retail | D38: =-C32 -> -11.66 | F38: =-E32 -> -11.85 | H38: =-G32 -> -11.64
A39: VI. | B39: Distribution Costs
B40: Delivery within 40kms | C40: =Lungalunga!G23 -> 1.1975138 | E40: =C40 -> 1.1975138 | G40: =E40 -> 1.1975138
B41: Ferry transport | C41: ='Likoni Mainland'!D25 -> 0.33 | E41: =C41 -> 0.33 | G41: =E41 -> 0.33
B42: Subtotal | C42: =C40+C41 -> 1.5275138 | E42: =E40+E41 -> 1.5275138 | G42: =G40+G41 -> 1.5275138
A43: VII | B43: Retailer's Margin | C43: ='MOMBASA_PRICE VAT Inclusive'!C42 -> 8.19 | E43: ='MOMBASA_PRICE VAT Inclusive'!E42 -> 8.19 | G43: ='MOMBASA_PRICE VAT Inclusive'!G42 -> 8.19
B44: Retail price | C44: =C$37+C$43+C$42 -> 167.07228 | E44: =E$37+E$43+E$42 -> 169.72267 | G44: =G$37+G$43+G$42 -> 166.91735
B45: LESS: Levies | C45: 0 | E45: 0 | G45: 0
B46: Non-VATable storage and distribution costs | C46: 0 | E46: 0 | G46: 0
B47: VATable value [(V)+(VI)-Input VAT] | C47: =C$44-C45-C46+D$38 -> 155.41228 | E47: =E$44-E45-E46+F$38 -> 157.87267 | G47: =G$44-G45-G46+H$38 -> 155.27735
B48: Output VAT on product at retail level | D48: =CONCATENATE("+ ",ROUND((C$47*0.08),2)) -> + 12.43 | F48: =CONCATENATE("+ ",ROUND((E$47*0.08),2)) -> + 12.63 | H48: =CONCATENATE("+ ",ROUND((G$47*0.08),2)) -> + 12.42
B49: ADD: VAT at retail | C49: =D48 -> + 12.43 | E49: =F48 -> + 12.63 | G49: =H48 -> + 12.42
B50: Retail Pump-Price under VAT regime | C50: =C$47+C$49+C$45+C$46 -> 167.84228 | D50: =D38+D48 -> 0.77 | E50: =E$47+E$49+E$45+E$46 -> 170.50267 | F50: =F38+F48 -> 0.78 | G50: =G$47+G$49+G$45+G$46 -> 167.69735 | H50: =H38+H48 -> 0.78

Sheet Kwale
C2: KWALE TOWN
C3: Petroleum Costing
C4: ='Likoni Mainland'!C4 -> March 15 - April 14, 2023
D6: PMS | E6: AGO | F6: DPK
C7: Kshs/lt | D7: ='WEIGHTED AVERAGE COST'!L40 -> 140.89005 | E7: ='WEIGHTED AVERAGE COST'!L76 -> 143.64234 | F7: ='WEIGHTED AVERAGE COST'!L104 -> 141.0813 | H7: Weighted average cost (KPRL + KOSF)
G8: =Mombasa!G8 -> 1.16 | H8: 16% VAT Inclusive
C9: Kshs/lt | D9: =$G$10*$G$9*$G$8 -> 0 | E9: =$G$10*$G$9*$G$8 -> 0 | F9: =$G$10*$G$9*$G$8 -> 0 | G9: 0 | H9: % transported through pipeline - Zero for Mombasa
G10: 0 | H10: Pipeline Rate
C11: Kshs/lt | D11: =$G$11*G12*$G$8 -> 0 | E11: =$G$11*G12*$G$8 -> 0 | F11: =$G$11*G12*$G$8 -> 0 | G11: =8.14*G14/1000 -> 0 | H11: Bridging Rate Kshs 0.0814 per litre x distance
G12: 0 | H12: % transported through road
C13: Kshs/lt | D13: =$G$13*D7 -> 0 | E13: =$G$13*E7 -> 0 | F13: =$G$13*F7 -> 0 | G13: 0 | H13: Allowed pipeline losses
G14: 0 | H14: Distance from Source Depot
C15: Kshs/lt | D15: =G15*D7 -> 0.70445024 | E15: =G16*E7 -> 0.43092702 | F15: =G16*F7 -> 0.42324391 | G15: 0.005 | H15: Allowed depot losses. 0.5% for PMS,RMS and 0.3% for AGO,DPK
G16: 0.003
C17: Kshs/lt | D17: =Mombasa!D18 -> 4.204 | E17: =Mombasa!E18 -> 4.174 | F17: =Mombasa!F18 -> 4.174 | H17: Allowed oil marketing company's gross wholesale margin
C19: Kshs/lt | D19: =SUM(D7:D18) -> 145.7985 | E19: =SUM(E7:E18) -> 148.24727 | F19: =SUM(F7:F18) -> 145.67855 | H19: Maximum Wholesale price
C21: Kshs/lt | D21: =Mombasa!D22 -> 8.19 | E21: =Mombasa!E22 -> 8.19 | F21: =Mombasa!F22 -> 8.19 | H21: Allowed retail dealers gross margin
C23: Kshs/lt | D23: =$G$23*$G$8 -> 0.62360664 | E23: =$G$23*$G$8 -> 0.62360664 | F23: =$G$23*$G$8 -> 0.62360664 | G23: =Mombasa!G24 -> 0.53759193 | H23: Road distance from Mombasa Depot | I23: 45 | J23: 40km radius-Delivery rate within town
C25: Kshs/lt | D25: 0.33 | E25: 0.33 | F25: 0.33 | H25: Ferry Charges
C27: Kshs/lt | D27: =D19+D21+D23+D25 -> 154.9421 | E27: =E19+E21+E23+E25 -> 157.39087 | F27: =F19+F21+F23+F25 -> 154.82215 | H27: Maximum retail pump price

Sheet KWALE_PRICE VAT Inclusive
B3: OMC WHOLE-SALE FUEL PRICE BREAK-DOWN INCLUDING VAT
B4: =Mombasa!C4 -> March 15 - April 14, 2023 | C4: Super petrol | E4: Diesel | G4: Kerosene
B5: Item | C5: COST/ PRICE | D5: (INPUT)/ OUTPUT | E5: COST/ PRICE | F5: (INPUT)/ OUTPUT | G5: COST/ PRICE | H5: (INPUT)/ OUTPUT
B6: Landed cost, exclusive of VAT (KShs/Litre) [a+b+c] | C6: =C$7+C$8 -> 90.386689 | E6: =E$7+E$8 -> 103.01178 | G6: =G$7+G$8 -> 105.4031
B7: (a) None VAT-charged costs (KShs/litre) | C7: ='PMS SUMMARY'!D45 -> 89.740845 | E7: ='AGO SUMMARY'!E47 -> 102.43802 | G7: ='DPK SUMMARY'!D44 -> 104.66296
B8: (b) VAT-charged costs (KShs/litre) | C8: ='PMS SUMMARY'!D44 -> 0.6458438 | E8: ='AGO SUMMARY'!E46 -> 0.5737644 | G8: ='DPK SUMMARY'!D43 -> 0.74013888
A9: I. | B9: VATable amount (KShs/Litre) | C9: =C$6 -> 90.386689 | E9: =E$6 -> 103.01178 | G9: =G$6 -> 105.4031
B10: INPUT VAT 2 (on I.) | D10: =-(C9*0.08) -> -7.2309351 | F10: =-(E9*0.08) -> -8.2409425 | H10: =-(G9*0.08) -> -8.4322483
A11: II. | B11: Levies
B12: Excise duty | C12: ='Breakdown for PMS, AGO & DPK'!D19 -> 21.95302 | E12: ='Breakdown for PMS, AGO & DPK'!E19 -> 11.37099 | G12: ='Breakdown for PMS, AGO & DPK'!F19 -> 11.37098
B13: Merchant Shipping Fee | C13: ='PMS SUMMARY'!D46 -> 0.029475332 | E13: ='AGO SUMMARY'!E48 -> 0.033048548 | G13: ='DPK SUMMARY'!D45 -> 0.0014519287
B14: Import Declaration Fee | C14: ='PMS SUMMARY'!D47 -> 3.0336263 | E14: ='AGO SUMMARY'!E49 -> 3.490076 | G14: ='DPK SUMMARY'!D46 -> 3.5235822
B15: Road Maintenance Levy | C15: ='Breakdown for PMS, AGO & DPK'!D20 -> 18 | E15: ='Breakdown for PMS, AGO & DPK'!E20 -> 18 | G15: 0
B16: Anti-adulteration Levy | C16: 0 | E16: 0 | G16: ='Breakdown for PMS, AGO & DPK'!F24 -> 18
B17: Petroleum Development Levy | C17: ='Breakdown for PMS, AGO & DPK'!D21 -> 5.4 | E17: ='Breakdown for PMS, AGO & DPK'!E21 -> 5.4 | G17: ='Breakdown for PMS, AGO & DPK'!F21 -> 0.4
B18: Petroleum Regulatory Levy | C18: ='Breakdown for PMS, AGO & DPK'!D22 -> 0.25 | E18: ='Breakdown for PMS, AGO & DPK'!E22 -> 0.25 | G18: ='Breakdown for PMS, AGO & DPK'!F22 -> 0.25
B19: Railway Development Levy | C19: ='Breakdown for PMS, AGO & DPK'!D23 -> 1.7335008 | E19: ='Breakdown for PMS, AGO & DPK'!E23 -> 1.9943291 | G19: ='Breakdown for PMS, AGO & DPK'!F23 -> 2.0134756
B20: Sub-total | C20: =SUM(C12:C19) -> 50.399622 | E20: =SUM(E12:E19) -> 40.538444 | G20: =SUM(G12:G19) -> 35.55949
A21: III. | B21: Storage and Distribution Costs (Variable/Litre) | C21: =SUM(C$22:C$23) -> 0.70445024 | E21: =SUM(E$22:E$23) -> 0.43092702 | G21: =SUM(G$22:G$23) -> 0.42324391
B22: Storage and Distribution Costs (with VAT) | C22: =SUM(C$24:C$25) -> 0 | E22: =SUM(E$24:E$25) -> 0 | G22: =SUM(G$24:G$25) -> 0
B23: Storage and Distribution Costs (without VAT) | C23: =C$26+C$27 -> 0.70445024 | E23: =E$26+E$27 -> 0.43092702 | G23: =G$26+G$27 -> 0.42324391
B24: Pipeline Transport (Msa-Likoni) | C24: ='Likoni Mainland'!D9 -> 0 | E24: ='Likoni Mainland'!E9 -> 0 | G24: ='Likoni Mainland'!F9 -> 0
B25: Road Transport (Msa-Likoni) - Bridging | C25: ='Likoni Mainland'!D11 -> 0 | E25: ='Likoni Mainland'!E11 -> 0 | G25: ='Likoni Mainland'!F11 -> 0
B26: Pipeline Losses | C26: ='Likoni Mainland'!D13 -> 0 | E26: ='Likoni Mainland'!E13 -> 0 | G26: ='Likoni Mainland'!F13 -> 0
B27: Depot Losses | C27: ='Likoni Mainland'!D15 -> 0.70445024 | E27: ='Likoni Mainland'!E15 -> 0.43092702 | G27: ='Likoni Mainland'!F15 -> 0.42324391
A28: IV. | B28: Oil Marketers Margin | C28: ='MOMBASA_PRICE VAT Inclusive'!$C$28 -> 4.204 | E28: ='MOMBASA_PRICE VAT Inclusive'!$E$28 -> 4.174 | G28: ='MOMBASA_PRICE VAT Inclusive'!$G$28 -> 4.174
B29: VATable price [(I)+(III)+(IV)] | C29: =C$9+C$20+C$22+C$23+C$28 -> 145.69476 | E29: =E$9+E$20+E$22+E$23+E$28 -> 148.15515 | G29: =G$9+G$20+G$22+G$23+G$28 -> 145.55984
B30: Output VAT | D30: =CONCATENATE("+ ",ROUND((C$29*0.08),2)) -> + 11.66 | F30: =CONCATENATE("+ ",ROUND((E$29*0.08),2)) -> + 11.85 | H30: =CONCATENATE("+ ",ROUND((G$29*0.08),2)) -> + 11.64
B31: OMC Wholesale price exclusive of VAT | C31: =C$9+C$20+C$21+C$28 -> 145.69476 | E31: =E$9+E$20+E$21+E$28 -> 148.15515 | G31: =G$9+G$20+G$21+G$28 -> 145.55984
B32: ADD: VAT at wholesale | C32: =D30 -> + 11.66 | E32: =F30 -> + 11.85 | G32: =H30 -> + 11.64
B33: Wholesale Price inxclusive of VAT | C33: =C31+C32 -> 157.35476 | D33: =+D10+D30 -> 4.4290649 | E33: =E31+E32 -> 160.00515 | F33: =F10+F30 -> 3.6090575 | G33: =G31+G32 -> 157.19984 | H33: =H10+H30 -> 3.2077517
B35: RETAIL FUEL COST BREAK-DOWN INCLUDING VAT
C36: =C4 -> Super petrol | E36: =E4 -> Diesel | G36: =G4 -> Kerosene
A37: V. | B37: Wholesale price inclusive of VAT | C37: =C33 -> 157.35476 | E37: =E33 -> 160.00515 | G37: =G33 -> 157.19984
B38: Input VAT on Product at retail | D38: =-C32 -> -11.66 | F38: =-E32 -> -11.85 | H38: =-G32 -> -11.64
A39: VI. | B39: Distribution Costs
B40: Delivery within 40kms | C40: =Kwale!G23 -> 0.53759193 | E40: =C40 -> 0.53759193 | G40: =E40 -> 0.53759193
B41: Ferry transport | C41: ='Likoni Mainland'!D25 -> 0.33 | E41: =C41 -> 0.33 | G41: =E41 -> 0.33
B42: Subtotal | C42: =C40+C41 -> 0.86759193 | E42: =E40+E41 -> 0.86759193 | G42: =G40+G41 -> 0.86759193
A43: VII | B43: Retailer's Margin | C43: ='MOMBASA_PRICE VAT Inclusive'!C42 -> 8.19 | E43: ='MOMBASA_PRICE VAT Inclusive'!E42 -> 8.19 | G43: ='MOMBASA_PRICE VAT Inclusive'!G42 -> 8.19
B44: Retail price | C44: =C$37+C$43+C$42 -> 166.41235 | E44: =E$37+E$43+E$42 -> 169.06274 | G44: =G$37+G$43+G$42 -> 166.25743
B45: LESS: Levies | C45: 0 | E45: 0 | G45: 0
B46: Non-VATable storage and distribution costs | C46: 0 | E46: 0 | G46: 0
B47: VATable value [(V)+(VI)-Input VAT] | C47: =C$44-C45-C46+D$38 -> 154.75235 | E47: =E$44-E45-E46+F$38 -> 157.21274 | G47: =G$44-G45-G46+H$38 -> 154.61743
B48: Output VAT on product at retail level | D48: =CONCATENATE("+ ",ROUND((C$47*0.08),2)) -> + 12.38 | F48: =CONCATENATE("+ ",ROUND((E$47*0.08),2)) -> + 12.58 | H48: =CONCATENATE("+ ",ROUND((G$47*0.08),2)) -> + 12.37
B49: ADD: VAT at retail | C49: =D48 -> + 12.38 | E49: =F48 -> + 12.58 | G49: =H48 -> + 12.37
B50: Retail Pump-Price under VAT regime | C50: =C$47+C$49+C$45+C$46 -> 167.13235 | D50: =D38+D48 -> 0.72 | E50: =E$47+E$49+E$45+E$46 -> 169.79274 | F50: =F38+F48 -> 0.73 | G50: =G$47+G$49+G$45+G$46 -> 166.98743 | H50: =H38+H48 -> 0.73

Sheet Malindi
C2: MALINDI TOWN
C3: Petroleum Costing
C4: =Kwale!C4 -> March 15 - April 14, 2023
D6: PMS | E6: AGO | F6: DPK
C7: Kshs/lt | D7: ='WEIGHTED AVERAGE COST'!L40 -> 140.89005 | E7: ='WEIGHTED AVERAGE COST'!L76 -> 143.64234 | F7: ='WEIGHTED AVERAGE COST'!L104 -> 141.0813 | H7: Weighted average cost (KPRL + KOSF)
G8: =Mombasa!G8 -> 1.16 | H8: 16% VAT Inclusive
C9: Kshs/lt | D9: =$G$10*$G$9*$G$8 -> 0 | E9: =$G$10*$G$9*$G$8 -> 0 | F9: =$G$10*$G$9*$G$8 -> 0 | G9: 0 | H9: % transported through pipeline - Zero for Mombasa
G10: 0 | H10: Pipeline Rate
C11: Kshs/lt | D11: =$G$11*G12*$G$8 -> 0 | E11: =$G$11*G12*$G$8 -> 0 | F11: =$G$11*G12*$G$8 -> 0 | G11: =8.14*G14/1000 -> 0 | H11: Bridging Rate Kshs 0.0814 per litre x distance
G12: 0 | H12: % transported through road
C13: Kshs/lt | D13: =$G$13*D7 -> 0 | E13: =$G$13*E7 -> 0 | F13: =$G$13*F7 -> 0 | G13: 0 | H13: Allowed pipeline losses
G14: 0 | H14: Distance from Source Depot
C15: Kshs/lt | D15: =G15*D7 -> 0.70445024 | E15: =G16*E7 -> 0.43092702 | F15: =G16*F7 -> 0.42324391 | G15: 0.005 | H15: Allowed depot losses. 0.5% for PMS,RMS and 0.3% for AGO,DPK
G16: 0.003
C17: Kshs/lt | D17: =Mombasa!D18 -> 4.204 | E17: =Mombasa!E18 -> 4.174 | F17: =Mombasa!F18 -> 4.174 | H17: Allowed oil marketing company's gross wholesale margin
C19: Kshs/lt | D19: =SUM(D7:D18) -> 145.7985 | E19: =SUM(E7:E18) -> 148.24727 | F19: =SUM(F7:F18) -> 145.67855 | H19: Maximum Wholesale price
C21: Kshs/lt | D21: =Mombasa!D22 -> 8.19 | E21: =Mombasa!E22 -> 8.19 | F21: =Mombasa!F22 -> 8.19 | H21: Allowed retail dealers gross margin
C23: Kshs/lt | D23: =$G$23*$G$8 -> 1.6113745 | E23: =$G$23*$G$8 -> 1.6113745 | F23: =$G$23*$G$8 -> 1.6113745 | G23: ='Delivery >40km-Sept 2013'!E24*I23/1000 -> 1.389116 | H23: Road distance from Mombasa Depot | I23: 116
C25: Kshs/lt | D25: =D19+D21+D23 -> 155.59987 | E25: =E19+E21+E23 -> 158.04864 | F25: =F19+F21+F23 -> 155.47992 | H25: Maximum retail pump price

Sheet MALINDI_PRICE VAT Inclusive
B3: OMC WHOLE-SALE FUEL PRICE BREAK-DOWN INCLUDING VAT
B4: =Mombasa!C4 -> March 15 - April 14, 2023 | C4: Super petrol | E4: Diesel | G4: Kerosene
B5: Item | C5: COST/ PRICE | D5: (INPUT)/ OUTPUT | E5: COST/ PRICE | F5: (INPUT)/ OUTPUT | G5: COST/ PRICE | H5: (INPUT)/ OUTPUT
B6: Landed cost, exclusive of VAT (KShs/Litre) [a+b+c] | C6: =C$7+C$8 -> 90.386689 | E6: =E$7+E$8 -> 103.01178 | G6: =G$7+G$8 -> 105.4031
B7: (a) None VAT-charged costs (KShs/litre) | C7: ='PMS SUMMARY'!D45 -> 89.740845 | E7: ='AGO SUMMARY'!E47 -> 102.43802 | G7: ='DPK SUMMARY'!D44 -> 104.66296
B8: (b) VAT-charged costs (KShs/litre) | C8: ='PMS SUMMARY'!D44 -> 0.6458438 | E8: ='AGO SUMMARY'!E46 -> 0.5737644 | G8: ='DPK SUMMARY'!D43 -> 0.74013888
A9: I. | B9: VATable amount (KShs/Litre) | C9: =C$6 -> 90.386689 | E9: =E$6 -> 103.01178 | G9: =G$6 -> 105.4031
B10: INPUT VAT 2 (on I.) | D10: =-(C9*0.08) -> -7.2309351 | F10: =-(E9*0.08) -> -8.2409425 | H10: =-(G9*0.08) -> -8.4322483
A11: II. | B11: Levies
B12: Excise duty | C12: ='Breakdown for PMS, AGO & DPK'!D19 -> 21.95302 | E12: ='Breakdown for PMS, AGO & DPK'!E19 -> 11.37099 | G12: ='Breakdown for PMS, AGO & DPK'!F19 -> 11.37098
B13: Merchant Shipping Fee | C13: ='PMS SUMMARY'!D46 -> 0.029475332 | E13: ='AGO SUMMARY'!E48 -> 0.033048548 | G13: ='DPK SUMMARY'!D45 -> 0.0014519287
B14: Import Declaration Fee | C14: ='PMS SUMMARY'!D47 -> 3.0336263 | E14: ='AGO SUMMARY'!E49 -> 3.490076 | G14: ='DPK SUMMARY'!D46 -> 3.5235822
B15: Road Maintenance Levy | C15: ='Breakdown for PMS, AGO & DPK'!D20 -> 18 | E15: ='Breakdown for PMS, AGO & DPK'!E20 -> 18 | G15: 0
B16: Anti-adulteration Levy | C16: 0 | E16: 0 | G16: ='Breakdown for PMS, AGO & DPK'!F24 -> 18
B17: Petroleum Development Levy | C17: ='Breakdown for PMS, AGO & DPK'!D21 -> 5.4 | E17: ='Breakdown for PMS, AGO & DPK'!E21 -> 5.4 | G17: ='Breakdown for PMS, AGO & DPK'!F21 -> 0.4
B18: Petroleum Regulatory Levy | C18: ='Breakdown for PMS, AGO & DPK'!D22 -> 0.25 | E18: ='Breakdown for PMS, AGO & DPK'!E22 -> 0.25 | G18: ='Breakdown for PMS, AGO & DPK'!F22 -> 0.25
B19: Railway Development Levy | C19: ='Breakdown for PMS, AGO & DPK'!D23 -> 1.7335008 | E19: ='Breakdown for PMS, AGO & DPK'!E23 -> 1.9943291 | G19: ='Breakdown for PMS, AGO & DPK'!F23 -> 2.0134756
B20: Sub-total | C20: =SUM(C12:C19) -> 50.399622 | E20: =SUM(E12:E19) -> 40.538444 | G20: =SUM(G12:G19) -> 35.55949
A21: III. | B21: Storage and Distribution Costs (Variable/Litre) | C21: =SUM(C$22:C$23) -> 0.70445024 | E21: =SUM(E$22:E$23) -> 0.43092702 | G21: =SUM(G$22:G$23) -> 0.42324391
B22: Storage and Distribution Costs (with VAT) | C22: =SUM(C$24:C$25) -> 0 | E22: =SUM(E$24:E$25) -> 0 | G22: =SUM(G$24:G$25) -> 0
B23: Storage and Distribution Costs (without VAT) | C23: =C$26+C$27 -> 0.70445024 | E23: =E$26+E$27 -> 0.43092702 | G23: =G$26+G$27 -> 0.42324391
B24: Pipeline Transport (Msa) | C24: =Mombasa!D9 -> 0 | E24: =Mombasa!E9 -> 0 | G24: =Mombasa!F9 -> 0
B25: Road Transport (Msa) - Bridging | C25: =Mombasa!D11 -> 0 | E25: =Mombasa!E11 -> 0 | G25: =Mombasa!F11 -> 0
B26: Pipeline Losses | C26: =Mombasa!D13 -> 0 | E26: =Mombasa!E13 -> 0 | G26: =Mombasa!F13 -> 0
B27: Depot Losses | C27: =Mombasa!D15 -> 0.70445024 | E27: =Mombasa!E15 -> 0.43092702 | G27: =Mombasa!F15 -> 0.42324391
A28: IV. | B28: Oil Marketers Margin | C28: =Mombasa!D18 -> 4.204 | E28: =Mombasa!E18 -> 4.174 | G28: =Mombasa!F18 -> 4.174
B29: VATable price [(I)+(III)+(IV)] | C29: =C$9+C$20+C$22+C$23+C$28 -> 145.69476 | E29: =E$9+E$20+E$22+E$23+E$28 -> 148.15515 | G29: =G$9+G$20+G$22+G$23+G$28 -> 145.55984
B30: Output VAT | D30: =CONCATENATE("+ ",ROUND((C$29*0.08),2)) -> + 11.66 | F30: =CONCATENATE("+ ",ROUND((E$29*0.08),2)) -> + 11.85 | H30: =CONCATENATE("+ ",ROUND((G$29*0.08),2)) -> + 11.64
B31: OMC Wholesale price exclusive of VAT | C31: =C$9+C$20+C$21+C$28 -> 145.69476 | E31: =E$9+E$20+E$21+E$28 -> 148.15515 | G31: =G$9+G$20+G$21+G$28 -> 145.55984
B32: ADD: VAT at wholesale | C32: =D30 -> + 11.66 | E32: =F30 -> + 11.85 | G32: =H30 -> + 11.64
B33: Wholesale Price inxclusive of VAT | C33: =C31+C32 -> 157.35476 | D33: =+D10+D30 -> 4.4290649 | E33: =E31+E32 -> 160.00515 | F33: =F10+F30 -> 3.6090575 | G33: =G31+G32 -> 157.19984 | H33: =H10+H30 -> 3.2077517
B35: RETAIL FUEL COST BREAK-DOWN INCLUDING VAT
C36: =C4 -> Super petrol | E36: =E4 -> Diesel | G36: =G4 -> Kerosene
A37: V. | B37: Wholesale price inclusive of VAT | C37: =C33 -> 157.35476 | E37: =E33 -> 160.00515 | G37: =G33 -> 157.19984
B38: Input VAT on Product at retail | D38: =-C32 -> -11.66 | F38: =-E32 -> -11.85 | H38: =-G32 -> -11.64
A39: VI. | B39: Distribution Cost
B40: Delivery Within 40kms | C40: =Malindi!G23 -> 1.389116 | E40: =C40 -> 1.389116 | G40: =E40 -> 1.389116
B41: Subtotal | C41: =SUM(C40) -> 1.389116 | E41: =SUM(E40) -> 1.389116 | G41: =SUM(G40) -> 1.389116
A42: VII. | B42: Retailer's Margin | C42: =Mombasa!D22 -> 8.19 | E42: =Mombasa!E22 -> 8.19 | G42: =Mombasa!F22 -> 8.19
B43: Retail price | C43: =C$37+C$42+C$41 -> 166.93388 | E43: =E$37+E$42+E$41 -> 169.58427 | G43: =G$37+G$42+G$41 -> 166.77895
B44: LESS: Levies | C44: 0 | E44: 0 | G44: 0
B45: Non-VATable storage and distribution costs | C45: 0 | E45: 0 | G45: 0
B46: VATable value [(V)+(VI)-Input VAT] | C46: =C$43-C44-C45+D$38 -> 155.27388 | E46: =E$43-E44-E45+F$38 -> 157.73427 | G46: =G$43-G44-G45+H$38 -> 155.13895
B47: Output VAT on product at retail level | D47: =CONCATENATE("+ ",ROUND((C$46*0.08),2)) -> + 12.42 | F47: =CONCATENATE("+ ",ROUND((E$46*0.08),2)) -> + 12.62 | H47: =CONCATENATE("+ ",ROUND((G$46*0.08),2)) -> + 12.41
B48: ADD: VAT at retail | C48: =D47 -> + 12.42 | E48: =F47 -> + 12.62 | G48: =H47 -> + 12.41
B49: Retail Pump-Price under VAT regime | C49: =C$46+C$48+C$44+C$45 -> 167.69388 | D49: =D38+D47 -> 0.76 | E49: =E$46+E$48+E$44+E$45 -> 170.35427 | F49: =F38+F47 -> 0.77 | G49: =G$46+G$48+G$44+G$45 -> 167.54895 | H49: =H38+H47 -> 0.77
A51: EXPECTED IMPACT ON THE FINAL RETAIL PRICE COMPARED TO THE NON-VAT REGIME
B53: ERC PRICE UNDER NON-VAT REGIME | C53: =Mombasa!D26 -> 154.6121 | D53: =C9+C20+C21+C28+C42+0.16*C8+0.16*SUM(C24:C25) -> 153.9881 | E53: ='Breakdown for PMS, AGO & DPK'!E26 -> 160.05845 | G53: ='Breakdown for PMS, AGO & DPK'!F26 -> 157.48856
B54: PRICE DIFFERENCE | C54: =C49-C53 -> 13.081773 | D54: =C53-D53 -> 0.62400843 | E54: =E49-E53 -> 10.295818 | G54: =G49-G53 -> 10.060393
B55: PERCENTAGE INCREAMENT | C55: =C54/C53 -> 0.084610274 | D55: =7-5.55+3.89-3.112 -> 2.228 | E55: =E54/E53 -> 0.064325363 | G55: =G54/G53 -> 0.063880152
B56: GOVERNMENT NET VAT COLLECTION (KSHS PER LITRE) | C56: =D$33+D$49+-$D$10 -> 12.42 | E56: =F$33+F$49 -> 4.3790575 | G56: =H$33+H$49 -> 3.9777517

Sheet Voi
C2: VOI TOWN
C3: Petroleum Costing
C4: =Malindi!C4 -> March 15 - April 14, 2023
D6: PMS | E6: AGO | F6: DPK
C7: Kshs/lt | D7: ='WEIGHTED AVERAGE COST'!L40 -> 140.89005 | E7: ='WEIGHTED AVERAGE COST'!L76 -> 143.64234 | F7: ='WEIGHTED AVERAGE COST'!L104 -> 141.0813 | H7: Weighted average cost (KPRL + KOSF)
G8: =Mombasa!G8 -> 1.16 | H8: 16% VAT Inclusive
C9: Kshs/lt | D9: =$G$10*$G$9*$G$8 -> 0 | E9: =$G$10*$G$9*$G$8 -> 0 | F9: =$G$10*$G$9*$G$8 -> 0 | G9: 0 | H9: % transported through pipeline - Zero for Mombasa
G10: 0 | H10: Pipeline Rate
C11: Kshs/lt | D11: =$G$11*G12*$G$8 -> 0 | E11: =$G$11*G12*$G$8 -> 0 | F11: =$G$11*G12*$G$8 -> 0 | G11: =8.14*G14/1000 -> 0 | H11: Bridging Rate Kshs 0.0814 per litre x distance
G12: 0 | H12: % transported through road
C13: Kshs/lt | D13: =$G$13*D7 -> 0 | E13: =$G$13*E7 -> 0 | F13: =$G$13*F7 -> 0 | G13: 0 | H13: Allowed pipeline losses
G14: 0 | H14: Distance from Source Depot
C15: Kshs/lt | D15: =G15*D7 -> 0.70445024 | E15: =G16*E7 -> 0.43092702 | F15: =G16*F7 -> 0.42324391 | G15: 0.005 | H15: Allowed depot losses. 0.5% for PMS,RMS and 0.3% for AGO,DPK
G16: 0.003
C17: Kshs/lt | D17: =Mombasa!D18 -> 4.204 | E17: =Mombasa!E18 -> 4.174 | F17: =Mombasa!F18 -> 4.174 | H17: Allowed oil marketing company's gross wholesale margin
C19: Kshs/lt | D19: =SUM(D7:D18) -> 145.7985 | E19: =SUM(E7:E18) -> 148.24727 | F19: =SUM(F7:F18) -> 145.67855 | H19: Maximum Wholesale price
C21: Kshs/lt | D21: =Mombasa!D22 -> 8.19 | E21: =Mombasa!E22 -> 8.19 | F21: =Mombasa!F22 -> 8.19 | H21: Allowed retail dealers gross margin
C23: Kshs/lt | D23: =$G$23*$G$8 -> 2.2086944 | E23: =$G$23*$G$8 -> 2.2086944 | F23: =$G$23*$G$8 -> 2.2086944 | G23: ='Delivery >40km-Sept 2013'!E24*I23/1000 -> 1.9040469 | H23: Road distance from Mombasa Depot | I23: 159
C25: Kshs/lt | D25: =D19+D21+D23 -> 156.19719 | E25: =E19+E21+E23 -> 158.64596 | F25: =F19+F21+F23 -> 156.07724 | H25: Maximum retail pump price

Sheet Voi_Price VAT Inclusive
B3: OMC WHOLE-SALE FUEL PRICE BREAK-DOWN INCLUDING VAT
B4: =Mombasa!C4 -> March 15 - April 14, 2023 | C4: Super petrol | E4: Diesel | G4: Kerosene
B5: Item | C5: COST/ PRICE | D5: (INPUT)/ OUTPUT | E5: COST/ PRICE | F5: (INPUT)/ OUTPUT | G5: COST/ PRICE | H5: (INPUT)/ OUTPUT
B6: Landed cost, exclusive of VAT (KShs/Litre) [a+b+c] | C6: =C$7+C$8 -> 90.386689 | E6: =E$7+E$8 -> 103.01178 | G6: =G$7+G$8 -> 105.4031
B7: (a) None VAT-charged costs (KShs/litre) | C7: ='PMS SUMMARY'!D45 -> 89.740845 | E7: ='AGO SUMMARY'!E47 -> 102.43802 | G7: ='DPK SUMMARY'!D44 -> 104.66296
B8: (b) VAT-charged costs (KShs/litre) | C8: ='PMS SUMMARY'!D44 -> 0.6458438 | E8: ='AGO SUMMARY'!E46 -> 0.5737644 | G8: ='DPK SUMMARY'!D43 -> 0.74013888
A9: I. | B9: VATable amount (KShs/Litre) | C9: =C$6 -> 90.386689 | E9: =E$6 -> 103.01178 | G9: =G$6 -> 105.4031
B10: INPUT VAT 2 (on I.) | D10: =-(C9*0.08) -> -7.2309351 | F10: =-(E9*0.08) -> -8.2409425 | H10: =-(G9*0.08) -> -8.4322483
A11: II. | B11: Levies
B12: Excise duty | C12: ='Breakdown for PMS, AGO & DPK'!D19 -> 21.95302 | E12: ='Breakdown for PMS, AGO & DPK'!E19 -> 11.37099 | G12: ='Breakdown for PMS, AGO & DPK'!F19 -> 11.37098
B13: Merchant Shipping Fee | C13: ='PMS SUMMARY'!D46 -> 0.029475332 | E13: ='AGO SUMMARY'!E48 -> 0.033048548 | G13: ='DPK SUMMARY'!D45 -> 0.0014519287
B14: Import Declaration Fee | C14: ='PMS SUMMARY'!D47 -> 3.0336263 | E14: ='AGO SUMMARY'!E49 -> 3.490076 | G14: ='DPK SUMMARY'!D46 -> 3.5235822
B15: Road Maintenance Levy | C15: ='Breakdown for PMS, AGO & DPK'!D20 -> 18 | E15: ='Breakdown for PMS, AGO & DPK'!E20 -> 18 | G15: 0
B16: Anti-adulteration Levy | C16: 0 | E16: 0 | G16: ='Breakdown for PMS, AGO & DPK'!F24 -> 18
B17: Petroleum Development Levy | C17: ='Breakdown for PMS, AGO & DPK'!D21 -> 5.4 | E17: ='Breakdown for PMS, AGO & DPK'!E21 -> 5.4 | G17: ='Breakdown for PMS, AGO & DPK'!F21 -> 0.4
B18: Petroleum Regulatory Levy | C18: ='Breakdown for PMS, AGO & DPK'!D22 -> 0.25 | E18: ='Breakdown for PMS, AGO & DPK'!E22 -> 0.25 | G18: ='Breakdown for PMS, AGO & DPK'!F22 -> 0.25
B19: Railway Development Levy | C19: ='Breakdown for PMS, AGO & DPK'!D23 -> 1.7335008 | E19: ='Breakdown for PMS, AGO & DPK'!E23 -> 1.9943291 | G19: ='Breakdown for PMS, AGO & DPK'!F23 -> 2.0134756
B20: Sub-total | C20: =SUM(C12:C19) -> 50.399622 | E20: =SUM(E12:E19) -> 40.538444 | G20: =SUM(G12:G19) -> 35.55949
A21: III. | B21: Storage and Distribution Costs (Variable/Litre) | C21: =SUM(C$22:C$23) -> 0.70445024 | E21: =SUM(E$22:E$23) -> 0.43092702 | G21: =SUM(G$22:G$23) -> 0.42324391
B22: Storage and Distribution Costs (with VAT) | C22: =SUM(C$24:C$25) -> 0 | E22: =SUM(E$24:E$25) -> 0 | G22: =SUM(G$24:G$25) -> 0
B23: Storage and Distribution Costs (without VAT) | C23: =C$26+C$27 -> 0.70445024 | E23: =E$26+E$27 -> 0.43092702 | G23: =G$26+G$27 -> 0.42324391
B24: Pipeline Transport (Msa) | C24: =Mombasa!D9 -> 0 | E24: =Mombasa!E9 -> 0 | G24: =Mombasa!F9 -> 0
B25: Road Transport (Msa) - Bridging | C25: =Mombasa!D11 -> 0 | E25: =Mombasa!E11 -> 0 | G25: =Mombasa!F11 -> 0
B26: Pipeline Losses | C26: =Mombasa!D13 -> 0 | E26: =Mombasa!E13 -> 0 | G26: =Mombasa!F13 -> 0
B27: Depot Losses | C27: =Mombasa!D15 -> 0.70445024 | E27: =Mombasa!E15 -> 0.43092702 | G27: =Mombasa!F15 -> 0.42324391
A28: IV. | B28: Oil Marketers Margin | C28: =Mombasa!D18 -> 4.204 | E28: =Mombasa!E18 -> 4.174 | G28: =Mombasa!F18 -> 4.174
B29: VATable price [(I)+(III)+(IV)] | C29: =C$9+C$20+C$22+C$23+C$28 -> 145.69476 | E29: =E$9+E$20+E$22+E$23+E$28 -> 148.15515 | G29: =G$9+G$20+G$22+G$23+G$28 -> 145.55984
B30: Output VAT | D30: =CONCATENATE("+ ",ROUND((C$29*0.08),2)) -> + 11.66 | F30: =CONCATENATE("+ ",ROUND((E$29*0.08),2)) -> + 11.85 | H30: =CONCATENATE("+ ",ROUND((G$29*0.08),2)) -> + 11.64
B31: OMC Wholesale price exclusive of VAT | C31: =C$9+C$20+C$21+C$28 -> 145.69476 | E31: =E$9+E$20+E$21+E$28 -> 148.15515 | G31: =G$9+G$20+G$21+G$28 -> 145.55984
B32: ADD: VAT at wholesale | C32: =D30 -> + 11.66 | E32: =F30 -> + 11.85 | G32: =H30 -> + 11.64
B33: Wholesale Price inxclusive of VAT | C33: =C31+C32 -> 157.35476 | D33: =+D10+D30 -> 4.4290649 | E33: =E31+E32 -> 160.00515 | F33: =F10+F30 -> 3.6090575 | G33: =G31+G32 -> 157.19984 | H33: =H10+H30 -> 3.2077517
B35: RETAIL FUEL COST BREAK-DOWN INCLUDING VAT
C36: =C4 -> Super petrol | E36: =E4 -> Diesel | G36: =G4 -> Kerosene
A37: V. | B37: Wholesale price inclusive of VAT | C37: =C33 -> 157.35476 | E37: =E33 -> 160.00515 | G37: =G33 -> 157.19984
B38: Input VAT on Product at retail | D38: =-C32 -> -11.66 | F38: =-E32 -> -11.85 | H38: =-G32 -> -11.64
A39: VI. | B39: Distribution Cost
B40: Delivery Within 40kms | C40: =Voi!G23 -> 1.9040469 | E40: =C40 -> 1.9040469 | G40: =E40 -> 1.9040469
B41: Subtotal | C41: =SUM(C40) -> 1.9040469 | E41: =SUM(E40) -> 1.9040469 | G41: =SUM(G40) -> 1.9040469
A42: VII. | B42: Retailer's Margin | C42: =Mombasa!D22 -> 8.19 | E42: =Mombasa!E22 -> 8.19 | G42: =Mombasa!F22 -> 8.19
B43: Retail price | C43: =C$37+C$42+C$41 -> 167.44881 | E43: =E$37+E$42+E$41 -> 170.0992 | G43: =G$37+G$42+G$41 -> 167.29388
B44: LESS: Levies | C44: 0 | E44: 0 | G44: 0
B45: Non-VATable storage and distribution costs | C45: 0 | E45: 0 | G45: 0
B46: VATable value [(V)+(VI)-Input VAT] | C46: =C$43-C44-C45+D$38 -> 155.78881 | E46: =E$43-E44-E45+F$38 -> 158.2492 | G46: =G$43-G44-G45+H$38 -> 155.65388
B47: Output VAT on product at retail level | D47: =CONCATENATE("+ ",ROUND((C$46*0.08),2)) -> + 12.46 | F47: =CONCATENATE("+ ",ROUND((E$46*0.08),2)) -> + 12.66 | H47: =CONCATENATE("+ ",ROUND((G$46*0.08),2)) -> + 12.45
B48: ADD: VAT at retail | C48: =D47 -> + 12.46 | E48: =F47 -> + 12.66 | G48: =H47 -> + 12.45
B49: Retail Pump-Price under VAT regime | C49: =C$46+C$48+C$44+C$45 -> 168.24881 | D49: =D38+D47 -> 0.8 | E49: =E$46+E$48+E$44+E$45 -> 170.9092 | F49: =F38+F47 -> 0.81 | G49: =G$46+G$48+G$44+G$45 -> 168.10388 | H49: =H38+H47 -> 0.81
A51: EXPECTED IMPACT ON THE FINAL RETAIL PRICE COMPARED TO THE NON-VAT REGIME
B53: ERC PRICE UNDER NON-VAT REGIME | C53: =Mombasa!D26 -> 154.6121 | D53: =C9+C20+C21+C28+C42+0.16*C8+0.16*SUM(C24:C25) -> 153.9881 | E53: ='Breakdown for PMS, AGO & DPK'!E26 -> 160.05845 | G53: ='Breakdown for PMS, AGO & DPK'!F26 -> 157.48856
B54: PRICE DIFFERENCE | C54: =C49-C53 -> 13.636703 | D54: =C53-D53 -> 0.62400843 | E54: =E49-E53 -> 10.850749 | G54: =G49-G53 -> 10.615324
B55: PERCENTAGE INCREAMENT | C55: =C54/C53 -> 0.088199455 | D55: =7-5.55+3.89-3.112 -> 2.228 | E55: =E54/E53 -> 0.067792415 | G55: =G54/G53 -> 0.067403779
B56: GOVERNMENT NET VAT COLLECTION (KSHS PER LITRE) | C56: =D$33+D$49+-$D$10 -> 12.46 | E56: =F$33+F$49 -> 4.4190575 | G56: =H$33+H$49 -> 4.0177517

Sheet Taveta
C2: TAVETA TOWN
C3: Petroleum Costing
C4: =Voi!C4 -> March 15 - April 14, 2023
D6: PMS | E6: AGO | F6: DPK
C7: Kshs/lt | D7: ='WEIGHTED AVERAGE COST'!L40 -> 140.89005 | E7: ='WEIGHTED AVERAGE COST'!L76 -> 143.64234 | F7: ='WEIGHTED AVERAGE COST'!L104 -> 141.0813 | H7: Weighted average cost (KPRL + KOSF)
G8: =Mombasa!G8 -> 1.16 | H8: 16% VAT Inclusive
C9: Kshs/lt | D9: =$G$10*$G$9*$G$8 -> 0 | E9: =$G$10*$G$9*$G$8 -> 0 | F9: =$G$10*$G$9*$G$8 -> 0 | G9: 0 | H9: % transported through pipeline - Zero for Mombasa
G10: 0 | H10: Pipeline Rate
C11: Kshs/lt | D11: =$G$11*G12*$G$8 -> 0 | E11: =$G$11*G12*$G$8 -> 0 | F11: =$G$11*G12*$G$8 -> 0 | G11: =8.14*G14/1000 -> 0 | H11: Bridging Rate Kshs 0.0814 per litre x distance
G12: =1-G9 -> 1 | H12: % transported through road
C13: Kshs/lt | D13: =$G$13*D7 -> 0 | E13: =$G$13*E7 -> 0 | F13: =$G$13*F7 -> 0 | G13: 0 | H13: Allowed pipeline losses
G14: 0 | H14: Distance from Source Depot
C15: Kshs/lt | D15: =G15*D7 -> 0.70445024 | E15: =G16*E7 -> 0.43092702 | F15: =G16*F7 -> 0.42324391 | G15: 0.005 | H15: Allowed depot losses. 0.5% for PMS,RMS and 0.3% for AGO,DPK
G16: 0.003
C17: Kshs/lt | D17: =Mombasa!D18 -> 4.204 | E17: =Mombasa!E18 -> 4.174 | F17: =Mombasa!F18 -> 4.174 | H17: Allowed oil marketing company's gross wholesale margin
C19: Kshs/lt | D19: =SUM(D7:D18) -> 145.7985 | E19: =SUM(E7:E18) -> 148.24727 | F19: =SUM(F7:F18) -> 145.67855 | H19: Maximum Wholesale price
C21: Kshs/lt | D21: =Mombasa!D22 -> 8.19 | E21: =Mombasa!E22 -> 8.19 | F21: =Mombasa!F22 -> 8.19 | H21: Allowed retail dealers gross margin
C23: Kshs/lt | D23: =$G$23*$G$8 -> 3.7228308 | E23: =$G$23*$G$8 -> 3.7228308 | F23: =$G$23*$G$8 -> 3.7228308 | G23: ='Delivery >40km-Sept 2013'!E24*I23/1000 -> 3.2093369 | H23: Road distance from Mombasa Depot | I23: 268
C25: Kshs/lt | D25: =D19+D21+D23 -> 157.71133 | E25: =E19+E21+E23 -> 160.1601 | F25: =F19+F21+F23 -> 157.59138 | H25: Maximum retail pump price

Sheet Taveta_Price VAT Inclusive
B3: OMC WHOLE-SALE FUEL PRICE BREAK-DOWN INCLUDING VAT
B4: =Mombasa!C4 -> March 15 - April 14, 2023 | C4: Super petrol | E4: Diesel | G4: Kerosene
B5: Item | C5: COST/ PRICE | D5: (INPUT)/ OUTPUT | E5: COST/ PRICE | F5: (INPUT)/ OUTPUT | G5: COST/ PRICE | H5: (INPUT)/ OUTPUT
B6: Landed cost, exclusive of VAT (KShs/Litre) [a+b+c] | C6: =C$7+C$8 -> 90.386689 | E6: =E$7+E$8 -> 103.01178 | G6: =G$7+G$8 -> 105.4031
B7: (a) None VAT-charged costs (KShs/litre) | C7: ='PMS SUMMARY'!D45 -> 89.740845 | E7: ='AGO SUMMARY'!E47 -> 102.43802 | G7: ='DPK SUMMARY'!D44 -> 104.66296
B8: (b) VAT-charged costs (KShs/litre) | C8: ='PMS SUMMARY'!D44 -> 0.6458438 | E8: ='AGO SUMMARY'!E46 -> 0.5737644 | G8: ='DPK SUMMARY'!D43 -> 0.74013888
A9: I. | B9: VATable amount (KShs/Litre) | C9: =C$6 -> 90.386689 | E9: =E$6 -> 103.01178 | G9: =G$6 -> 105.4031
B10: INPUT VAT 2 (on I.) | D10: =-(C9*0.08) -> -7.2309351 | F10: =-(E9*0.08) -> -8.2409425 | H10: =-(G9*0.08) -> -8.4322483
A11: II. | B11: Levies
B12: Excise duty | C12: ='Breakdown for PMS, AGO & DPK'!D19 -> 21.95302 | E12: ='Breakdown for PMS, AGO & DPK'!E19 -> 11.37099 | G12: ='Breakdown for PMS, AGO & DPK'!F19 -> 11.37098
B13: Merchant Shipping Fee | C13: ='PMS SUMMARY'!D46 -> 0.029475332 | E13: ='AGO SUMMARY'!E48 -> 0.033048548 | G13: ='DPK SUMMARY'!D45 -> 0.0014519287
B14: Import Declaration Fee | C14: ='PMS SUMMARY'!D47 -> 3.0336263 | E14: ='AGO SUMMARY'!E49 -> 3.490076 | G14: ='DPK SUMMARY'!D46 -> 3.5235822
B15: Road Maintenance Levy | C15: ='Breakdown for PMS, AGO & DPK'!D20 -> 18 | E15: ='Breakdown for PMS, AGO & DPK'!E20 -> 18 | G15: 0
B16: Anti-adulteration Levy | C16: 0 | E16: 0 | G16: ='Breakdown for PMS, AGO & DPK'!F24 -> 18
B17: Petroleum Development Levy | C17: ='Breakdown for PMS, AGO & DPK'!D21 -> 5.4 | E17: ='Breakdown for PMS, AGO & DPK'!E21 -> 5.4 | G17: ='Breakdown for PMS, AGO & DPK'!F21 -> 0.4
B18: Petroleum Regulatory Levy | C18: ='Breakdown for PMS, AGO & DPK'!D22 -> 0.25 | E18: ='Breakdown for PMS, AGO & DPK'!E22 -> 0.25 | G18: ='Breakdown for PMS, AGO & DPK'!F22 -> 0.25
B19: Railway Development Levy | C19: ='Breakdown for PMS, AGO & DPK'!D23 -> 1.7335008 | E19: ='Breakdown for PMS, AGO & DPK'!E23 -> 1.9943291 | G19: ='Breakdown for PMS, AGO & DPK'!F23 -> 2.0134756
B20: Sub-total | C20: =SUM(C12:C19) -> 50.399622 | E20: =SUM(E12:E19) -> 40.538444 | G20: =SUM(G12:G19) -> 35.55949
A21: III. | B21: Storage and Distribution Costs (Variable/Litre) | C21: =SUM(C$22:C$23) -> 0.70445024 | E21: =SUM(E$22:E$23) -> 0.43092702 | G21: =SUM(G$22:G$23) -> 0.42324391
B22: Storage and Distribution Costs (with VAT) | C22: =SUM(C$24:C$25) -> 0 | E22: =SUM(E$24:E$25) -> 0 | G22: =SUM(G$24:G$25) -> 0
B23: Storage and Distribution Costs (without VAT) | C23: =C$26+C$27 -> 0.70445024 | E23: =E$26+E$27 -> 0.43092702 | G23: =G$26+G$27 -> 0.42324391
B24: Pipeline Transport (Msa) | C24: =Mombasa!D9 -> 0 | E24: =Mombasa!E9 -> 0 | G24: =Mombasa!F9 -> 0
B25: Road Transport (Msa) - Bridging | C25: =Mombasa!D11 -> 0 | E25: =Mombasa!E11 -> 0 | G25: =Mombasa!F11 -> 0
B26: Pipeline Losses | C26: =Mombasa!D13 -> 0 | E26: =Mombasa!E13 -> 0 | G26: =Mombasa!F13 -> 0
B27: Depot Losses | C27: =Mombasa!D15 -> 0.70445024 | E27: =Mombasa!E15 -> 0.43092702 | G27: =Mombasa!F15 -> 0.42324391
A28: IV. | B28: Oil Marketers Margin | C28: =Mombasa!D18 -> 4.204 | E28: =Mombasa!E18 -> 4.174 | G28: =Mombasa!F18 -> 4.174
B29: VATable price [(I)+(III)+(IV)] | C29: =C$9+C$20+C$22+C$23+C$28 -> 145.69476 | E29: =E$9+E$20+E$22+E$23+E$28 -> 148.15515 | G29: =G$9+G$20+G$22+G$23+G$28 -> 145.55984
B30: Output VAT | D30: =CONCATENATE("+ ",ROUND((C$29*0.08),2)) -> + 11.66 | F30: =CONCATENATE("+ ",ROUND((E$29*0.08),2)) -> + 11.85 | H30: =CONCATENATE("+ ",ROUND((G$29*0.08),2)) -> + 11.64
B31: OMC Wholesale price exclusive of VAT | C31: =C$9+C$20+C$21+C$28 -> 145.69476 | E31: =E$9+E$20+E$21+E$28 -> 148.15515 | G31: =G$9+G$20+G$21+G$28 -> 145.55984
B32: ADD: VAT at wholesale | C32: =D30 -> + 11.66 | E32: =F30 -> + 11.85 | G32: =H30 -> + 11.64
B33: Wholesale Price inxclusive of VAT | C33: =C31+C32 -> 157.35476 | D33: =+D10+D30 -> 4.4290649 | E33: =E31+E32 -> 160.00515 | F33: =F10+F30 -> 3.6090575 | G33: =G31+G32 -> 157.19984 | H33: =H10+H30 -> 3.2077517
B35: RETAIL FUEL COST BREAK-DOWN INCLUDING VAT
C36: =C4 -> Super petrol | E36: =E4 -> Diesel | G36: =G4 -> Kerosene
A37: V. | B37: Wholesale price inclusive of VAT | C37: =C33 -> 157.35476 | E37: =E33 -> 160.00515 | G37: =G33 -> 157.19984
B38: Input VAT on Product at retail | D38: =-C32 -> -11.66 | F38: =-E32 -> -11.85 | H38: =-G32 -> -11.64
A39: VI. | B39: Distribution Cost
B40: Delivery Within 40kms | C40: =Taveta!G23 -> 3.2093369 | E40: =C40 -> 3.2093369 | G40: =E40 -> 3.2093369
B41: Subtotal | C41: =SUM(C40) -> 3.2093369 | E41: =SUM(E40) -> 3.2093369 | G41: =SUM(G40) -> 3.2093369
A42: VII. | B42: Retailer's Margin | C42: =Mombasa!D22 -> 8.19 | E42: =Mombasa!E22 -> 8.19 | G42: =Mombasa!F22 -> 8.19
B43: Retail price | C43: =C$37+C$42+C$41 -> 168.7541 | E43: =E$37+E$42+E$41 -> 171.40449 | G43: =G$37+G$42+G$41 -> 168.59917
B44: LESS: Levies | C44: 0 | E44: 0 | G44: 0
B45: Non-VATable storage and distribution costs | C45: 0 | E45: 0 | G45: 0
B46: VATable value [(V)+(VI)-Input VAT] | C46: =C$43-C44-C45+D$38 -> 157.0941 | E46: =E$43-E44-E45+F$38 -> 159.55449 | G46: =G$43-G44-G45+H$38 -> 156.95917
B47: Output VAT on product at retail level | D47: =CONCATENATE("+ ",ROUND((C$46*0.08),2)) -> + 12.57 | F47: =CONCATENATE("+ ",ROUND((E$46*0.08),2)) -> + 12.76 | H47: =CONCATENATE("+ ",ROUND((G$46*0.08),2)) -> + 12.56
B48: ADD: VAT at retail | C48: =D47 -> + 12.57 | E48: =F47 -> + 12.76 | G48: =H47 -> + 12.56
B49: Retail Pump-Price under VAT regime | C49: =C$46+C$48+C$44+C$45 -> 169.6641 | D49: =D38+D47 -> 0.91 | E49: =E$46+E$48+E$44+E$45 -> 172.31449 | F49: =F38+F47 -> 0.91 | G49: =G$46+G$48+G$44+G$45 -> 169.51917 | H49: =H38+H47 -> 0.92
A51: EXPECTED IMPACT ON THE FINAL RETAIL PRICE COMPARED TO THE NON-VAT REGIME
B53: ERC PRICE UNDER NON-VAT REGIME | C53: =Mombasa!D26 -> 154.6121 | D53: =C9+C20+C21+C28+C42+0.16*C8+0.16*SUM(C24:C25) -> 153.9881 | E53: ='Breakdown for PMS, AGO & DPK'!E26 -> 160.05845 | G53: ='Breakdown for PMS, AGO & DPK'!F26 -> 157.48856
B54: PRICE DIFFERENCE | C54: =C49-C53 -> 15.051993 | D54: =C53-D53 -> 0.62400843 | E54: =E49-E53 -> 12.256039 | G54: =G49-G53 -> 12.030614
B55: PERCENTAGE INCREAMENT | C55: =C54/C53 -> 0.097353266 | D55: =7-5.55+3.89-3.112 -> 2.228 | E55: =E54/E53 -> 0.07657227 | G55: =G54/G53 -> 0.0763904
B56: GOVERNMENT NET VAT COLLECTION (KSHS PER LITRE) | C56: =D$33+D$49+-$D$10 -> 12.57 | E56: =F$33+F$49 -> 4.5190575 | G56: =H$33+H$49 -> 4.1277517

Sheet Lamu
C2: LAMU TOWN
C3: Petroleum Costing
C4: =Taveta!C4 -> March 15 - April 14, 2023
D6: PMS | E6: AGO | F6: DPK
C7: Kshs/lt | D7: ='WEIGHTED AVERAGE COST'!L40 -> 140.89005 | E7: ='WEIGHTED AVERAGE COST'!L76 -> 143.64234 | F7: ='WEIGHTED AVERAGE COST'!L104 -> 141.0813 | H7: Weighted average cost (KPRL + KOSF)
G8: =Mombasa!G8 -> 1.16 | H8: 16% VAT Inclusive
C9: Kshs/lt | D9: =$G$10*$G$9*$G$8 -> 0 | E9: =$G$10*$G$9*$G$8 -> 0 | F9: =$G$10*$G$9*$G$8 -> 0 | G9: 0 | H9: % transported through pipeline - Zero for Mombasa
G10: 0 | H10: Pipeline Rate
C11: Kshs/lt | D11: =$G$11*G12*$G$8 -> 0 | E11: =$G$11*G12*$G$8 -> 0 | F11: =$G$11*G12*$G$8 -> 0 | G11: =8.14*G14/1000 -> 0 | H11: Bridging Rate Kshs 0.0814 per litre x distance
G12: =1-G9 -> 1 | H12: % transported through road
C13: Kshs/lt | D13: =$G$13*D7 -> 0 | E13: =$G$13*E7 -> 0 | F13: =$G$13*F7 -> 0 | G13: 0 | H13: Allowed pipeline losses
G14: 0 | H14: Distance from Source Depot
C15: Kshs/lt | D15: =G15*D7 -> 0.70445024 | E15: =G16*E7 -> 0.43092702 | F15: =G16*F7 -> 0.42324391 | G15: 0.005 | H15: Allowed depot losses. 0.5% for PMS,RMS and 0.3% for AGO,DPK
G16: 0.003
C17: Kshs/lt | D17: =Mombasa!D18 -> 4.204 | E17: =Mombasa!E18 -> 4.174 | F17: =Mombasa!F18 -> 4.174 | H17: Allowed oil marketing company's gross wholesale margin
C19: Kshs/lt | D19: =SUM(D7:D18) -> 145.7985 | E19: =SUM(E7:E18) -> 148.24727 | F19: =SUM(F7:F18) -> 145.67855 | H19: Maximum Wholesale price
C21: Kshs/lt | D21: =Mombasa!D22 -> 8.19 | E21: =Mombasa!E22 -> 8.19 | F21: =Mombasa!F22 -> 8.19 | H21: Allowed retail dealers gross margin
C23: Kshs/lt | D23: =$G$23*$G$8 -> 4.1673479 | E23: =$G$23*$G$8 -> 4.1673479 | F23: =$G$23*$G$8 -> 4.1673479 | G23: ='Delivery >40km-Sept 2013'!E24*I23/1000 -> 3.5925413 | H23: Road distance from Mombasa Depot | I23: 300
C25: Kshs/lt | D25: =D19+D21+D23 -> 158.15585 | E25: =E19+E21+E23 -> 160.60462 | F25: =F19+F21+F23 -> 158.03589 | H25: Maximum retail pump price

Sheet Lamu_Price VAT Inclusive
B3: OMC WHOLE-SALE FUEL PRICE BREAK-DOWN INCLUDING VAT
B4: =Mombasa!C4 -> March 15 - April 14, 2023 | C4: Super petrol | E4: Diesel | G4: Kerosene
B5: Item | C5: COST/ PRICE | D5: (INPUT)/ OUTPUT | E5: COST/ PRICE | F5: (INPUT)/ OUTPUT | G5: COST/ PRICE | H5: (INPUT)/ OUTPUT
B6: Landed cost, exclusive of VAT (KShs/Litre) [a+b+c] | C6: =C$7+C$8 -> 90.386689 | E6: =E$7+E$8 -> 103.01178 | G6: =G$7+G$8 -> 105.4031
B7: (a) None VAT-charged costs (KShs/litre) | C7: ='PMS SUMMARY'!D45 -> 89.740845 | E7: ='AGO SUMMARY'!E47 -> 102.43802 | G7: ='DPK SUMMARY'!D44 -> 104.66296
B8: (b) VAT-charged costs (KShs/litre) | C8: ='PMS SUMMARY'!D44 -> 0.6458438 | E8: ='AGO SUMMARY'!E46 -> 0.5737644 | G8: ='DPK SUMMARY'!D43 -> 0.74013888
A9: I. | B9: VATable amount (KShs/Litre) | C9: =C$6 -> 90.386689 | E9: =E$6 -> 103.01178 | G9: =G$6 -> 105.4031
B10: INPUT VAT 2 (on I.) | D10: =-(C9*0.08) -> -7.2309351 | F10: =-(E9*0.08) -> -8.2409425 | H10: =-(G9*0.08) -> -8.4322483
A11: II. | B11: Levies
B12: Excise duty | C12: ='Breakdown for PMS, AGO & DPK'!D19 -> 21.95302 | E12: ='Breakdown for PMS, AGO & DPK'!E19 -> 11.37099 | G12: ='Breakdown for PMS, AGO & DPK'!F19 -> 11.37098
B13: Merchant Shipping Fee | C13: ='PMS SUMMARY'!D46 -> 0.029475332 | E13: ='AGO SUMMARY'!E48 -> 0.033048548 | G13: ='DPK SUMMARY'!D45 -> 0.0014519287
B14: Import Declaration Fee | C14: ='PMS SUMMARY'!D47 -> 3.0336263 | E14: ='AGO SUMMARY'!E49 -> 3.490076 | G14: ='DPK SUMMARY'!D46 -> 3.5235822
B15: Road Maintenance Levy | C15: ='Breakdown for PMS, AGO & DPK'!D20 -> 18 | E15: ='Breakdown for PMS, AGO & DPK'!E20 -> 18 | G15: 0
B16: Anti-adulteration Levy | C16: 0 | E16: 0 | G16: ='Breakdown for PMS, AGO & DPK'!F24 -> 18
B17: Petroleum Development Levy | C17: ='Breakdown for PMS, AGO & DPK'!D21 -> 5.4 | E17: ='Breakdown for PMS, AGO & DPK'!E21 -> 5.4 | G17: ='Breakdown for PMS, AGO & DPK'!F21 -> 0.4
B18: Petroleum Regulatory Levy | C18: ='Breakdown for PMS, AGO & DPK'!D22 -> 0.25 | E18: ='Breakdown for PMS, AGO & DPK'!E22 -> 0.25 | G18: ='Breakdown for PMS, AGO & DPK'!F22 -> 0.25
B19: Railway Development Levy | C19: ='Breakdown for PMS, AGO & DPK'!D23 -> 1.7335008 | E19: ='Breakdown for PMS, AGO & DPK'!E23 -> 1.9943291 | G19: ='Breakdown for PMS, AGO & DPK'!F23 -> 2.0134756
B20: Sub-total | C20: =SUM(C12:C19) -> 50.399622 | E20: =SUM(E12:E19) -> 40.538444 | G20: =SUM(G12:G19) -> 35.55949
A21: III. | B21: Storage and Distribution Costs (Variable/Litre) | C21: =SUM(C$22:C$23) -> 0.70445024 | E21: =SUM(E$22:E$23) -> 0.43092702 | G21: =SUM(G$22:G$23) -> 0.42324391
B22: Storage and Distribution Costs (with VAT) | C22: =SUM(C$24:C$25) -> 0 | E22: =SUM(E$24:E$25) -> 0 | G22: =SUM(G$24:G$25) -> 0
B23: Storage and Distribution Costs (without VAT) | C23: =C$26+C$27 -> 0.70445024 | E23: =E$26+E$27 -> 0.43092702 | G23: =G$26+G$27 -> 0.42324391
B24: Pipeline Transport (Msa) | C24: =Mombasa!D9 -> 0 | E24: =Mombasa!E9 -> 0 | G24: =Mombasa!F9 -> 0
B25: Road Transport (Msa) - Bridging | C25: =Mombasa!D11 -> 0 | E25: =Mombasa!E11 -> 0 | G25: =Mombasa!F11 -> 0
B26: Pipeline Losses | C26: =Mombasa!D13 -> 0 | E26: =Mombasa!E13 -> 0 | G26: =Mombasa!F13 -> 0
B27: Depot Losses | C27: =Mombasa!D15 -> 0.70445024 | E27: =Mombasa!E15 -> 0.43092702 | G27: =Mombasa!F15 -> 0.42324391
A28: IV. | B28: Oil Marketers Margin | C28: =Mombasa!D18 -> 4.204 | E28: =Mombasa!E18 -> 4.174 | G28: =Mombasa!F18 -> 4.174
B29: VATable price [(I)+(III)+(IV)] | C29: =C$9+C$20+C$22+C$23+C$28 -> 145.69476 | E29: =E$9+E$20+E$22+E$23+E$28 -> 148.15515 | G29: =G$9+G$20+G$22+G$23+G$28 -> 145.55984
B30: Output VAT | D30: =CONCATENATE("+ ",ROUND((C$29*0.08),2)) -> + 11.66 | F30: =CONCATENATE("+ ",ROUND((E$29*0.08),2)) -> + 11.85 | H30: =CONCATENATE("+ ",ROUND((G$29*0.08),2)) -> + 11.64
B31: OMC Wholesale price exclusive of VAT | C31: =C$9+C$20+C$21+C$28 -> 145.69476 | E31: =E$9+E$20+E$21+E$28 -> 148.15515 | G31: =G$9+G$20+G$21+G$28 -> 145.55984
B32: ADD: VAT at wholesale | C32: =D30 -> + 11.66 | E32: =F30 -> + 11.85 | G32: =H30 -> + 11.64
B33: Wholesale Price inxclusive of VAT | C33: =C31+C32 -> 157.35476 | D33: =+D10+D30 -> 4.4290649 | E33: =E31+E32 -> 160.00515 | F33: =F10+F30 -> 3.6090575 | G33: =G31+G32 -> 157.19984 | H33: =H10+H30 -> 3.2077517
B35: RETAIL FUEL COST BREAK-DOWN INCLUDING VAT
C36: =C4 -> Super petrol | E36: =E4 -> Diesel | G36: =G4 -> Kerosene
A37: V. | B37: Wholesale price inclusive of VAT | C37: =C33 -> 157.35476 | E37: =E33 -> 160.00515 | G37: =G33 -> 157.19984
B38: Input VAT on Product at retail | D38: =-C32 -> -11.66 | F38: =-E32 -> -11.85 | H38: =-G32 -> -11.64
A39: VI. | B39: Distribution Cost
B40: Delivery Within 40kms | C40: =Lamu!G23 -> 3.5925413 | E40: =C40 -> 3.5925413 | G40: =E40 -> 3.5925413
B41: Subtotal | C41: =SUM(C40) -> 3.5925413 | E41: =SUM(E40) -> 3.5925413 | G41: =SUM(G40) -> 3.5925413
A42: VII. | B42: Retailer's Margin | C42: =Mombasa!D22 -> 8.19 | E42: =Mombasa!E22 -> 8.19 | G42: =Mombasa!F22 -> 8.19
B43: Retail price | C43: =C$37+C$42+C$41 -> 169.1373 | E43: =E$37+E$42+E$41 -> 171.78769 | G43: =G$37+G$42+G$41 -> 168.98238
B44: LESS: Levies | C44: 0 | E44: 0 | G44: 0
B45: Non-VATable storage and distribution costs | C45: 0 | E45: 0 | G45: 0
B46: VATable value [(V)+(VI)-Input VAT] | C46: =C$43-C44-C45+D$38 -> 157.4773 | E46: =E$43-E44-E45+F$38 -> 159.93769 | G46: =G$43-G44-G45+H$38 -> 157.34238
B47: Output VAT on product at retail level | D47: =CONCATENATE("+ ",ROUND((C$46*0.08),2)) -> + 12.6 | F47: =CONCATENATE("+ ",ROUND((E$46*0.08),2)) -> + 12.8 | H47: =CONCATENATE("+ ",ROUND((G$46*0.08),2)) -> + 12.59
B48: ADD: VAT at retail | C48: =D47 -> + 12.6 | E48: =F47 -> + 12.8 | G48: =H47 -> + 12.59
B49: Retail Pump-Price under VAT regime | C49: =C$46+C$48+C$44+C$45 -> 170.0773 | D49: =D38+D47 -> 0.94 | E49: =E$46+E$48+E$44+E$45 -> 172.73769 | F49: =F38+F47 -> 0.95 | G49: =G$46+G$48+G$44+G$45 -> 169.93238 | H49: =H38+H47 -> 0.95
A51: EXPECTED IMPACT ON THE FINAL RETAIL PRICE COMPARED TO THE NON-VAT REGIME
B53: ERC PRICE UNDER NON-VAT REGIME | C53: =Mombasa!D26 -> 154.6121 | D53: =C9+C20+C21+C28+C42+0.16*C8+0.16*SUM(C24:C25) -> 153.9881 | E53: ='Breakdown for PMS, AGO & DPK'!E26 -> 160.05845 | G53: ='Breakdown for PMS, AGO & DPK'!F26 -> 157.48856
B54: PRICE DIFFERENCE | C54: =C49-C53 -> 15.465198 | D54: =C53-D53 -> 0.62400843 | E54: =E49-E53 -> 12.679243 | G54: =G49-G53 -> 12.443818
B55: PERCENTAGE INCREAMENT | C55: =C54/C53 -> 0.10002579 | D55: =7-5.55+3.89-3.112 -> 2.228 | E55: =E54/E53 -> 0.079216331 | G55: =G54/G53 -> 0.079014111
B56: GOVERNMENT NET VAT COLLECTION (KSHS PER LITRE) | C56: =D$33+D$49+-$D$10 -> 12.6 | E56: =F$33+F$49 -> 4.5590575 | G56: =H$33+H$49 -> 4.1577517

Sheet Hola
C2: LAMU TOWN
C3: Petroleum Costing
C4: =Taveta!C4 -> March 15 - April 14, 2023
D6: PMS | E6: AGO | F6: DPK
C7: Kshs/lt | D7: ='WEIGHTED AVERAGE COST'!L40 -> 140.89005 | E7: ='WEIGHTED AVERAGE COST'!L76 -> 143.64234 | F7: ='WEIGHTED AVERAGE COST'!L104 -> 141.0813 | H7: Weighted average cost (KPRL + KOSF)
G8: =Mombasa!G8 -> 1.16 | H8: 16% VAT Inclusive
C9: Kshs/lt | D9: =$G$10*$G$9*$G$8 -> 0 | E9: =$G$10*$G$9*$G$8 -> 0 | F9: =$G$10*$G$9*$G$8 -> 0 | G9: 0 | H9: % transported through pipeline - Zero for Mombasa
G10: 0 | H10: Pipeline Rate
C11: Kshs/lt | D11: =$G$11*G12*$G$8 -> 0 | E11: =$G$11*G12*$G$8 -> 0 | F11: =$G$11*G12*$G$8 -> 0 | G11: =8.14*G14/1000 -> 0 | H11: Bridging Rate Kshs 0.0814 per litre x distance
G12: =1-G9 -> 1 | H12: % transported through road
C13: Kshs/lt | D13: =$G$13*D7 -> 0 | E13: =$G$13*E7 -> 0 | F13: =$G$13*F7 -> 0 | G13: 0 | H13: Allowed pipeline losses
G14: 0 | H14: Distance from Source Depot
C15: Kshs/lt | D15: =G15*D7 -> 0.70445024 | E15: =G16*E7 -> 0.43092702 | F15: =G16*F7 -> 0.42324391 | G15: 0.005 | H15: Allowed depot losses. 0.5% for PMS,RMS and 0.3% for AGO,DPK
G16: 0.003
C17: Kshs/lt | D17: =Mombasa!D18 -> 4.204 | E17: =Mombasa!E18 -> 4.174 | F17: =Mombasa!F18 -> 4.174 | H17: Allowed oil marketing company's gross wholesale margin
C19: Kshs/lt | D19: =SUM(D7:D18) -> 145.7985 | E19: =SUM(E7:E18) -> 148.24727 | F19: =SUM(F7:F18) -> 145.67855 | H19: Maximum Wholesale price
C21: Kshs/lt | D21: =Mombasa!D22 -> 8.19 | E21: =Mombasa!E22 -> 8.19 | F21: =Mombasa!F22 -> 8.19 | H21: Allowed retail dealers gross margin
C23: Kshs/lt | D23: =$G$23*$G$8 -> 4.4729534 | E23: =$G$23*$G$8 -> 4.4729534 | F23: =$G$23*$G$8 -> 4.4729534 | G23: ='Delivery >40km-Sept 2013'!E24*I23/1000 -> 3.8559943 | H23: Road distance from Mombasa Depot | I23: 322
C25: Kshs/lt | D25: =D19+D21+D23 -> 158.46145 | E25: =E19+E21+E23 -> 160.91022 | F25: =F19+F21+F23 -> 158.3415 | H25: Maximum retail pump price

Sheet Hola_Price VAT Inclusive
B3: OMC WHOLE-SALE FUEL PRICE BREAK-DOWN INCLUDING VAT
B4: =Mombasa!C4 -> March 15 - April 14, 2023 | C4: Super petrol | E4: Diesel | G4: Kerosene
B5: Item | C5: COST/ PRICE | D5: (INPUT)/ OUTPUT | E5: COST/ PRICE | F5: (INPUT)/ OUTPUT | G5: COST/ PRICE | H5: (INPUT)/ OUTPUT
B6: Landed cost, exclusive of VAT (KShs/Litre) [a+b+c] | C6: =C$7+C$8 -> 90.386689 | E6: =E$7+E$8 -> 103.01178 | G6: =G$7+G$8 -> 105.4031
B7: (a) None VAT-charged costs (KShs/litre) | C7: ='PMS SUMMARY'!D45 -> 89.740845 | E7: ='AGO SUMMARY'!E47 -> 102.43802 | G7: ='DPK SUMMARY'!D44 -> 104.66296
B8: (b) VAT-charged costs (KShs/litre) | C8: ='PMS SUMMARY'!D44 -> 0.6458438 | E8: ='AGO SUMMARY'!E46 -> 0.5737644 | G8: ='DPK SUMMARY'!D43 -> 0.74013888
A9: I. | B9: VATable amount (KShs/Litre) | C9: =C$6 -> 90.386689 | E9: =E$6 -> 103.01178 | G9: =G$6 -> 105.4031
B10: INPUT VAT 2 (on I.) | D10: =-(C9*0.08) -> -7.2309351 | F10: =-(E9*0.08) -> -8.2409425 | H10: =-(G9*0.08) -> -8.4322483
A11: II. | B11: Levies
B12: Excise duty | C12: ='Breakdown for PMS, AGO & DPK'!D19 -> 21.95302 | E12: ='Breakdown for PMS, AGO & DPK'!E19 -> 11.37099 | G12: ='Breakdown for PMS, AGO & DPK'!F19 -> 11.37098
B13: Merchant Shipping Fee | C13: ='PMS SUMMARY'!D46 -> 0.029475332 | E13: ='AGO SUMMARY'!E48 -> 0.033048548 | G13: ='DPK SUMMARY'!D45 -> 0.0014519287
B14: Import Declaration Fee | C14: ='PMS SUMMARY'!D47 -> 3.0336263 | E14: ='AGO SUMMARY'!E49 -> 3.490076 | G14: ='DPK SUMMARY'!D46 -> 3.5235822
B15: Road Maintenance Levy | C15: ='Breakdown for PMS, AGO & DPK'!D20 -> 18 | E15: ='Breakdown for PMS, AGO & DPK'!E20 -> 18 | G15: 0
B16: Anti-adulteration Levy | C16: 0 | E16: 0 | G16: ='Breakdown for PMS, AGO & DPK'!F24 -> 18
B17: Petroleum Development Levy | C17: ='Breakdown for PMS, AGO & DPK'!D21 -> 5.4 | E17: ='Breakdown for PMS, AGO & DPK'!E21 -> 5.4 | G17: ='Breakdown for PMS, AGO & DPK'!F21 -> 0.4
B18: Petroleum Regulatory Levy | C18: ='Breakdown for PMS, AGO & DPK'!D22 -> 0.25 | E18: ='Breakdown for PMS, AGO & DPK'!E22 -> 0.25 | G18: ='Breakdown for PMS, AGO & DPK'!F22 -> 0.25
B19: Railway Development Levy | C19: ='Breakdown for PMS, AGO & DPK'!D23 -> 1.7335008 | E19: ='Breakdown for PMS, AGO & DPK'!E23 -> 1.9943291 | G19: ='Breakdown for PMS, AGO & DPK'!F23 -> 2.0134756
B20: Sub-total | C20: =SUM(C12:C19) -> 50.399622 | E20: =SUM(E12:E19) -> 40.538444 | G20: =SUM(G12:G19) -> 35.55949
A21: III. | B21: Storage and Distribution Costs (Variable/Litre) | C21: =SUM(C$22:C$23) -> 0.70445024 | E21: =SUM(E$22:E$23) -> 0.43092702 | G21: =SUM(G$22:G$23) -> 0.42324391
B22: Storage and Distribution Costs (with VAT) | C22: =SUM(C$24:C$25) -> 0 | E22: =SUM(E$24:E$25) -> 0 | G22: =SUM(G$24:G$25) -> 0
B23: Storage and Distribution Costs (without VAT) | C23: =C$26+C$27 -> 0.70445024 | E23: =E$26+E$27 -> 0.43092702 | G23: =G$26+G$27 -> 0.42324391
B24: Pipeline Transport (Msa) | C24: =Mombasa!D9 -> 0 | E24: =Mombasa!E9 -> 0 | G24: =Mombasa!F9 -> 0
B25: Road Transport (Msa) - Bridging | C25: =Mombasa!D11 -> 0 | E25: =Mombasa!E11 -> 0 | G25: =Mombasa!F11 -> 0
B26: Pipeline Losses | C26: =Mombasa!D13 -> 0 | E26: =Mombasa!E13 -> 0 | G26: =Mombasa!F13 -> 0
B27: Depot Losses | C27: =Mombasa!D15 -> 0.70445024 | E27: =Mombasa!E15 -> 0.43092702 | G27: =Mombasa!F15 -> 0.42324391
A28: IV. | B28: Oil Marketers Margin | C28: =Mombasa!D18 -> 4.204 | E28: =Mombasa!E18 -> 4.174 | G28: =Mombasa!F18 -> 4.174
B29: VATable price [(I)+(III)+(IV)] | C29: =C$9+C$20+C$22+C$23+C$28 -> 145.69476 | E29: =E$9+E$20+E$22+E$23+E$28 -> 148.15515 | G29: =G$9+G$20+G$22+G$23+G$28 -> 145.55984
B30: Output VAT | D30: =CONCATENATE("+ ",ROUND((C$29*0.08),2)) -> + 11.66 | F30: =CONCATENATE("+ ",ROUND((E$29*0.08),2)) -> + 11.85 | H30: =CONCATENATE("+ ",ROUND((G$29*0.08),2)) -> + 11.64
B31: OMC Wholesale price exclusive of VAT | C31: =C$9+C$20+C$21+C$28 -> 145.69476 | E31: =E$9+E$20+E$21+E$28 -> 148.15515 | G31: =G$9+G$20+G$21+G$28 -> 145.55984
B32: ADD: VAT at wholesale | C32: =D30 -> + 11.66 | E32: =F30 -> + 11.85 | G32: =H30 -> + 11.64
B33: Wholesale Price inxclusive of VAT | C33: =C31+C32 -> 157.35476 | D33: =+D10+D30 -> 4.4290649 | E33: =E31+E32 -> 160.00515 | F33: =F10+F30 -> 3.6090575 | G33: =G31+G32 -> 157.19984 | H33: =H10+H30 -> 3.2077517
B35: RETAIL FUEL COST BREAK-DOWN INCLUDING VAT
C36: =C4 -> Super petrol | E36: =E4 -> Diesel | G36: =G4 -> Kerosene
A37: V. | B37: Wholesale price inclusive of VAT | C37: =C33 -> 157.35476 | E37: =E33 -> 160.00515 | G37: =G33 -> 157.19984
B38: Input VAT on Product at retail | D38: =-C32 -> -11.66 | F38: =-E32 -> -11.85 | H38: =-G32 -> -11.64
A39: VI. | B39: Distribution Cost
B40: Delivery Within 40kms | C40: =Hola!G23 -> 3.8559943 | E40: =C40 -> 3.8559943 | G40: =E40 -> 3.8559943
B41: Subtotal | C41: =SUM(C40) -> 3.8559943 | E41: =SUM(E40) -> 3.8559943 | G41: =SUM(G40) -> 3.8559943
A42: VII. | B42: Retailer's Margin | C42: =Mombasa!D22 -> 8.19 | E42: =Mombasa!E22 -> 8.19 | G42: =Mombasa!F22 -> 8.19
B43: Retail price | C43: =C$37+C$42+C$41 -> 169.40076 | E43: =E$37+E$42+E$41 -> 172.05115 | G43: =G$37+G$42+G$41 -> 169.24583
B44: LESS: Levies | C44: 0 | E44: 0 | G44: 0
B45: Non-VATable storage and distribution costs | C45: 0 | E45: 0 | G45: 0
B46: VATable value [(V)+(VI)-Input VAT] | C46: =C$43-C44-C45+D$38 -> 157.74076 | E46: =E$43-E44-E45+F$38 -> 160.20115 | G46: =G$43-G44-G45+H$38 -> 157.60583
B47: Output VAT on product at retail level | D47: =CONCATENATE("+ ",ROUND((C$46*0.08),2)) -> + 12.62 | F47: =CONCATENATE("+ ",ROUND((E$46*0.08),2)) -> + 12.82 | H47: =CONCATENATE("+ ",ROUND((G$46*0.08),2)) -> + 12.61
B48: ADD: VAT at retail | C48: =D47 -> + 12.62 | E48: =F47 -> + 12.82 | G48: =H47 -> + 12.61
B49: Retail Pump-Price under VAT regime | C49: =C$46+C$48+C$44+C$45 -> 170.36076 | D49: =D38+D47 -> 0.96 | E49: =E$46+E$48+E$44+E$45 -> 173.02115 | F49: =F38+F47 -> 0.97 | G49: =G$46+G$48+G$44+G$45 -> 170.21583 | H49: =H38+H47 -> 0.97
A51: EXPECTED IMPACT ON THE FINAL RETAIL PRICE COMPARED TO THE NON-VAT REGIME
B53: ERC PRICE UNDER NON-VAT REGIME | C53: =Mombasa!D26 -> 154.6121 | D53: =C9+C20+C21+C28+C42+0.16*C8+0.16*SUM(C24:C25) -> 153.9881 | E53: ='Breakdown for PMS, AGO & DPK'!E26 -> 160.05845 | G53: ='Breakdown for PMS, AGO & DPK'!F26 -> 157.48856
B54: PRICE DIFFERENCE | C54: =C49-C53 -> 15.748651 | D54: =C53-D53 -> 0.62400843 | E54: =E49-E53 -> 12.962696 | G54: =G49-G53 -> 12.727271
B55: PERCENTAGE INCREAMENT | C55: =C54/C53 -> 0.10185911 | D55: =7-5.55+3.89-3.112 -> 2.228 | E55: =E54/E53 -> 0.080987266 | G55: =G54/G53 -> 0.080813943
B56: GOVERNMENT NET VAT COLLECTION (KSHS PER LITRE) | C56: =D$33+D$49+-$D$10 -> 12.62 | E56: =F$33+F$49 -> 4.5790575 | G56: =H$33+H$49 -> 4.1777517

Sheet Minjila
C2: MINJIRA TOWN
C3: Petroleum Costing
C4: =Taveta!C4 -> March 15 - April 14, 2023
D6: PMS | E6: AGO | F6: DPK
C7: Kshs/lt | D7: ='WEIGHTED AVERAGE COST'!L40 -> 140.89005 | E7: ='WEIGHTED AVERAGE COST'!L76 -> 143.64234 | F7: ='WEIGHTED AVERAGE COST'!L104 -> 141.0813 | H7: Weighted average cost (KPRL + KOSF)
G8: =Mombasa!G8 -> 1.16 | H8: 16% VAT Inclusive
C9: Kshs/lt | D9: =$G$10*$G$9*$G$8 -> 0 | E9: =$G$10*$G$9*$G$8 -> 0 | F9: =$G$10*$G$9*$G$8 -> 0 | G9: 0 | H9: % transported through pipeline - Zero for Mombasa
G10: 0 | H10: Pipeline Rate
C11: Kshs/lt | D11: =$G$11*G12*$G$8 -> 0 | E11: =$G$11*G12*$G$8 -> 0 | F11: =$G$11*G12*$G$8 -> 0 | G11: =8.14*G14/1000 -> 0 | H11: Bridging Rate Kshs 0.0814 per litre x distance
G12: =1-G9 -> 1 | H12: % transported through road
C13: Kshs/lt | D13: =$G$13*D7 -> 0 | E13: =$G$13*E7 -> 0 | F13: =$G$13*F7 -> 0 | G13: 0 | H13: Allowed pipeline losses
G14: 0 | H14: Distance from Source Depot
C15: Kshs/lt | D15: =G15*D7 -> 0.70445024 | E15: =G16*E7 -> 0.43092702 | F15: =G16*F7 -> 0.42324391 | G15: 0.005 | H15: Allowed depot losses. 0.5% for PMS,RMS and 0.3% for AGO,DPK
G16: 0.003
C17: Kshs/lt | D17: =Mombasa!D18 -> 4.204 | E17: =Mombasa!E18 -> 4.174 | F17: =Mombasa!F18 -> 4.174 | H17: Allowed oil marketing company's gross wholesale margin
C19: Kshs/lt | D19: =SUM(D7:D18) -> 145.7985 | E19: =SUM(E7:E18) -> 148.24727 | F19: =SUM(F7:F18) -> 145.67855 | H19: Maximum Wholesale price
C21: Kshs/lt | D21: =Mombasa!D22 -> 8.19 | E21: =Mombasa!E22 -> 8.19 | F21: =Mombasa!F22 -> 8.19 | H21: Allowed retail dealers gross margin
C23: Kshs/lt | D23: =$G$23*$G$8 -> 3.0560551 | E23: =$G$23*$G$8 -> 3.0560551 | F23: =$G$23*$G$8 -> 3.0560551 | G23: ='Delivery >40km-Sept 2013'!E24*I23/1000 -> 2.6345303 | H23: Road distance from Mombasa Depot | I23: 220
C25: Kshs/lt | D25: =D19+D21+D23 -> 157.04455 | E25: =E19+E21+E23 -> 159.49332 | F25: =F19+F21+F23 -> 156.9246 | H25: Maximum retail pump price

Sheet Minjila_Price VAT Inclusive
B3: OMC WHOLE-SALE FUEL PRICE BREAK-DOWN INCLUDING VAT
B4: =Mombasa!C4 -> March 15 - April 14, 2023 | C4: Super petrol | E4: Diesel | G4: Kerosene
B5: Item | C5: COST/ PRICE | D5: (INPUT)/ OUTPUT | E5: COST/ PRICE | F5: (INPUT)/ OUTPUT | G5: COST/ PRICE | H5: (INPUT)/ OUTPUT
B6: Landed cost, exclusive of VAT (KShs/Litre) [a+b+c] | C6: =C$7+C$8 -> 90.386689 | E6: =E$7+E$8 -> 103.01178 | G6: =G$7+G$8 -> 105.4031
B7: (a) None VAT-charged costs (KShs/litre) | C7: ='PMS SUMMARY'!D45 -> 89.740845 | E7: ='AGO SUMMARY'!E47 -> 102.43802 | G7: ='DPK SUMMARY'!D44 -> 104.66296
B8: (b) VAT-charged costs (KShs/litre) | C8: ='PMS SUMMARY'!D44 -> 0.6458438 | E8: ='AGO SUMMARY'!E46 -> 0.5737644 | G8: ='DPK SUMMARY'!D43 -> 0.74013888
A9: I. | B9: VATable amount (KShs/Litre) | C9: =C$6 -> 90.386689 | E9: =E$6 -> 103.01178 | G9: =G$6 -> 105.4031
B10: INPUT VAT 2 (on I.) | D10: =-(C9*0.08) -> -7.2309351 | F10: =-(E9*0.08) -> -8.2409425 | H10: =-(G9*0.08) -> -8.4322483
A11: II. | B11: Levies
B12: Excise duty | C12: ='Breakdown for PMS, AGO & DPK'!D19 -> 21.95302 | E12: ='Breakdown for PMS, AGO & DPK'!E19 -> 11.37099 | G12: ='Breakdown for PMS, AGO & DPK'!F19 -> 11.37098
B13: Merchant Shipping Fee | C13: ='PMS SUMMARY'!D46 -> 0.029475332 | E13: ='AGO SUMMARY'!E48 -> 0.033048548 | G13: ='DPK SUMMARY'!D45 -> 0.0014519287
B14: Import Declaration Fee | C14: ='PMS SUMMARY'!D47 -> 3.0336263 | E14: ='AGO SUMMARY'!E49 -> 3.490076 | G14: ='DPK SUMMARY'!D46 -> 3.5235822
B15: Road Maintenance Levy | C15: ='Breakdown for PMS, AGO & DPK'!D20 -> 18 | E15: ='Breakdown for PMS, AGO & DPK'!E20 -> 18 | G15: 0
B16: Anti-adulteration Levy | C16: 0 | E16: 0 | G16: ='Breakdown for PMS, AGO & DPK'!F24 -> 18
B17: Petroleum Development Levy | C17: ='Breakdown for PMS, AGO & DPK'!D21 -> 5.4 | E17: ='Breakdown for PMS, AGO & DPK'!E21 -> 5.4 | G17: ='Breakdown for PMS, AGO & DPK'!F21 -> 0.4
B18: Petroleum Regulatory Levy | C18: ='Breakdown for PMS, AGO & DPK'!D22 -> 0.25 | E18: ='Breakdown for PMS, AGO & DPK'!E22 -> 0.25 | G18: ='Breakdown for PMS, AGO & DPK'!F22 -> 0.25
B19: Railway Development Levy | C19: ='Breakdown for PMS, AGO & DPK'!D23 -> 1.7335008 | E19: ='Breakdown for PMS, AGO & DPK'!E23 -> 1.9943291 | G19: ='Breakdown for PMS, AGO & DPK'!F23 -> 2.0134756
B20: Sub-total | C20: =SUM(C12:C19) -> 50.399622 | E20: =SUM(E12:E19) -> 40.538444 | G20: =SUM(G12:G19) -> 35.55949
A21: III. | B21: Storage and Distribution Costs (Variable/Litre) | C21: =SUM(C$22:C$23) -> 0.70445024 | E21: =SUM(E$22:E$23) -> 0.43092702 | G21: =SUM(G$22:G$23) -> 0.42324391
B22: Storage and Distribution Costs (with VAT) | C22: =SUM(C$24:C$25) -> 0 | E22: =SUM(E$24:E$25) -> 0 | G22: =SUM(G$24:G$25) -> 0
B23: Storage and Distribution Costs (without VAT) | C23: =C$26+C$27 -> 0.70445024 | E23: =E$26+E$27 -> 0.43092702 | G23: =G$26+G$27 -> 0.42324391
B24: Pipeline Transport (Msa) | C24: =Mombasa!D9 -> 0 | E24: =Mombasa!E9 -> 0 | G24: =Mombasa!F9 -> 0
B25: Road Transport (Msa) - Bridging | C25: =Mombasa!D11 -> 0 | E25: =Mombasa!E11 -> 0 | G25: =Mombasa!F11 -> 0
B26: Pipeline Losses | C26: =Mombasa!D13 -> 0 | E26: =Mombasa!E13 -> 0 | G26: =Mombasa!F13 -> 0
B27: Depot Losses | C27: =Mombasa!D15 -> 0.70445024 | E27: =Mombasa!E15 -> 0.43092702 | G27: =Mombasa!F15 -> 0.42324391
A28: IV. | B28: Oil Marketers Margin | C28: =Mombasa!D18 -> 4.204 | E28: =Mombasa!E18 -> 4.174 | G28: =Mombasa!F18 -> 4.174
B29: VATable price [(I)+(III)+(IV)] | C29: =C$9+C$20+C$22+C$23+C$28 -> 145.69476 | E29: =E$9+E$20+E$22+E$23+E$28 -> 148.15515 | G29: =G$9+G$20+G$22+G$23+G$28 -> 145.55984
B30: Output VAT | D30: =CONCATENATE("+ ",ROUND((C$29*0.08),2)) -> + 11.66 | F30: =CONCATENATE("+ ",ROUND((E$29*0.08),2)) -> + 11.85 | H30: =CONCATENATE("+ ",ROUND((G$29*0.08),2)) -> + 11.64
B31: OMC Wholesale price exclusive of VAT | C31: =C$9+C$20+C$21+C$28 -> 145.69476 | E31: =E$9+E$20+E$21+E$28 -> 148.15515 | G31: =G$9+G$20+G$21+G$28 -> 145.55984
B32: ADD: VAT at wholesale | C32: =D30 -> + 11.66 | E32: =F30 -> + 11.85 | G32: =H30 -> + 11.64
B33: Wholesale Price inxclusive of VAT | C33: =C31+C32 -> 157.35476 | D33: =+D10+D30 -> 4.4290649 | E33: =E31+E32 -> 160.00515 | F33: =F10+F30 -> 3.6090575 | G33: =G31+G32 -> 157.19984 | H33: =H10+H30 -> 3.2077517
B35: RETAIL FUEL COST BREAK-DOWN INCLUDING VAT
C36: =C4 -> Super petrol | E36: =E4 -> Diesel | G36: =G4 -> Kerosene
A37: V. | B37: Wholesale price inclusive of VAT | C37: =C33 -> 157.35476 | E37: =E33 -> 160.00515 | G37: =G33 -> 157.19984
B38: Input VAT on Product at retail | D38: =-C32 -> -11.66 | F38: =-E32 -> -11.85 | H38: =-G32 -> -11.64
A39: VI. | B39: Distribution Cost
B40: Delivery Within 40kms | C40: =Minjila!G23 -> 2.6345303 | E40: =C40 -> 2.6345303 | G40: =E40 -> 2.6345303
B41: Subtotal | C41: =SUM(C40) -> 2.6345303 | E41: =SUM(E40) -> 2.6345303 | G41: =SUM(G40) -> 2.6345303
A42: VII. | B42: Retailer's Margin | C42: =Mombasa!D22 -> 8.19 | E42: =Mombasa!E22 -> 8.19 | G42: =Mombasa!F22 -> 8.19
B43: Retail price | C43: =C$37+C$42+C$41 -> 168.17929 | E43: =E$37+E$42+E$41 -> 170.82968 | G43: =G$37+G$42+G$41 -> 168.02437
B44: LESS: Levies | C44: 0 | E44: 0 | G44: 0
B45: Non-VATable storage and distribution costs | C45: 0 | E45: 0 | G45: 0
B46: VATable value [(V)+(VI)-Input VAT] | C46: =C$43-C44-C45+D$38 -> 156.51929 | E46: =E$43-E44-E45+F$38 -> 158.97968 | G46: =G$43-G44-G45+H$38 -> 156.38437
B47: Output VAT on product at retail level | D47: =CONCATENATE("+ ",ROUND((C$46*0.08),2)) -> + 12.52 | F47: =CONCATENATE("+ ",ROUND((E$46*0.08),2)) -> + 12.72 | H47: =CONCATENATE("+ ",ROUND((G$46*0.08),2)) -> + 12.51
B48: ADD: VAT at retail | C48: =D47 -> + 12.52 | E48: =F47 -> + 12.72 | G48: =H47 -> + 12.51
B49: Retail Pump-Price under VAT regime | C49: =C$46+C$48+C$44+C$45 -> 169.03929 | D49: =D38+D47 -> 0.86 | E49: =E$46+E$48+E$44+E$45 -> 171.69968 | F49: =F38+F47 -> 0.87 | G49: =G$46+G$48+G$44+G$45 -> 168.89437 | H49: =H38+H47 -> 0.87
A51: EXPECTED IMPACT ON THE FINAL RETAIL PRICE COMPARED TO THE NON-VAT REGIME
B53: ERC PRICE UNDER NON-VAT REGIME | C53: =Mombasa!D26 -> 154.6121 | D53: =C9+C20+C21+C28+C42+0.16*C8+0.16*SUM(C24:C25) -> 153.9881 | E53: ='Breakdown for PMS, AGO & DPK'!E26 -> 160.05845 | G53: ='Breakdown for PMS, AGO & DPK'!F26 -> 157.48856
B54: PRICE DIFFERENCE | C54: =C49-C53 -> 14.427187 | D54: =C53-D53 -> 0.62400843 | E54: =E49-E53 -> 11.641232 | G54: =G49-G53 -> 11.405807
B55: PERCENTAGE INCREAMENT | C55: =C54/C53 -> 0.093312143 | D55: =7-5.55+3.89-3.112 -> 2.228 | E55: =E54/E53 -> 0.072731132 | G55: =G54/G53 -> 0.072423086
B56: GOVERNMENT NET VAT COLLECTION (KSHS PER LITRE) | C56: =D$33+D$49+-$D$10 -> 12.52 | E56: =F$33+F$49 -> 4.4790575 | G56: =H$33+H$49 -> 4.0777517

Sheet Samburu
C2: SAMBURUTOWN
C3: Petroleum Costing
C4: =Taveta!C4 -> March 15 - April 14, 2023
D6: PMS | E6: AGO | F6: DPK
C7: Kshs/lt | D7: ='WEIGHTED AVERAGE COST'!L40 -> 140.89005 | E7: ='WEIGHTED AVERAGE COST'!L76 -> 143.64234 | F7: ='WEIGHTED AVERAGE COST'!L104 -> 141.0813 | H7: Weighted average cost (KPRL + KOSF)
G8: =Mombasa!G8 -> 1.16 | H8: 16% VAT Inclusive
C9: Kshs/lt | D9: =$G$10*$G$9*$G$8 -> 0 | E9: =$G$10*$G$9*$G$8 -> 0 | F9: =$G$10*$G$9*$G$8 -> 0 | G9: 0 | H9: % transported through pipeline - Zero for Mombasa
G10: 0 | H10: Pipeline Rate
C11: Kshs/lt | D11: =$G$11*G12*$G$8 -> 0 | E11: =$G$11*G12*$G$8 -> 0 | F11: =$G$11*G12*$G$8 -> 0 | G11: =8.14*G14/1000 -> 0 | H11: Bridging Rate Kshs 0.0814 per litre x distance
G12: =1-G9 -> 1 | H12: % transported through road
C13: Kshs/lt | D13: =$G$13*D7 -> 0 | E13: =$G$13*E7 -> 0 | F13: =$G$13*F7 -> 0 | G13: 0 | H13: Allowed pipeline losses
G14: 0 | H14: Distance from Source Depot
C15: Kshs/lt | D15: =G15*D7 -> 0.70445024 | E15: =G16*E7 -> 0.43092702 | F15: =G16*F7 -> 0.42324391 | G15: 0.005 | H15: Allowed depot losses. 0.5% for PMS,RMS and 0.3% for AGO,DPK
G16: 0.003
C17: Kshs/lt | D17: =Mombasa!D18 -> 4.204 | E17: =Mombasa!E18 -> 4.174 | F17: =Mombasa!F18 -> 4.174 | H17: Allowed oil marketing company's gross wholesale margin
C19: Kshs/lt | D19: =SUM(D7:D18) -> 145.7985 | E19: =SUM(E7:E18) -> 148.24727 | F19: =SUM(F7:F18) -> 145.67855 | H19: Maximum Wholesale price
C21: Kshs/lt | D21: =Mombasa!D22 -> 8.19 | E21: =Mombasa!E22 -> 8.19 | F21: =Mombasa!F22 -> 8.19 | H21: Allowed retail dealers gross margin
C23: Kshs/lt | D23: =$G$23*$G$8 -> 0.94459885 | E23: =$G$23*$G$8 -> 0.94459885 | F23: =$G$23*$G$8 -> 0.94459885 | G23: ='Delivery >40km-Sept 2013'!E24*I23/1000 -> 0.81430935 | H23: Road distance from Mombasa Depot | I23: 68
C25: Kshs/lt | D25: =D19+D21+D23 -> 154.9331 | E25: =E19+E21+E23 -> 157.38187 | F25: =F19+F21+F23 -> 154.81315 | H25: Maximum retail pump price

Sheet Samburu_Price VAT Inclusive
B3: OMC WHOLE-SALE FUEL PRICE BREAK-DOWN INCLUDING VAT
B4: =Mombasa!C4 -> March 15 - April 14, 2023 | C4: Super petrol | E4: Diesel | G4: Kerosene
B5: Item | C5: COST/ PRICE | D5: (INPUT)/ OUTPUT | E5: COST/ PRICE | F5: (INPUT)/ OUTPUT | G5: COST/ PRICE | H5: (INPUT)/ OUTPUT
B6: Landed cost, exclusive of VAT (KShs/Litre) [a+b+c] | C6: =C$7+C$8 -> 90.386689 | E6: =E$7+E$8 -> 103.01178 | G6: =G$7+G$8 -> 105.4031
B7: (a) None VAT-charged costs (KShs/litre) | C7: ='PMS SUMMARY'!D45 -> 89.740845 | E7: ='AGO SUMMARY'!E47 -> 102.43802 | G7: ='DPK SUMMARY'!D44 -> 104.66296
B8: (b) VAT-charged costs (KShs/litre) | C8: ='PMS SUMMARY'!D44 -> 0.6458438 | E8: ='AGO SUMMARY'!E46 -> 0.5737644 | G8: ='DPK SUMMARY'!D43 -> 0.74013888
A9: I. | B9: VATable amount (KShs/Litre) | C9: =C$6 -> 90.386689 | E9: =E$6 -> 103.01178 | G9: =G$6 -> 105.4031
B10: INPUT VAT 2 (on I.) | D10: =-(C9*0.08) -> -7.2309351 | F10: =-(E9*0.08) -> -8.2409425 | H10: =-(G9*0.08) -> -8.4322483
A11: II. | B11: Levies
B12: Excise duty | C12: ='Breakdown for PMS, AGO & DPK'!D19 -> 21.95302 | E12: ='Breakdown for PMS, AGO & DPK'!E19 -> 11.37099 | G12: ='Breakdown for PMS, AGO & DPK'!F19 -> 11.37098
B13: Merchant Shipping Fee | C13: ='PMS SUMMARY'!D46 -> 0.029475332 | E13: ='AGO SUMMARY'!E48 -> 0.033048548 | G13: ='DPK SUMMARY'!D45 -> 0.0014519287
B14: Import Declaration Fee | C14: ='PMS SUMMARY'!D47 -> 3.0336263 | E14: ='AGO SUMMARY'!E49 -> 3.490076 | G14: ='DPK SUMMARY'!D46 -> 3.5235822
B15: Road Maintenance Levy | C15: ='Breakdown for PMS, AGO & DPK'!D20 -> 18 | E15: ='Breakdown for PMS, AGO & DPK'!E20 -> 18 | G15: 0
B16: Anti-adulteration Levy | C16: 0 | E16: 0 | G16: ='Breakdown for PMS, AGO & DPK'!F24 -> 18
B17: Petroleum Development Levy | C17: ='Breakdown for PMS, AGO & DPK'!D21 -> 5.4 | E17: ='Breakdown for PMS, AGO & DPK'!E21 -> 5.4 | G17: ='Breakdown for PMS, AGO & DPK'!F21 -> 0.4
B18: Petroleum Regulatory Levy | C18: ='Breakdown for PMS, AGO & DPK'!D22 -> 0.25 | E18: ='Breakdown for PMS, AGO & DPK'!E22 -> 0.25 | G18: ='Breakdown for PMS, AGO & DPK'!F22 -> 0.25
B19: Railway Development Levy | C19: ='Breakdown for PMS, AGO & DPK'!D23 -> 1.7335008 | E19: ='Breakdown for PMS, AGO & DPK'!E23 -> 1.9943291 | G19: ='Breakdown for PMS, AGO & DPK'!F23 -> 2.0134756
B20: Sub-total | C20: =SUM(C12:C19) -> 50.399622 | E20: =SUM(E12:E19) -> 40.538444 | G20: =SUM(G12:G19) -> 35.55949
A21: III. | B21: Storage and Distribution Costs (Variable/Litre) | C21: =SUM(C$22:C$23) -> 0.70445024 | E21: =SUM(E$22:E$23) -> 0.43092702 | G21: =SUM(G$22:G$23) -> 0.42324391
B22: Storage and Distribution Costs (with VAT) | C22: =SUM(C$24:C$25) -> 0 | E22: =SUM(E$24:E$25) -> 0 | G22: =SUM(G$24:G$25) -> 0
B23: Storage and Distribution Costs (without VAT) | C23: =C$26+C$27 -> 0.70445024 | E23: =E$26+E$27 -> 0.43092702 | G23: =G$26+G$27 -> 0.42324391
B24: Pipeline Transport (Msa) | C24: =Mombasa!D9 -> 0 | E24: =Mombasa!E9 -> 0 | G24: =Mombasa!F9 -> 0
B25: Road Transport (Msa) - Bridging | C25: =Mombasa!D11 -> 0 | E25: =Mombasa!E11 -> 0 | G25: =Mombasa!F11 -> 0
B26: Pipeline Losses | C26: =Mombasa!D13 -> 0 | E26: =Mombasa!E13 -> 0 | G26: =Mombasa!F13 -> 0
B27: Depot Losses | C27: =Mombasa!D15 -> 0.70445024 | E27: =Mombasa!E15 -> 0.43092702 | G27: =Mombasa!F15 -> 0.42324391
A28: IV. | B28: Oil Marketers Margin | C28: =Mombasa!D18 -> 4.204 | E28: =Mombasa!E18 -> 4.174 | G28: =Mombasa!F18 -> 4.174
B29: VATable price [(I)+(III)+(IV)] | C29: =C$9+C$20+C$22+C$23+C$28 -> 145.69476 | E29: =E$9+E$20+E$22+E$23+E$28 -> 148.15515 | G29: =G$9+G$20+G$22+G$23+G$28 -> 145.55984
B30: Output VAT | D30: =CONCATENATE("+ ",ROUND((C$29*0.08),2)) -> + 11.66 | F30: =CONCATENATE("+ ",ROUND((E$29*0.08),2)) -> + 11.85 | H30: =CONCATENATE("+ ",ROUND((G$29*0.08),2)) -> + 11.64
B31: OMC Wholesale price exclusive of VAT | C31: =C$9+C$20+C$21+C$28 -> 145.69476 | E31: =E$9+E$20+E$21+E$28 -> 148.15515 | G31: =G$9+G$20+G$21+G$28 -> 145.55984
B32: ADD: VAT at wholesale | C32: =D30 -> + 11.66 | E32: =F30 -> + 11.85 | G32: =H30 -> + 11.64
B33: Wholesale Price inxclusive of VAT | C33: =C31+C32 -> 157.35476 | D33: =+D10+D30 -> 4.4290649 | E33: =E31+E32 -> 160.00515 | F33: =F10+F30 -> 3.6090575 | G33: =G31+G32 -> 157.19984 | H33: =H10+H30 -> 3.2077517
B35: RETAIL FUEL COST BREAK-DOWN INCLUDING VAT
C36: =C4 -> Super petrol | E36: =E4 -> Diesel | G36: =G4 -> Kerosene
A37: V. | B37: Wholesale price inclusive of VAT | C37: =C33 -> 157.35476 | E37: =E33 -> 160.00515 | G37: =G33 -> 157.19984
B38: Input VAT on Product at retail | D38: =-C32 -> -11.66 | F38: =-E32 -> -11.85 | H38: =-G32 -> -11.64
A39: VI. | B39: Distribution Cost
B40: Delivery Within 40kms | C40: =Samburu!G23 -> 0.81430935 | E40: =C40 -> 0.81430935 | G40: =E40 -> 0.81430935
B41: Subtotal | C41: =SUM(C40) -> 0.81430935 | E41: =SUM(E40) -> 0.81430935 | G41: =SUM(G40) -> 0.81430935
A42: VII. | B42: Retailer's Margin | C42: =Mombasa!D22 -> 8.19 | E42: =Mombasa!E22 -> 8.19 | G42: =Mombasa!F22 -> 8.19
B43: Retail price | C43: =C$37+C$42+C$41 -> 166.35907 | E43: =E$37+E$42+E$41 -> 169.00946 | G43: =G$37+G$42+G$41 -> 166.20415
B44: LESS: Levies | C44: 0 | E44: 0 | G44: 0
B45: Non-VATable storage and distribution costs | C45: 0 | E45: 0 | G45: 0
B46: VATable value [(V)+(VI)-Input VAT] | C46: =C$43-C44-C45+D$38 -> 154.69907 | E46: =E$43-E44-E45+F$38 -> 157.15946 | G46: =G$43-G44-G45+H$38 -> 154.56415
B47: Output VAT on product at retail level | D47: =CONCATENATE("+ ",ROUND((C$46*0.08),2)) -> + 12.38 | F47: =CONCATENATE("+ ",ROUND((E$46*0.08),2)) -> + 12.57 | H47: =CONCATENATE("+ ",ROUND((G$46*0.08),2)) -> + 12.37
B48: ADD: VAT at retail | C48: =D47 -> + 12.38 | E48: =F47 -> + 12.57 | G48: =H47 -> + 12.37
B49: Retail Pump-Price under VAT regime | C49: =C$46+C$48+C$44+C$45 -> 167.07907 | D49: =D38+D47 -> 0.72 | E49: =E$46+E$48+E$44+E$45 -> 169.72946 | F49: =F38+F47 -> 0.72 | G49: =G$46+G$48+G$44+G$45 -> 166.93415 | H49: =H38+H47 -> 0.73
A51: EXPECTED IMPACT ON THE FINAL RETAIL PRICE COMPARED TO THE NON-VAT REGIME
B53: ERC PRICE UNDER NON-VAT REGIME | C53: =Mombasa!D26 -> 154.6121 | D53: =C9+C20+C21+C28+C42+0.16*C8+0.16*SUM(C24:C25) -> 153.9881 | E53: ='Breakdown for PMS, AGO & DPK'!E26 -> 160.05845 | G53: ='Breakdown for PMS, AGO & DPK'!F26 -> 157.48856
B54: PRICE DIFFERENCE | C54: =C49-C53 -> 12.466966 | D54: =C53-D53 -> 0.62400843 | E54: =E49-E53 -> 9.6710113 | G54: =G49-G53 -> 9.4455866
B55: PERCENTAGE INCREAMENT | C55: =C54/C53 -> 0.080633828 | D55: =7-5.55+3.89-3.112 -> 2.228 | E55: =E54/E53 -> 0.060421748 | G55: =G54/G53 -> 0.059976335
B56: GOVERNMENT NET VAT COLLECTION (KSHS PER LITRE) | C56: =D$33+D$49+-$D$10 -> 12.38 | E56: =F$33+F$49 -> 4.3290575 | G56: =H$33+H$49 -> 3.9377517

Sheet Taru
C2: TARU TOWN
C3: Petroleum Costing
C4: =Taveta!C4 -> March 15 - April 14, 2023
D6: PMS | E6: AGO | F6: DPK
C7: Kshs/lt | D7: ='WEIGHTED AVERAGE COST'!L40 -> 140.89005 | E7: ='WEIGHTED AVERAGE COST'!L76 -> 143.64234 | F7: ='WEIGHTED AVERAGE COST'!L104 -> 141.0813 | H7: Weighted average cost (KPRL + KOSF)
G8: =Mombasa!G8 -> 1.16 | H8: 16% VAT Inclusive
C9: Kshs/lt | D9: =$G$10*$G$9*$G$8 -> 0 | E9: =$G$10*$G$9*$G$8 -> 0 | F9: =$G$10*$G$9*$G$8 -> 0 | G9: 0 | H9: % transported through pipeline - Zero for Mombasa
G10: 0 | H10: Pipeline Rate
C11: Kshs/lt | D11: =$G$11*G12*$G$8 -> 0 | E11: =$G$11*G12*$G$8 -> 0 | F11: =$G$11*G12*$G$8 -> 0 | G11: =8.14*G14/1000 -> 0 | H11: Bridging Rate Kshs 0.0814 per litre x distance
G12: =1-G9 -> 1 | H12: % transported through road
C13: Kshs/lt | D13: =$G$13*D7 -> 0 | E13: =$G$13*E7 -> 0 | F13: =$G$13*F7 -> 0 | G13: 0 | H13: Allowed pipeline losses
G14: 0 | H14: Distance from Source Depot
C15: Kshs/lt | D15: =G15*D7 -> 0.70445024 | E15: =G16*E7 -> 0.43092702 | F15: =G16*F7 -> 0.42324391 | G15: 0.005 | H15: Allowed depot losses. 0.5% for PMS,RMS and 0.3% for AGO,DPK
G16: 0.003
C17: Kshs/lt | D17: =Mombasa!D18 -> 4.204 | E17: =Mombasa!E18 -> 4.174 | F17: =Mombasa!F18 -> 4.174 | H17: Allowed oil marketing company's gross wholesale margin
C19: Kshs/lt | D19: =SUM(D7:D18) -> 145.7985 | E19: =SUM(E7:E18) -> 148.24727 | F19: =SUM(F7:F18) -> 145.67855 | H19: Maximum Wholesale price
C21: Kshs/lt | D21: =Mombasa!D22 -> 8.19 | E21: =Mombasa!E22 -> 8.19 | F21: =Mombasa!F22 -> 8.19 | H21: Allowed retail dealers gross margin
C23: Kshs/lt | D23: =$G$23*$G$8 -> 1.1390751 | E23: =$G$23*$G$8 -> 1.1390751 | F23: =$G$23*$G$8 -> 1.1390751 | G23: ='Delivery >40km-Sept 2013'!E24*I23/1000 -> 0.98196128 | H23: Road distance from Mombasa Depot | I23: 82
C25: Kshs/lt | D25: =D19+D21+D23 -> 155.12757 | E25: =E19+E21+E23 -> 157.57634 | F25: =F19+F21+F23 -> 155.00762 | H25: Maximum retail pump price

Sheet Taru_Price VAT Inclusive
B3: OMC WHOLE-SALE FUEL PRICE BREAK-DOWN INCLUDING VAT
B4: =Mombasa!C4 -> March 15 - April 14, 2023 | C4: Super petrol | E4: Diesel | G4: Kerosene
B5: Item | C5: COST/ PRICE | D5: (INPUT)/ OUTPUT | E5: COST/ PRICE | F5: (INPUT)/ OUTPUT | G5: COST/ PRICE | H5: (INPUT)/ OUTPUT
B6: Landed cost, exclusive of VAT (KShs/Litre) [a+b+c] | C6: =C$7+C$8 -> 90.386689 | E6: =E$7+E$8 -> 103.01178 | G6: =G$7+G$8 -> 105.4031
B7: (a) None VAT-charged costs (KShs/litre) | C7: ='PMS SUMMARY'!D45 -> 89.740845 | E7: ='AGO SUMMARY'!E47 -> 102.43802 | G7: ='DPK SUMMARY'!D44 -> 104.66296
B8: (b) VAT-charged costs (KShs/litre) | C8: ='PMS SUMMARY'!D44 -> 0.6458438 | E8: ='AGO SUMMARY'!E46 -> 0.5737644 | G8: ='DPK SUMMARY'!D43 -> 0.74013888
A9: I. | B9: VATable amount (KShs/Litre) | C9: =C$6 -> 90.386689 | E9: =E$6 -> 103.01178 | G9: =G$6 -> 105.4031
B10: INPUT VAT 2 (on I.) | D10: =-(C9*0.08) -> -7.2309351 | F10: =-(E9*0.08) -> -8.2409425 | H10: =-(G9*0.08) -> -8.4322483
A11: II. | B11: Levies
B12: Excise duty | C12: ='Breakdown for PMS, AGO & DPK'!D19 -> 21.95302 | E12: ='Breakdown for PMS, AGO & DPK'!E19 -> 11.37099 | G12: ='Breakdown for PMS, AGO & DPK'!F19 -> 11.37098
B13: Merchant Shipping Fee | C13: ='PMS SUMMARY'!D46 -> 0.029475332 | E13: ='AGO SUMMARY'!E48 -> 0.033048548 | G13: ='DPK SUMMARY'!D45 -> 0.0014519287
B14: Import Declaration Fee | C14: ='PMS SUMMARY'!D47 -> 3.0336263 | E14: ='AGO SUMMARY'!E49 -> 3.490076 | G14: ='DPK SUMMARY'!D46 -> 3.5235822
B15: Road Maintenance Levy | C15: ='Breakdown for PMS, AGO & DPK'!D20 -> 18 | E15: ='Breakdown for PMS, AGO & DPK'!E20 -> 18 | G15: 0
B16: Anti-adulteration Levy | C16: 0 | E16: 0 | G16: ='Breakdown for PMS, AGO & DPK'!F24 -> 18
B17: Petroleum Development Levy | C17: ='Breakdown for PMS, AGO & DPK'!D21 -> 5.4 | E17: ='Breakdown for PMS, AGO & DPK'!E21 -> 5.4 | G17: ='Breakdown for PMS, AGO & DPK'!F21 -> 0.4
B18: Petroleum Regulatory Levy | C18: ='Breakdown for PMS, AGO & DPK'!D22 -> 0.25 | E18: ='Breakdown for PMS, AGO & DPK'!E22 -> 0.25 | G18: ='Breakdown for PMS, AGO & DPK'!F22 -> 0.25
B19: Railway Development Levy | C19: ='Breakdown for PMS, AGO & DPK'!D23 -> 1.7335008 | E19: ='Breakdown for PMS, AGO & DPK'!E23 -> 1.9943291 | G19: ='Breakdown for PMS, AGO & DPK'!F23 -> 2.0134756
B20: Sub-total | C20: =SUM(C12:C19) -> 50.399622 | E20: =SUM(E12:E19) -> 40.538444 | G20: =SUM(G12:G19) -> 35.55949
A21: III. | B21: Storage and Distribution Costs (Variable/Litre) | C21: =SUM(C$22:C$23) -> 0.70445024 | E21: =SUM(E$22:E$23) -> 0.43092702 | G21: =SUM(G$22:G$23) -> 0.42324391
B22: Storage and Distribution Costs (with VAT) | C22: =SUM(C$24:C$25) -> 0 | E22: =SUM(E$24:E$25) -> 0 | G22: =SUM(G$24:G$25) -> 0
B23: Storage and Distribution Costs (without VAT) | C23: =C$26+C$27 -> 0.70445024 | E23: =E$26+E$27 -> 0.43092702 | G23: =G$26+G$27 -> 0.42324391
B24: Pipeline Transport (Msa) | C24: =Mombasa!D9 -> 0 | E24: =Mombasa!E9 -> 0 | G24: =Mombasa!F9 -> 0
B25: Road Transport (Msa) - Bridging | C25: =Mombasa!D11 -> 0 | E25: =Mombasa!E11 -> 0 | G25: =Mombasa!F11 -> 0
B26: Pipeline Losses | C26: =Mombasa!D13 -> 0 | E26: =Mombasa!E13 -> 0 | G26: =Mombasa!F13 -> 0
B27: Depot Losses | C27: =Mombasa!D15 -> 0.70445024 | E27: =Mombasa!E15 -> 0.43092702 | G27: =Mombasa!F15 -> 0.42324391
A28: IV. | B28: Oil Marketers Margin | C28: =Mombasa!D18 -> 4.204 | E28: =Mombasa!E18 -> 4.174 | G28: =Mombasa!F18 -> 4.174
B29: VATable price [(I)+(III)+(IV)] | C29: =C$9+C$20+C$22+C$23+C$28 -> 145.69476 | E29: =E$9+E$20+E$22+E$23+E$28 -> 148.15515 | G29: =G$9+G$20+G$22+G$23+G$28 -> 145.55984
B30: Output VAT | D30: =CONCATENATE("+ ",ROUND((C$29*0.08),2)) -> + 11.66 | F30: =CONCATENATE("+ ",ROUND((E$29*0.08),2)) -> + 11.85 | H30: =CONCATENATE("+ ",ROUND((G$29*0.08),2)) -> + 11.64
B31: OMC Wholesale price exclusive of VAT | C31: =C$9+C$20+C$21+C$28 -> 145.69476 | E31: =E$9+E$20+E$21+E$28 -> 148.15515 | G31: =G$9+G$20+G$21+G$28 -> 145.55984
B32: ADD: VAT at wholesale | C32: =D30 -> + 11.66 | E32: =F30 -> + 11.85 | G32: =H30 -> + 11.64
B33: Wholesale Price inxclusive of VAT | C33: =C31+C32 -> 157.35476 | D33: =+D10+D30 -> 4.4290649 | E33: =E31+E32 -> 160.00515 | F33: =F10+F30 -> 3.6090575 | G33: =G31+G32 -> 157.19984 | H33: =H10+H30 -> 3.2077517
B35: RETAIL FUEL COST BREAK-DOWN INCLUDING VAT
C36: =C4 -> Super petrol | E36: =E4 -> Diesel | G36: =G4 -> Kerosene
A37: V. | B37: Wholesale price inclusive of VAT | C37: =C33 -> 157.35476 | E37: =E33 -> 160.00515 | G37: =G33 -> 157.19984
B38: Input VAT on Product at retail | D38: =-C32 -> -11.66 | F38: =-E32 -> -11.85 | H38: =-G32 -> -11.64
A39: VI. | B39: Distribution Cost
B40: Delivery Within 40kms | C40: =Taru!G23 -> 0.98196128 | E40: =C40 -> 0.98196128 | G40: =E40 -> 0.98196128
B41: Subtotal | C41: =SUM(C40) -> 0.98196128 | E41: =SUM(E40) -> 0.98196128 | G41: =SUM(G40) -> 0.98196128
A42: VII. | B42: Retailer's Margin | C42: =Mombasa!D22 -> 8.19 | E42: =Mombasa!E22 -> 8.19 | G42: =Mombasa!F22 -> 8.19
B43: Retail price | C43: =C$37+C$42+C$41 -> 166.52672 | E43: =E$37+E$42+E$41 -> 169.17711 | G43: =G$37+G$42+G$41 -> 166.3718
B44: LESS: Levies | C44: 0 | E44: 0 | G44: 0
B45: Non-VATable storage and distribution costs | C45: 0 | E45: 0 | G45: 0
B46: VATable value [(V)+(VI)-Input VAT] | C46: =C$43-C44-C45+D$38 -> 154.86672 | E46: =E$43-E44-E45+F$38 -> 157.32711 | G46: =G$43-G44-G45+H$38 -> 154.7318
B47: Output VAT on product at retail level | D47: =CONCATENATE("+ ",ROUND((C$46*0.08),2)) -> + 12.39 | F47: =CONCATENATE("+ ",ROUND((E$46*0.08),2)) -> + 12.59 | H47: =CONCATENATE("+ ",ROUND((G$46*0.08),2)) -> + 12.38
B48: ADD: VAT at retail | C48: =D47 -> + 12.39 | E48: =F47 -> + 12.59 | G48: =H47 -> + 12.38
B49: Retail Pump-Price under VAT regime | C49: =C$46+C$48+C$44+C$45 -> 167.25672 | D49: =D38+D47 -> 0.73 | E49: =E$46+E$48+E$44+E$45 -> 169.91711 | F49: =F38+F47 -> 0.74 | G49: =G$46+G$48+G$44+G$45 -> 167.1118 | H49: =H38+H47 -> 0.74
A51: EXPECTED IMPACT ON THE FINAL RETAIL PRICE COMPARED TO THE NON-VAT REGIME
B53: ERC PRICE UNDER NON-VAT REGIME | C53: =Mombasa!D26 -> 154.6121 | D53: =C9+C20+C21+C28+C42+0.16*C8+0.16*SUM(C24:C25) -> 153.9881 | E53: ='Breakdown for PMS, AGO & DPK'!E26 -> 160.05845 | G53: ='Breakdown for PMS, AGO & DPK'!F26 -> 157.48856
B54: PRICE DIFFERENCE | C54: =C49-C53 -> 12.644618 | D54: =C53-D53 -> 0.62400843 | E54: =E49-E53 -> 9.8586632 | G54: =G49-G53 -> 9.6232385
B55: PERCENTAGE INCREAMENT | C55: =C54/C53 -> 0.081782845 | D55: =7-5.55+3.89-3.112 -> 2.228 | E55: =E54/E53 -> 0.061594144 | G55: =G54/G53 -> 0.061104365
B56: GOVERNMENT NET VAT COLLECTION (KSHS PER LITRE) | C56: =D$33+D$49+-$D$10 -> 12.39 | E56: =F$33+F$49 -> 4.3490575 | G56: =H$33+H$49 -> 3.9477517

Sheet Mpeketoni
C2: MPEKETONI TOWN
C3: Petroleum Costing
C4: =Taveta!C4 -> March 15 - April 14, 2023
D6: PMS | E6: AGO | F6: DPK
C7: Kshs/lt | D7: ='WEIGHTED AVERAGE COST'!L40 -> 140.89005 | E7: ='WEIGHTED AVERAGE COST'!L76 -> 143.64234 | F7: ='WEIGHTED AVERAGE COST'!L104 -> 141.0813 | H7: Weighted average cost (KPRL + KOSF)
G8: =Mombasa!G8 -> 1.16 | H8: 16% VAT Inclusive
C9: Kshs/lt | D9: =$G$10*$G$9*$G$8 -> 0 | E9: =$G$10*$G$9*$G$8 -> 0 | F9: =$G$10*$G$9*$G$8 -> 0 | G9: 0 | H9: % transported through pipeline - Zero for Mombasa
G10: 0 | H10: Pipeline Rate
C11: Kshs/lt | D11: =$G$11*G12*$G$8 -> 0 | E11: =$G$11*G12*$G$8 -> 0 | F11: =$G$11*G12*$G$8 -> 0 | G11: =8.14*G14/1000 -> 0 | H11: Bridging Rate Kshs 0.0814 per litre x distance
G12: =1-G9 -> 1 | H12: % transported through road
C13: Kshs/lt | D13: =$G$13*D7 -> 0 | E13: =$G$13*E7 -> 0 | F13: =$G$13*F7 -> 0 | G13: 0 | H13: Allowed pipeline losses
G14: 0 | H14: Distance from Source Depot
C15: Kshs/lt | D15: =G15*D7 -> 0.70445024 | E15: =G16*E7 -> 0.43092702 | F15: =G16*F7 -> 0.42324391 | G15: 0.005 | H15: Allowed depot losses. 0.5% for PMS,RMS and 0.3% for AGO,DPK
G16: 0.003
C17: Kshs/lt | D17: =Mombasa!D18 -> 4.204 | E17: =Mombasa!E18 -> 4.174 | F17: =Mombasa!F18 -> 4.174 | H17: Allowed oil marketing company's gross wholesale margin
C19: Kshs/lt | D19: =SUM(D7:D18) -> 145.7985 | E19: =SUM(E7:E18) -> 148.24727 | F19: =SUM(F7:F18) -> 145.67855 | H19: Maximum Wholesale price
C21: Kshs/lt | D21: =Mombasa!D22 -> 8.19 | E21: =Mombasa!E22 -> 8.19 | F21: =Mombasa!F22 -> 8.19 | H21: Allowed retail dealers gross margin
C23: Kshs/lt | D23: =$G$23*$G$8 -> 4.1673479 | E23: =$G$23*$G$8 -> 4.1673479 | F23: =$G$23*$G$8 -> 4.1673479 | G23: ='Delivery >40km-Sept 2013'!E24*I23/1000 -> 3.5925413 | H23: Road distance from Mombasa Depot | I23: 300
C25: Kshs/lt | D25: =D19+D21+D23 -> 158.15585 | E25: =E19+E21+E23 -> 160.60462 | F25: =F19+F21+F23 -> 158.03589 | H25: Maximum retail pump price

Sheet Mpeketoni_Price VAT Inclusive
B3: OMC WHOLE-SALE FUEL PRICE BREAK-DOWN INCLUDING VAT
B4: =Mombasa!C4 -> March 15 - April 14, 2023 | C4: Super petrol | E4: Diesel | G4: Kerosene
B5: Item | C5: COST/ PRICE | D5: (INPUT)/ OUTPUT | E5: COST/ PRICE | F5: (INPUT)/ OUTPUT | G5: COST/ PRICE | H5: (INPUT)/ OUTPUT
B6: Landed cost, exclusive of VAT (KShs/Litre) [a+b+c] | C6: =C$7+C$8 -> 90.386689 | E6: =E$7+E$8 -> 103.01178 | G6: =G$7+G$8 -> 105.4031
B7: (a) None VAT-charged costs (KShs/litre) | C7: ='PMS SUMMARY'!D45 -> 89.740845 | E7: ='AGO SUMMARY'!E47 -> 102.43802 | G7: ='DPK SUMMARY'!D44 -> 104.66296
B8: (b) VAT-charged costs (KShs/litre) | C8: ='PMS SUMMARY'!D44 -> 0.6458438 | E8: ='AGO SUMMARY'!E46 -> 0.5737644 | G8: ='DPK SUMMARY'!D43 -> 0.74013888
A9: I. | B9: VATable amount (KShs/Litre) | C9: =C$6 -> 90.386689 | E9: =E$6 -> 103.01178 | G9: =G$6 -> 105.4031
B10: INPUT VAT 2 (on I.) | D10: =-(C9*0.08) -> -7.2309351 | F10: =-(E9*0.08) -> -8.2409425 | H10: =-(G9*0.08) -> -8.4322483
A11: II. | B11: Levies
B12: Excise duty | C12: ='Breakdown for PMS, AGO & DPK'!D19 -> 21.95302 | E12: ='Breakdown for PMS, AGO & DPK'!E19 -> 11.37099 | G12: ='Breakdown for PMS, AGO & DPK'!F19 -> 11.37098
B13: Merchant Shipping Fee | C13: ='PMS SUMMARY'!D46 -> 0.029475332 | E13: ='AGO SUMMARY'!E48 -> 0.033048548 | G13: ='DPK SUMMARY'!D45 -> 0.0014519287
B14: Import Declaration Fee | C14: ='PMS SUMMARY'!D47 -> 3.0336263 | E14: ='AGO SUMMARY'!E49 -> 3.490076 | G14: ='DPK SUMMARY'!D46 -> 3.5235822
B15: Road Maintenance Levy | C15: ='Breakdown for PMS, AGO & DPK'!D20 -> 18 | E15: ='Breakdown for PMS, AGO & DPK'!E20 -> 18 | G15: 0
B16: Anti-adulteration Levy | C16: 0 | E16: 0 | G16: ='Breakdown for PMS, AGO & DPK'!F24 -> 18
B17: Petroleum Development Levy | C17: ='Breakdown for PMS, AGO & DPK'!D21 -> 5.4 | E17: ='Breakdown for PMS, AGO & DPK'!E21 -> 5.4 | G17: ='Breakdown for PMS, AGO & DPK'!F21 -> 0.4
B18: Petroleum Regulatory Levy | C18: ='Breakdown for PMS, AGO & DPK'!D22 -> 0.25 | E18: ='Breakdown for PMS, AGO & DPK'!E22 -> 0.25 | G18: ='Breakdown for PMS, AGO & DPK'!F22 -> 0.25
B19: Railway Development Levy | C19: ='Breakdown for PMS, AGO & DPK'!D23 -> 1.7335008 | E19: ='Breakdown for PMS, AGO & DPK'!E23 -> 1.9943291 | G19: ='Breakdown for PMS, AGO & DPK'!F23 -> 2.0134756
B20: Sub-total | C20: =SUM(C12:C19) -> 50.399622 | E20: =SUM(E12:E19) -> 40.538444 | G20: =SUM(G12:G19) -> 35.55949
A21: III. | B21: Storage and Distribution Costs (Variable/Litre) | C21: =SUM(C$22:C$23) -> 0.70445024 | E21: =SUM(E$22:E$23) -> 0.43092702 | G21: =SUM(G$22:G$23) -> 0.42324391
B22: Storage and Distribution Costs (with VAT) | C22: =SUM(C$24:C$25) -> 0 | E22: =SUM(E$24:E$25) -> 0 | G22: =SUM(G$24:G$25) -> 0
B23: Storage and Distribution Costs (without VAT) | C23: =C$26+C$27 -> 0.70445024 | E23: =E$26+E$27 -> 0.43092702 | G23: =G$26+G$27 -> 0.42324391
B24: Pipeline Transport (Msa) | C24: =Mombasa!D9 -> 0 | E24: =Mombasa!E9 -> 0 | G24: =Mombasa!F9 -> 0
B25: Road Transport (Msa) - Bridging | C25: =Mombasa!D11 -> 0 | E25: =Mombasa!E11 -> 0 | G25: =Mombasa!F11 -> 0
B26: Pipeline Losses | C26: =Mombasa!D13 -> 0 | E26: =Mombasa!E13 -> 0 | G26: =Mombasa!F13 -> 0
B27: Depot Losses | C27: =Mombasa!D15 -> 0.70445024 | E27: =Mombasa!E15 -> 0.43092702 | G27: =Mombasa!F15 -> 0.42324391
A28: IV. | B28: Oil Marketers Margin | C28: =Mombasa!D18 -> 4.204 | E28: =Mombasa!E18 -> 4.174 | G28: =Mombasa!F18 -> 4.174
B29: VATable price [(I)+(III)+(IV)] | C29: =C$9+C$20+C$22+C$23+C$28 -> 145.69476 | E29: =E$9+E$20+E$22+E$23+E$28 -> 148.15515 | G29: =G$9+G$20+G$22+G$23+G$28 -> 145.55984
B30: Output VAT | D30: =CONCATENATE("+ ",ROUND((C$29*0.08),2)) -> + 11.66 | F30: =CONCATENATE("+ ",ROUND((E$29*0.08),2)) -> + 11.85 | H30: =CONCATENATE("+ ",ROUND((G$29*0.08),2)) -> + 11.64
B31: OMC Wholesale price exclusive of VAT | C31: =C$9+C$20+C$21+C$28 -> 145.69476 | E31: =E$9+E$20+E$21+E$28 -> 148.15515 | G31: =G$9+G$20+G$21+G$28 -> 145.55984
B32: ADD: VAT at wholesale | C32: =D30 -> + 11.66 | E32: =F30 -> + 11.85 | G32: =H30 -> + 11.64
B33: Wholesale Price inxclusive of VAT | C33: =C31+C32 -> 157.35476 | D33: =+D10+D30 -> 4.4290649 | E33: =E31+E32 -> 160.00515 | F33: =F10+F30 -> 3.6090575 | G33: =G31+G32 -> 157.19984 | H33: =H10+H30 -> 3.2077517
B35: RETAIL FUEL COST BREAK-DOWN INCLUDING VAT
C36: =C4 -> Super petrol | E36: =E4 -> Diesel | G36: =G4 -> Kerosene
A37: V. | B37: Wholesale price inclusive of VAT | C37: =C33 -> 157.35476 | E37: =E33 -> 160.00515 | G37: =G33 -> 157.19984
B38: Input VAT on Product at retail | D38: =-C32 -> -11.66 | F38: =-E32 -> -11.85 | H38: =-G32 -> -11.64
A39: VI. | B39: Distribution Cost
B40: Delivery Within 40kms | C40: =Mpeketoni!G23 -> 3.5925413 | E40: =C40 -> 3.5925413 | G40: =E40 -> 3.5925413
B41: Subtotal | C41: =SUM(C40) -> 3.5925413 | E41: =SUM(E40) -> 3.5925413 | G41: =SUM(G40) -> 3.5925413
A42: VII. | B42: Retailer's Margin | C42: =Mombasa!D22 -> 8.19 | E42: =Mombasa!E22 -> 8.19 | G42: =Mombasa!F22 -> 8.19
B43: Retail price | C43: =C$37+C$42+C$41 -> 169.1373 | E43: =E$37+E$42+E$41 -> 171.78769 | G43: =G$37+G$42+G$41 -> 168.98238
B44: LESS: Levies | C44: 0 | E44: 0 | G44: 0
B45: Non-VATable storage and distribution costs | C45: 0 | E45: 0 | G45: 0
B46: VATable value [(V)+(VI)-Input VAT] | C46: =C$43-C44-C45+D$38 -> 157.4773 | E46: =E$43-E44-E45+F$38 -> 159.93769 | G46: =G$43-G44-G45+H$38 -> 157.34238
B47: Output VAT on product at retail level | D47: =CONCATENATE("+ ",ROUND((C$46*0.08),2)) -> + 12.6 | F47: =CONCATENATE("+ ",ROUND((E$46*0.08),2)) -> + 12.8 | H47: =CONCATENATE("+ ",ROUND((G$46*0.08),2)) -> + 12.59
B48: ADD: VAT at retail | C48: =D47 -> + 12.6 | E48: =F47 -> + 12.8 | G48: =H47 -> + 12.59
B49: Retail Pump-Price under VAT regime | C49: =C$46+C$48+C$44+C$45 -> 170.0773 | D49: =D38+D47 -> 0.94 | E49: =E$46+E$48+E$44+E$45 -> 172.73769 | F49: =F38+F47 -> 0.95 | G49: =G$46+G$48+G$44+G$45 -> 169.93238 | H49: =H38+H47 -> 0.95
A51: EXPECTED IMPACT ON THE FINAL RETAIL PRICE COMPARED TO THE NON-VAT REGIME
B53: ERC PRICE UNDER NON-VAT REGIME | C53: =Mombasa!D26 -> 154.6121 | D53: =C9+C20+C21+C28+C42+0.16*C8+0.16*SUM(C24:C25) -> 153.9881 | E53: ='Breakdown for PMS, AGO & DPK'!E26 -> 160.05845 | G53: ='Breakdown for PMS, AGO & DPK'!F26 -> 157.48856
B54: PRICE DIFFERENCE | C54: =C49-C53 -> 15.465198 | D54: =C53-D53 -> 0.62400843 | E54: =E49-E53 -> 12.679243 | G54: =G49-G53 -> 12.443818
B55: PERCENTAGE INCREAMENT | C55: =C54/C53 -> 0.10002579 | D55: =7-5.55+3.89-3.112 -> 2.228 | E55: =E54/E53 -> 0.079216331 | G55: =G54/G53 -> 0.079014111
B56: GOVERNMENT NET VAT COLLECTION (KSHS PER LITRE) | C56: =D$33+D$49+-$D$10 -> 12.6 | E56: =F$33+F$49 -> 4.5590575 | G56: =H$33+H$49 -> 4.1577517

Sheet Garsen
C2: GARSEN TOWN
C3: Petroleum Costing
C4: =Taveta!C4 -> March 15 - April 14, 2023
D6: PMS | E6: AGO | F6: DPK
C7: Kshs/lt | D7: ='WEIGHTED AVERAGE COST'!L40 -> 140.89005 | E7: ='WEIGHTED AVERAGE COST'!L76 -> 143.64234 | F7: ='WEIGHTED AVERAGE COST'!L104 -> 141.0813 | H7: Weighted average cost (KPRL + KOSF)
G8: =Mombasa!G8 -> 1.16 | H8: 16% VAT Inclusive
C9: Kshs/lt | D9: =$G$10*$G$9*$G$8 -> 0 | E9: =$G$10*$G$9*$G$8 -> 0 | F9: =$G$10*$G$9*$G$8 -> 0 | G9: 0 | H9: % transported through pipeline - Zero for Mombasa
G10: 0 | H10: Pipeline Rate
C11: Kshs/lt | D11: =$G$11*G12*$G$8 -> 0 | E11: =$G$11*G12*$G$8 -> 0 | F11: =$G$11*G12*$G$8 -> 0 | G11: =8.14*G14/1000 -> 0 | H11: Bridging Rate Kshs 0.0814 per litre x distance
G12: =1-G9 -> 1 | H12: % transported through road
C13: Kshs/lt | D13: =$G$13*D7 -> 0 | E13: =$G$13*E7 -> 0 | F13: =$G$13*F7 -> 0 | G13: 0 | H13: Allowed pipeline losses
G14: 0 | H14: Distance from Source Depot
C15: Kshs/lt | D15: =G15*D7 -> 0.70445024 | E15: =G16*E7 -> 0.43092702 | F15: =G16*F7 -> 0.42324391 | G15: 0.005 | H15: Allowed depot losses. 0.5% for PMS,RMS and 0.3% for AGO,DPK
G16: 0.003
C17: Kshs/lt | D17: =Mombasa!D18 -> 4.204 | E17: =Mombasa!E18 -> 4.174 | F17: =Mombasa!F18 -> 4.174 | H17: Allowed oil marketing company's gross wholesale margin
C19: Kshs/lt | D19: =SUM(D7:D18) -> 145.7985 | E19: =SUM(E7:E18) -> 148.24727 | F19: =SUM(F7:F18) -> 145.67855 | H19: Maximum Wholesale price
C21: Kshs/lt | D21: =Mombasa!D22 -> 8.19 | E21: =Mombasa!E22 -> 8.19 | F21: =Mombasa!F22 -> 8.19 | H21: Allowed retail dealers gross margin
C23: Kshs/lt | D23: =$G$23*$G$8 -> 3.1532932 | E23: =$G$23*$G$8 -> 3.1532932 | F23: =$G$23*$G$8 -> 3.1532932 | G23: ='Delivery >40km-Sept 2013'!E24*I23/1000 -> 2.7183562 | H23: Road distance from Mombasa Depot | I23: 227
C25: Kshs/lt | D25: =D19+D21+D23 -> 157.14179 | E25: =E19+E21+E23 -> 159.59056 | F25: =F19+F21+F23 -> 157.02184 | H25: Maximum retail pump price

Sheet Garsen_Price VAT Inclusive
B3: OMC WHOLE-SALE FUEL PRICE BREAK-DOWN INCLUDING VAT
B4: =Mombasa!C4 -> March 15 - April 14, 2023 | C4: Super petrol | E4: Diesel | G4: Kerosene
B5: Item | C5: COST/ PRICE | D5: (INPUT)/ OUTPUT | E5: COST/ PRICE | F5: (INPUT)/ OUTPUT | G5: COST/ PRICE | H5: (INPUT)/ OUTPUT
B6: Landed cost, exclusive of VAT (KShs/Litre) [a+b+c] | C6: =C$7+C$8 -> 90.386689 | E6: =E$7+E$8 -> 103.01178 | G6: =G$7+G$8 -> 105.4031
B7: (a) None VAT-charged costs (KShs/litre) | C7: ='PMS SUMMARY'!D45 -> 89.740845 | E7: ='AGO SUMMARY'!E47 -> 102.43802 | G7: ='DPK SUMMARY'!D44 -> 104.66296
B8: (b) VAT-charged costs (KShs/litre) | C8: ='PMS SUMMARY'!D44 -> 0.6458438 | E8: ='AGO SUMMARY'!E46 -> 0.5737644 | G8: ='DPK SUMMARY'!D43 -> 0.74013888
A9: I. | B9: VATable amount (KShs/Litre) | C9: =C$6 -> 90.386689 | E9: =E$6 -> 103.01178 | G9: =G$6 -> 105.4031
B10: INPUT VAT 2 (on I.) | D10: =-(C9*0.08) -> -7.2309351 | F10: =-(E9*0.08) -> -8.2409425 | H10: =-(G9*0.08) -> -8.4322483
A11: II. | B11: Levies
B12: Excise duty | C12: ='Breakdown for PMS, AGO & DPK'!D19 -> 21.95302 | E12: ='Breakdown for PMS, AGO & DPK'!E19 -> 11.37099 | G12: ='Breakdown for PMS, AGO & DPK'!F19 -> 11.37098
B13: Merchant Shipping Fee | C13: ='PMS SUMMARY'!D46 -> 0.029475332 | E13: ='AGO SUMMARY'!E48 -> 0.033048548 | G13: ='DPK SUMMARY'!D45 -> 0.0014519287
B14: Import Declaration Fee | C14: ='PMS SUMMARY'!D47 -> 3.0336263 | E14: ='AGO SUMMARY'!E49 -> 3.490076 | G14: ='DPK SUMMARY'!D46 -> 3.5235822
B15: Road Maintenance Levy | C15: ='Breakdown for PMS, AGO & DPK'!D20 -> 18 | E15: ='Breakdown for PMS, AGO & DPK'!E20 -> 18 | G15: 0
B16: Anti-adulteration Levy | C16: 0 | E16: 0 | G16: ='Breakdown for PMS, AGO & DPK'!F24 -> 18
B17: Petroleum Development Levy | C17: ='Breakdown for PMS, AGO & DPK'!D21 -> 5.4 | E17: ='Breakdown for PMS, AGO & DPK'!E21 -> 5.4 | G17: ='Breakdown for PMS, AGO & DPK'!F21 -> 0.4
B18: Petroleum Regulatory Levy | C18: ='Breakdown for PMS, AGO & DPK'!D22 -> 0.25 | E18: ='Breakdown for PMS, AGO & DPK'!E22 -> 0.25 | G18: ='Breakdown for PMS, AGO & DPK'!F22 -> 0.25
B19: Railway Development Levy | C19: ='Breakdown for PMS, AGO & DPK'!D23 -> 1.7335008 | E19: ='Breakdown for PMS, AGO & DPK'!E23 -> 1.9943291 | G19: ='Breakdown for PMS, AGO & DPK'!F23 -> 2.0134756
B20: Sub-total | C20: =SUM(C12:C19) -> 50.399622 | E20: =SUM(E12:E19) -> 40.538444 | G20: =SUM(G12:G19) -> 35.55949
A21: III. | B21: Storage and Distribution Costs (Variable/Litre) | C21: =SUM(C$22:C$23) -> 0.70445024 | E21: =SUM(E$22:E$23) -> 0.43092702 | G21: =SUM(G$22:G$23) -> 0.42324391
B22: Storage and Distribution Costs (with VAT) | C22: =SUM(C$24:C$25) -> 0 | E22: =SUM(E$24:E$25) -> 0 | G22: =SUM(G$24:G$25) -> 0
B23: Storage and Distribution Costs (without VAT) | C23: =C$26+C$27 -> 0.70445024 | E23: =E$26+E$27 -> 0.43092702 | G23: =G$26+G$27 -> 0.42324391
B24: Pipeline Transport (Msa) | C24: =Mombasa!D9 -> 0 | E24: =Mombasa!E9 -> 0 | G24: =Mombasa!F9 -> 0
B25: Road Transport (Msa) - Bridging | C25: =Mombasa!D11 -> 0 | E25: =Mombasa!E11 -> 0 | G25: =Mombasa!F11 -> 0
B26: Pipeline Losses | C26: =Mombasa!D13 -> 0 | E26: =Mombasa!E13 -> 0 | G26: =Mombasa!F13 -> 0
B27: Depot Losses | C27: =Mombasa!D15 -> 0.70445024 | E27: =Mombasa!E15 -> 0.43092702 | G27: =Mombasa!F15 -> 0.42324391
A28: IV. | B28: Oil Marketers Margin | C28: =Mombasa!D18 -> 4.204 | E28: =Mombasa!E18 -> 4.174 | G28: =Mombasa!F18 -> 4.174
B29: VATable price [(I)+(III)+(IV)] | C29: =C$9+C$20+C$22+C$23+C$28 -> 145.69476 | E29: =E$9+E$20+E$22+E$23+E$28 -> 148.15515 | G29: =G$9+G$20+G$22+G$23+G$28 -> 145.55984
B30: Output VAT | D30: =CONCATENATE("+ ",ROUND((C$29*0.08),2)) -> + 11.66 | F30: =CONCATENATE("+ ",ROUND((E$29*0.08),2)) -> + 11.85 | H30: =CONCATENATE("+ ",ROUND((G$29*0.08),2)) -> + 11.64
B31: OMC Wholesale price exclusive of VAT | C31: =C$9+C$20+C$21+C$28 -> 145.69476 | E31: =E$9+E$20+E$21+E$28 -> 148.15515 | G31: =G$9+G$20+G$21+G$28 -> 145.55984
B32: ADD: VAT at wholesale | C32: =D30 -> + 11.66 | E32: =F30 -> + 11.85 | G32: =H30 -> + 11.64
B33: Wholesale Price inxclusive of VAT | C33: =C31+C32 -> 157.35476 | D33: =+D10+D30 -> 4.4290649 | E33: =E31+E32 -> 160.00515 | F33: =F10+F30 -> 3.6090575 | G33: =G31+G32 -> 157.19984 | H33: =H10+H30 -> 3.2077517
B35: RETAIL FUEL COST BREAK-DOWN INCLUDING VAT
C36: =C4 -> Super petrol | E36: =E4 -> Diesel | G36: =G4 -> Kerosene
A37: V. | B37: Wholesale price inclusive of VAT | C37: =C33 -> 157.35476 | E37: =E33 -> 160.00515 | G37: =G33 -> 157.19984
B38: Input VAT on Product at retail | D38: =-C32 -> -11.66 | F38: =-E32 -> -11.85 | H38: =-G32 -> -11.64
A39: VI. | B39: Distribution Cost
B40: Delivery Within 40kms | C40: =Garsen!G23 -> 2.7183562 | E40: =C40 -> 2.7183562 | G40: =E40 -> 2.7183562
B41: Subtotal | C41: =SUM(C40) -> 2.7183562 | E41: =SUM(E40) -> 2.7183562 | G41: =SUM(G40) -> 2.7183562
A42: VII. | B42: Retailer's Margin | C42: =Mombasa!D22 -> 8.19 | E42: =Mombasa!E22 -> 8.19 | G42: =Mombasa!F22 -> 8.19
B43: Retail price | C43: =C$37+C$42+C$41 -> 168.26312 | E43: =E$37+E$42+E$41 -> 170.91351 | G43: =G$37+G$42+G$41 -> 168.10819
B44: LESS: Levies | C44: 0 | E44: 0 | G44: 0
B45: Non-VATable storage and distribution costs | C45: 0 | E45: 0 | G45: 0
B46: VATable value [(V)+(VI)-Input VAT] | C46: =C$43-C44-C45+D$38 -> 156.60312 | E46: =E$43-E44-E45+F$38 -> 159.06351 | G46: =G$43-G44-G45+H$38 -> 156.46819
B47: Output VAT on product at retail level | D47: =CONCATENATE("+ ",ROUND((C$46*0.08),2)) -> + 12.53 | F47: =CONCATENATE("+ ",ROUND((E$46*0.08),2)) -> + 12.73 | H47: =CONCATENATE("+ ",ROUND((G$46*0.08),2)) -> + 12.52
B48: ADD: VAT at retail | C48: =D47 -> + 12.53 | E48: =F47 -> + 12.73 | G48: =H47 -> + 12.52
B49: Retail Pump-Price under VAT regime | C49: =C$46+C$48+C$44+C$45 -> 169.13312 | D49: =D38+D47 -> 0.87 | E49: =E$46+E$48+E$44+E$45 -> 171.79351 | F49: =F38+F47 -> 0.88 | G49: =G$46+G$48+G$44+G$45 -> 168.98819 | H49: =H38+H47 -> 0.88
A51: EXPECTED IMPACT ON THE FINAL RETAIL PRICE COMPARED TO THE NON-VAT REGIME
B53: ERC PRICE UNDER NON-VAT REGIME | C53: =Mombasa!D26 -> 154.6121 | D53: =C9+C20+C21+C28+C42+0.16*C8+0.16*SUM(C24:C25) -> 153.9881 | E53: ='Breakdown for PMS, AGO & DPK'!E26 -> 160.05845 | G53: ='Breakdown for PMS, AGO & DPK'!F26 -> 157.48856
B54: PRICE DIFFERENCE | C54: =C49-C53 -> 14.521013 | D54: =C53-D53 -> 0.62400843 | E54: =E49-E53 -> 11.735058 | G54: =G49-G53 -> 11.499633
